Workbook
Name __bookmark_1: #REF!
Name __bookmark_1: #REF!
Name A: [1]BRACAL!#REF!
Name A: [1]BRACAL!#REF!
Name aA: [2]BRACAL!#REF!
Name aA: [2]BRACAL!#REF!
Name aaa: [2]BRACAL!#REF!
Name aaa: [2]BRACAL!#REF!
Name aaaa: #REF!
Name aaaa: #REF!
Name AB: [1]BRACAL!#REF!
Name AB: [1]BRACAL!#REF!
Name AC: #REF!
Name AC: #REF!
Name aewqeW: #REF!
Name aewqeW: #REF!
Name ajuizatxt: [3]Atualização!#REF!
Name alienacao: #REF!
Name alienacao: #REF!
Name ANALISTA: #REF! tabela9analista
Name ANALISTA: #REF! tabela9analista
Name Apoio: [4]PRJ!$AG$27:$AI$32
Name Área_Construída: #REF!
Name Área_Construída: #REF!
Name as: [2]BRACAL!#REF!
Name as: [2]BRACAL!#REF!
Name asa: [2]BRACAL!#REF!
Name asa: [2]BRACAL!#REF!
Name asd: [2]BRACAL!#REF!
Name asd: [2]BRACAL!#REF!
Name asdf: [2]BRACAL!#REF!
Name asdf: [2]BRACAL!#REF!
Name atualizatxt: [3]Atualização!#REF!
Name b: [1]BRACAL!#REF!
Name ba: [1]BRACAL!#REF!
Name base: #REF!
Name bb: [2]BRACAL!#REF!
Name bb: [2]BRACAL!#REF!
Name bbb: [1]BRACAL!#REF!
Name bbb: [1]BRACAL!#REF!
Name bbbb: [2]BRACAL!#REF!
Name bbbb: [2]BRACAL!#REF!
Name bbbbn: [2]BRACAL!#REF!
Name bbbbn: [2]BRACAL!#REF!
Name bbbn: [1]BRACAL!#REF!
Name bColat: [5]Mult_Exec!$C$12
Name Bem: #REF!
Name Bem: #REF!
Name bm: [2]BRACAL!#REF!
Name bm: [2]BRACAL!#REF!
Name bn: [2]BRACAL!#REF!
Name bn: [2]BRACAL!#REF!
Name C_Node_Total: [6]RECORD!$C$2
Name Chart_Value_Basis: [6]TORNADO!$B$2
Name Cidades: #REF!
Name Cidades: #REF!
Name CN_9_7: #REF!
Name CN_9_7: #REF!
Name CN_9_7_LB_1_Val: #REF!
Name CN_9_7_LB_1_Val: #REF!

Sheet Resumo Imóveis 2 - VENDAS
A1: 72.1
G2: =SUM(G5:G45) -> 21429554 | I2: =SUM(I5:I45) -> 17871567 | V2: =SUM(V5:V45) -> 26936102 | W2: =SUM(W5:W45) -> 19032102
B3: Ativos | F3: Regulatório | G3: Avaliação | AA3: 46092
B4: Mat. | C4: Tipo | D4: Tipologia | E4: Cidade | F4: Registrado? | G4: VF | H4: % Propriedade | I4: VF Líq. | J4: Tem proposta? | K4: Melhor Proposta (ativa) | L4: Comprador | M4: Obs | N4: Carta Adjudicação? | O4: Data Adjudicação | P4: Registro | Q4: Data Registro | R4: SPE | S4: Dt. Avaliação | T4: Valor Avaliação | U4: Valor Venda Forçada | V4: VM Liq | W4: VF Liq | X4: TABELA GI | Y4: Valor recebido / Proposta | Z4: Condições de Venda | AA4: Status atual
B5: 72157 | C5: Urbano | D5: Comercial | E5: Ribeirão Preto/SP | F5: Ok | G5: 1593000 | H5: 1 | I5: 1593000 | J5: - | K5: 3100000 | L5: - | M5: Vendido | N5: SIM | O5: 45917 | P5: Sim | Q5: 45968 | R5: SPE Comercial | S5: 14/08/2025 10:11 | T5: 2969000 | U5: 1781000 | V5: =T5*H5 -> 2969000 | W5: =U5*H5 -> 1781000 | X5: Vendido | Y5: =241607.9+2174471.15 -> 2416079 | Z5: Pago | AA5: Vendido
B6: 62872 | C6: Urbano | D6: Comercial | E6: Ribeirão Preto/SP | F6: Ok | G6: 533549 | H6: 1 | I6: 533549 | J6: - | K6: - | L6: - | M6: Vendido (em conjunto 62872 e 72157) | N6: SIM | O6: 45917 | P6: Sim | Q6: 45968 | R6: SPE Comercial | S6: 14/08/2025 10:16 | T6: 1002000 | U6: 701000 | V6: =T6*H6 -> 1002000 | W6: =U6*H6 -> 701000 | X6: Vendido | Y6: =68392.1+615528.85 -> 683920.95 | Z6: Pago | AA6: Vendido
B7: 83398 | C7: Urbano | D7: Comercial | E7: Ribeirão Preto/SP | F7: Ok | G7: 710900 | H7: 0.5 | I7: 355450 | J7: - | K7: - | L7: - | M7: - | N7: SIM | O7: 45834 | P7: Sim | Q7: 45968 | R7: SPE Comercial | S7: 19/08/2025 15:25 | T7: 643000 | U7: 457000 | V7: =T7*H7 -> 321500 | W7: =U7*H7 -> 228500 | X7: Vendido | Y7: 250000 | Z7: Pago | AA7: Vendido
B8: 23299 | C8: Urbano | D8: Comercial | E8: Ribeirão Preto/SP | F8: Ok | G8: 3833000 | H8: 1 | I8: 3833000 | J8: - | K8: - | L8: - | M8: - | N8: SIM | O8: 45834 | P8: Sim | Q8: 45925 | R8: SPE Comercial | S8: 14/08/2025 10:07 | T8: 7158000 | U8: 4796000 | V8: =T8*H8 -> 7158000 | W8: =U8*H8 -> 4796000 | X8: 6000000 | Y8: 6150000 | Z8: A vista | AA8: Aprovado - em escritura | AB8: vendido??
B9: 48207 | C9: Urbano | D9: Residencial | E9: Ribeirão Preto/SP | F9: Ok | G9: 2217000 | H9: 1 | I9: 2217000 | J9: - | K9: - | L9: - | M9: - | N9: SIM | O9: 45834 | P9: Sim | Q9: 45898 | R9: SPE Residencial | S9: 07/10/2025 17:44 | T9: 3074000 | U9: 2460000 | V9: =T9*H9 -> 3074000 | W9: =U9*H9 -> 2460000 | X9: 6000000 | Y9: - | Z9: - | AA9: Sem proposta | AF9: 1621
B10: 32744 | C10: Urbano | D10: Residencial | E10: Ribeirão Preto/SP | F10: Ok | G10: 980000 | H10: 1 | I10: 980000 | J10: - | K10: - | L10: - | M10: - | N10: SIM | O10: 45917 | P10: Sim | Q10: 46009 | R10: SPE Residencial | S10: 17/07/2025 17:22 | T10: 2741000 | U10: 1645000 | V10: =T10*H10 -> 2741000 | W10: =U10*H10 -> 1645000 | X10: 2750000 | Y10: - | Z10: - | AA10: Sem proposta | AF10: =11%*AF9 -> 178.31
B11: 5104 | C11: Urbano | D11: Comercial | E11: Ribeirão Preto/SP | F11: Ok | G11: 727000 | H11: 1 | I11: 727000 | J11: - | K11: - | L11: - | M11: - | N11: SIM | O11: 45917 | P11: Sim | Q11: 45971 | R11: SPE Comercial | S11: 19/12/2025 09:30 | T11: 1003000 | U11: 732000 | V11: =T11*H11 -> 1003000 | W11: =U11*H11 -> 732000 | X11: 1024000 | Y11: - | Z11: - | AA11: Sem proposta
B12: 76858 | C12: Urbano | D12: Comercial | E12: Ribeirão Preto/SP | F12: Ok | G12: 590500 | H12: 1 | I12: 590500 | J12: - | K12: - | L12: - | M12: - | N12: SIM | O12: 45834 | P12: Sim | Q12: 45916 | R12: SPE Comercial | S12: 08/07/2025 15:09 | T12: 672000 | U12: 470000 | V12: =T12*H12 -> 672000 | W12: =U12*H12 -> 470000 | X12: 672000 | Y12: - | Z12: - | AA12: Sem proposta
B13: 3417 | C13: Urbano | D13: Residencial | E13: Ribeirão Preto/SP | F13: Ok | G13: 462000 | H13: 1 | I13: 462000 | J13: - | K13: - | L13: - | M13: - | N13: SIM | O13: 45834 | P13: Sim | Q13: 46009 | R13: SPE Residencial | S13: 10/07/2025 11:07 | T13: 579000 | U13: 446000 | V13: =T13*H13 -> 579000 | W13: =U13*H13 -> 446000 | X13: 636900 | Y13: - | Z13: - | AA13: Sem proposta
B14: 5103 | C14: Urbano | D14: Comercial | E14: Ribeirão Preto/SP | F14: Ok | G14: 439000 | H14: 1 | I14: 439000 | J14: - | K14: - | L14: - | M14: - | N14: SIM | O14: 45917 | P14: Sim | Q14: 46008 | R14: SPE Comercial | S14: 13/01/2026 12:45 | T14: 536000 | U14: 391000 | V14: =T14*H14 -> 536000 | W14: =U14*H14 -> 391000 | X14: 571000 | Y14: - | Z14: - | AA14: Sem proposta
B15: 52218 | C15: Urbano | D15: Residencial | E15: Ribeirão Preto/SP | F15: Ok | G15: 436000 | H15: 1 | I15: 436000 | J15: - | K15: - | L15: - | M15: - | N15: SIM | O15: 45917 | P15: Sim | Q15: 46009 | R15: SPE Residencial | S15: 17/07/2025 17:27 | T15: 656000 | U15: 459000 | V15: =T15*H15 -> 656000 | W15: =U15*H15 -> 459000 | X15: 656000 | Y15: - | Z15: - | AA15: Sem proposta
B16: 149 | C16: Urbano | D16: Residencial | E16: Ribeirão Preto/SP | F16: Ok | G16: 311000 | H16: 0.33333333 | I16: 103666.67 | J16: - | K16: - | L16: - | M16: - | N16: SIM | O16: 45834 | P16: Sim | Q16: 46003 | R16: SPE Residencial | S16: 18/07/2025 09:51 | T16: 297000 | U16: 228000 | V16: =T16*H16 -> 99000 | W16: =U16*H16 -> 76000 | X16: 108900 | Y16: - | Z16: - | AA16: Sem proposta
B17: 78782 | C17: Urbano | D17: Residencial | E17: Ribeirão Preto/SP | F17: Ok | G17: 221000 | H17: 1 | I17: 221000 | J17: - | K17: - | L17: - | M17: - | N17: SIM | O17: 45834 | P17: Sim | Q17: 45940 | R17: SPE Residencial | S17: 13/01/2026 12:47 | T17: 308000 | U17: 237000 | V17: =T17*H17 -> 308000 | W17: =U17*H17 -> 237000 | X17: 180000 | Y17: - | Z17: - | AA17: Sem proposta
B18: 59250 | C18: Urbano | D18: Residencial | E18: Ribeirão Preto/SP | F18: Ok | G18: 160000 | H18: 1 | I18: 160000 | J18: - | K18: - | L18: - | M18: - | N18: SIM | O18: 45834 | P18: Sim | Q18: 45968 | R18: SPE Residencial | S18: 19/11/2025 10:09 | T18: 232000 | U18: 165000 | V18: =T18*H18 -> 232000 | W18: =U18*H18 -> 165000 | X18: 190000 | Y18: - | Z18: - | AA18: Sem proposta
B19: 78780 | C19: Urbano | D19: Residencial | E19: Ribeirão Preto/SP | F19: Ok | G19: 154000 | H19: 1 | I19: 154000 | J19: - | K19: - | L19: - | M19: - | N19: SIM | O19: 45834 | P19: Sim | Q19: 45898 | R19: SPE Residencial | S19: 08/07/2025 14:00 | T19: 184000 | U19: 142000 | V19: =T19*H19 -> 184000 | W19: =U19*H19 -> 142000 | X19: 180000 | Y19: - | Z19: - | AA19: Sem proposta
B20: 78781 | C20: Urbano | D20: Residencial | E20: Ribeirão Preto/SP | F20: Ok | G20: 154000 | H20: 1 | I20: 154000 | J20: - | K20: - | L20: - | M20: - | N20: SIM | O20: 45834 | P20: Sim | Q20: 45898 | R20: SPE Residencial | S20: 10/07/2025 10:59 | T20: 184000 | U20: 141000 | V20: =T20*H20 -> 184000 | W20: =U20*H20 -> 141000 | X20: 180000 | Y20: - | Z20: - | AA20: Sem proposta
B21: 78783 | C21: Urbano | D21: Residencial | E21: Ribeirão Preto/SP | F21: Ok | G21: 154000 | H21: 1 | I21: 154000 | J21: - | K21: - | L21: - | M21: - | N21: SIM | O21: 45834 | P21: Sim | Q21: 45898 | R21: SPE Residencial | S21: 08/07/2025 14:21 | T21: 184000 | U21: 142000 | V21: =T21*H21 -> 184000 | W21: =U21*H21 -> 142000 | X21: 180000 | Y21: - | Z21: - | AA21: Sem proposta
B22: 78784 | C22: Urbano | D22: Residencial | E22: Ribeirão Preto/SP | F22: Ok | G22: 154000 | H22: 1 | I22: 154000 | J22: - | K22: - | L22: - | M22: - | N22: SIM | O22: 45834 | P22: Sim | Q22: 45898 | R22: SPE Residencial | S22: 08/07/2025 14:24 | T22: 184000 | U22: 142000 | V22: =T22*H22 -> 184000 | W22: =U22*H22 -> 142000 | X22: 180000 | Y22: - | Z22: - | AA22: Sem proposta
... B29: 102754 | C29: Urbano | D29: Residencial | E29: Ribeirão Preto/SP | F29: Ok | G29: 136000 | H29: 1 | I29: 136000 | J29: - | K29: - | L29: - | M29: - | N29: SIM | O29: 45834 | P29: Sim | Q29: 45971 | R29: SPE Residencial | S29: 08/10/2025 10:16 | T29: 168000 | U29: 118000 | V29: =T29*H29 -> 168000 | W29: =U29*H29 -> 118000 | X29: 180000 | Y29: - | Z29: - | AA29: Sem proposta
B30: 36052 | C30: Urbano | D30: Comercial | E30: Ribeirão Preto/SP | F30: Ok | G30: 123000 | H30: 1 | I30: 123000 | J30: - | K30: - | L30: - | M30: - | N30: NÃO | O30: - | P30: Não | Q30: - | R30: SPE Comercial | S30: 16/01/2026 18:15 | T30: 159000 | U30: 122000 | V30: =T30*H30 -> 159000 | W30: =U30*H30 -> 122000 | X30: 165000 | Y30: - | Z30: - | AA30: Sem proposta
B31: 36053 | C31: Urbano | D31: Comercial | E31: Ribeirão Preto/SP | F31: Ok | G31: 123000 | H31: 1 | I31: 123000 | J31: - | K31: - | L31: - | M31: - | N31: NÃO | O31: - | P31: Não | Q31: - | R31: SPE Comercial | S31: 13/01/2026 12:49 | T31: 137000 | U31: 105000 | V31: =T31*H31 -> 137000 | W31: =U31*H31 -> 105000 | X31: 165000 | Y31: - | Z31: - | AA31: Sem proposta
B32: 96154 | C32: Urbano | D32: Residencial | E32: Ribeirão Preto/SP | F32: Ok | G32: 109000 | H32: 1 | I32: 109000 | J32: - | K32: - | L32: - | M32: - | N32: SIM | O32: 45834 | P32: Sim | Q32: 45915 | R32: SPE Residencial | S32: 10/07/2025 10:48 | T32: 187000 | U32: 131000 | V32: =T32*H32 -> 187000 | W32: =U32*H32 -> 131000 | X32: 169760 | Y32: - | Z32: - | AA32: Sem proposta
B33: 96155 | C33: Urbano | D33: Residencial | E33: Ribeirão Preto/SP | F33: Ok | G33: 109000 | H33: 1 | I33: 109000 | J33: - | K33: - | L33: - | M33: - | N33: SIM | O33: 45834 | P33: Sim | Q33: 45915 | R33: SPE Residencial | S33: 10/07/2025 10:46 | T33: 187000 | U33: 131000 | V33: =T33*H33 -> 187000 | W33: =U33*H33 -> 131000 | X33: 169760 | Y33: - | Z33: - | AA33: Sem proposta
B34: 96157 | C34: Urbano | D34: Residencial | E34: Ribeirão Preto/SP | F34: Ok | G34: 62000 | H34: 1 | I34: 62000 | J34: - | K34: - | L34: - | M34: - | N34: SIM | O34: 45834 | P34: Sim | Q34: 45915 | R34: SPE Residencial | S34: 10/07/2025 17:48 | T34: 101000 | U34: 65000 | V34: =T34*H34 -> 101000 | W34: =U34*H34 -> 65000 | X34: 138240 | Y34: - | Z34: - | AA34: Sem proposta
B35: 96156 | C35: Urbano | D35: Residencial | E35: Ribeirão Preto/SP | F35: Ok | G35: 62000 | H35: 1 | I35: 62000 | J35: - | K35: - | L35: - | M35: - | N35: SIM | O35: 45834 | P35: Sim | Q35: 45915 | R35: SPE Residencial | S35: 14/07/2025 22:16 | T35: 101000 | U35: 65000 | V35: =T35*H35 -> 101000 | W35: =U35*H35 -> 65000 | X35: 138240 | Y35: - | Z35: - | AA35: Sem proposta
B36: 96158 | C36: Urbano | D36: Comercial | E36: Ribeirão Preto/SP | F36: Ok | G36: 127800 | H36: 1 | I36: 127800 | J36: - | K36: - | L36: - | M36: - | N36: SIM | O36: 45834 | P36: Sim | Q36: 45915 | R36: SPE Comercial | S36: 10/07/2025 11:16 | T36: 144000 | U36: 101000 | V36: =T36*H36 -> 144000 | W36: =U36*H36 -> 101000 | X36: 158400 | Y36: - | Z36: - | AA36: Sem proposta
B37: 116945 | C37: Urbano | D37: Residencial | E37: Ilha Comprida/SP | F37: Ok | G37: 0 | H37: 1 | I37: 0 | J37: - | K37: - | L37: - | M37: - | N37: SIM | O37: 45834 | P37: Sim | Q37: 45902 | R37: SPE Residencial | S37: 21/10/2025 09:53 | T37: 15000 | U37: 0 | V37: =T37*H37 -> 15000 | W37: =U37*H37 -> 0 | X37: 15000 | Y37: - | Z37: - | AA37: Sem proposta
B38: 116946 | C38: Urbano | D38: Residencial | E38: Ilha Comprida/SP | F38: Ok | G38: 0 | H38: 1 | I38: 0 | J38: - | K38: - | L38: - | M38: - | N38: SIM | O38: 45834 | P38: Sim | Q38: 45902 | R38: SPE Residencial | S38: 21/10/2025 09:54 | T38: 15000 | U38: 0 | V38: =T38*H38 -> 15000 | W38: =U38*H38 -> 0 | X38: 15000 | Y38: - | Z38: - | AA38: Sem proposta
B39: 6660 | C39: Urbano | D39: Comercial | E39: Ribeirão Preto/SP | F39: Ok | G39: 1923389.1 | H39: 0.33333333 | I39: 641129.69 | J39: - | K39: - | L39: - | M39: - | N39: SIM | O39: 45834 | P39: Sim | Q39: 46010 | R39: SPE Comercial | S39: 17/10/2023 12:01 | T39: 1923389.1 | U39: 1923389.1 | V39: =T39*H39 -> 641129.69 | W39: =U39*H39 -> 641129.69 | X39: Bloqueado para time comercial | Y39: - | Z39: - | AA39: n/a
B40: 11055 | C40: Urbano | D40: Comercial | E40: Ribeirão Preto/SP | F40: Ok | G40: 1832137.3 | H40: 0.33333333 | I40: 610712.44 | J40: - | K40: - | L40: - | M40: - | N40: SIM | O40: 45834 | P40: Sim | Q40: 46003 | R40: SPE Comercial | S40: 17/10/2023 11:55 | T40: 1832137.3 | U40: 1832137.3 | V40: =T40*H40 -> 610712.44 | W40: =U40*H40 -> 610712.44 | X40: Bloqueado para time comercial | Y40: - | Z40: - | AA40: n/a
B41: 11054 | C41: Urbano | D41: Comercial | E41: Ribeirão Preto/SP | F41: Ok | G41: 737278.6 | H41: 0.33333333 | I41: 245759.53 | J41: - | K41: - | L41: - | M41: - | N41: SIM | O41: 45834 | P41: Sim | Q41: 46003 | R41: SPE Comercial | S41: 17/10/2023 12:09 | T41: 737278.6 | U41: 737278.6 | V41: =T41*H41 -> 245759.53 | W41: =U41*H41 -> 245759.53 | X41: Bloqueado para time comercial | Y41: - | Z41: - | AA41: n/a
B42: 6529 | C42: Urbano | D42: Residencial | E42: Ribeirão Preto/SP | F42: Ok | G42: 230000 | H42: 1 | I42: 230000 | J42: - | K42: - | L42: - | M42: - | N42: SIM | O42: 45834 | P42: Sim | Q42: 45898 | R42: SPE Residencial | S42: 07/10/2025 10:19 | T42: 418000 | U42: 293000 | V42: =T42*H42 -> 418000 | W42: =U42*H42 -> 293000 | X42: Bloqueado para time comercial | Y42: - | Z42: - | AA42: n/a
B43: 53194 | C43: Urbano | D43: Residencial | E43: Ribeirão Preto/SP | F43: Ok | G43: 222000 | H43: 1 | I43: 222000 | J43: - | K43: - | L43: - | M43: - | N43: SIM | O43: 45834 | P43: Sim | Q43: 45898 | R43: SPE Residencial | S43: 07/10/2025 10:18 | T43: 414000 | U43: 290000 | V43: =T43*H43 -> 414000 | W43: =U43*H43 -> 290000 | X43: Bloqueado para time comercial | Y43: - | Z43: - | AA43: n/a
B44: 6549 | C44: Urbano | D44: Residencial | E44: Ribeirão Preto/SP | F44: Ok | G44: 822000 | H44: 1 | I44: 822000 | J44: - | K44: - | L44: - | M44: - | N44: SIM | O44: 45834 | P44: Sim | Q44: 46010 | R44: SPE Residencial | S44: 17/07/2025 17:13 | T44: 0 | U44: 0 | V44: =T44*H44 -> 0 | W44: =U44*H44 -> 0 | X44: Bloqueado para time comercial | Y44: - | Z44: - | AA44: n/a
B45: 96153 | C45: Urbano | D45: Residencial | E45: Ribeirão Preto/SP | F45: Ok | G45: 109000 | H45: 1 | I45: 109000 | J45: - | K45: - | L45: - | M45: - | N45: SIM | O45: 45834 | P45: Não | Q45: - | R45: SPE Residencial | S45: 10/07/2025 10:44 | T45: 187000 | U45: 131000 | V45: =T45*H45 -> 187000 | W45: =U45*H45 -> 131000 | X45: Bloqueado para time comercial | Y45: - | Z45: - | AA45: n/a
G46: =SUM(G5:G45) -> 21429554 | I46: =SUM(I5:I45) -> 17871567 | K46: =SUM(K5:K45) -> 3100000

Sheet Pgto Alugueis Processo
B2: Mat. | C2: Data | D2: Mês Aluguel | E2: Dt Adjudicação | F2: Valor Depositado | H2: Apto
B3: 78783 | C3: 45923 | D3: junho | E3: 45834 | F3: 306.38 | H3: 22
B4: 78783 | C4: 45923 | D4: julho | E4: 45834 | F4: 276.46 | H4: 22
B5: 78783 | C5: 45923 | D5: agosto | E5: 45834 | F5: 52.35 | H5: 22
B6: 78783 | C6: 45923 | D6: setembro | E6: 45834 | F6: 14.95 | H6: 22
B7: 78785 | C7: 45923 | D7: junho | E7: 45834 | F7: 973.31 | H7: 32
B8: 78785 | C8: 45923 | D8: julho | E8: 45834 | F8: 973.31 | H8: 32
B9: 78785 | C9: 45923 | D9: agosto | E9: 45834 | F9: 973.31 | H9: 32
B10: 78785 | C10: 45923 | D10: setembro | E10: 45834 | F10: 973.31 | H10: 32
B11: 78786 | C11: 45923 | D11: junho | E11: 45834 | F11: 2015.69 | H11: 41
B12: 78786 | C12: 45923 | D12: agosto | E12: 45834 | F12: 949.77 | H12: 41
B13: 78787 | C13: 45923 | D13: junho | E13: 45834 | F13: 827.87 | H13: 42
B14: 78787 | C14: 45923 | D14: julho | E14: 45834 | F14: 827.87 | H14: 42
... B16: 78787 | C16: 45923 | D16: setembro | E16: 45834 | F16: 827.87 | H16: 42
B17: TOTAL | F17: =SUM(F3:F16) -> 10470.32

Sheet Pgto Alugueis SPE RESIDENCIAL
B2: Valor | C2: Data Recebimento | D2: Imóvel
B3: 973.31 | C3: 45973 | D3: 3039
B4: 851.3 | C4: 45978 | D4: 3026
B5: 577.87 | C5: 45982 | D5: 3150
B6: 1065.92 | C6: 45986 | D6: 3012
B7: 956.09 | C7: 45987 | D7: 3367
B8: 973.31 | C8: 46002 | D8: 3039
B9: 851.3 | C9: 46009 | D9: 3026
B10: 827.27 | C10: 46380 | D10: 3150
B11: 956.09 | C11: 46020 | D11: 3367
B12: 975.8 | C12: 46035 | D12: 3039
B13: 853.8 | C13: 46041 | D13: 3026
B14: 1419.51 | C14: 46048 | D14: 3150
... B18: 3808.24 | C18: 45965 | D18: 3012

Sheet Resumo Imóveis
M2: EM REVISÃO
L3: =SUM(L5:L45) -> 23939000 | M3: =SUM(M5:M45) -> 21429554 | O3: =SUM(O5:O45) -> 17871567
B4: Origem | C4: Matrícula | D4: Carta Adjudicação | E4: Procuradoria | F4: Classe Imóvel | G4: Tipologia | H4: Cartório | I4: Cidade | J4: Dt. Avaliação | K4: Nível | L4: Valor FCC | M4: VF | N4: % Propriedade | O4: VF Líq. | R4: DECISÃO 26/06/2025
A5: Previsão 08/10 | B5: FCC | C5: 23299 | D5: 1 | E5: =IFERROR(VLOOKUP(C5,$U$22:$U$27,1,0),"-") -> - | F5: Imóvel Urbano | G5: Comercial | H5: 2º CRI | I5: Ribeirão Preto/SP | J5: 45189.369 | K5: Nível 2 | L5: =VLOOKUP(C5,[14]Planilha1!M:N,2,0) -> 6683000 | M5: 3833000 | N5: 1 | O5: =N5*M5 -> 3833000
A6: Registrado | B6: FCC | C6: 48207 | D6: 1 | E6: =IFERROR(VLOOKUP(C6,$U$22:$U$27,1,0),"-") -> - | F6: Imóvel Urbano | G6: Residencial | H6: 2º CRI | I6: Ribeirão Preto/SP | J6: 45804.5 | K6: Nível 3 | L6: =VLOOKUP(C6,[14]Planilha1!M:N,2,0) -> 2725000 | M6: 2217000 | N6: 1 | O6: =N6*M6 -> 2217000
A7: Previsão 05/09 | B7: FCC | C7: 6660 | D7: 1 | E7: =IFERROR(VLOOKUP(C7,$U$22:$U$27,1,0),"-") -> - | F7: Imóvel Urbano | G7: Comercial | H7: 2º CRI | I7: Ribeirão Preto/SP | J7: 45211.867 | K7: Nível 3 | L7: =VLOOKUP(C7,[14]Planilha1!M:N,2,0) -> 4316000 | M7: 1923389.1 | N7: 0.33333333 | O7: =N7*M7 -> 641129.69
A8: Previsão 05/09 | B8: FCC | C8: 11055 | D8: 1 | E8: =IFERROR(VLOOKUP(C8,$U$22:$U$27,1,0),"-") -> - | F8: Imóvel Urbano | G8: Comercial | H8: 2º CRI | I8: Ribeirão Preto/SP | J8: 45211.867 | K8: Nível 3 | L8: =VLOOKUP(C8,[14]Planilha1!M:N,2,0) -> 0 | M8: 1832137.3 | N8: 0.33333333 | O8: =N8*M8 -> 610712.44 | U8: 33/41
A9: Previsão 05/09 | B9: FCC | C9: 11054 | D9: 1 | E9: =IFERROR(VLOOKUP(C9,$U$22:$U$27,1,0),"-") -> - | F9: Imóvel Urbano | G9: Comercial | H9: 2º CRI | I9: Ribeirão Preto/SP | J9: 45211.867 | K9: Nível 3 | L9: =VLOOKUP(C9,[14]Planilha1!M:N,2,0) -> 0 | M9: 737278.6 | N9: 0.33333333 | O9: =N9*M9 -> 245759.53
A10: Sem Carta | B10: FCC | C10: 72157 | D10: - | E10: 1 | F10: Imóvel Urbano | G10: Comercial | H10: 2º CRI | I10: Ribeirão Preto/SP | J10: 45190.7 | K10: Nível 3 | L10: =VLOOKUP(C10,[14]Planilha1!M:N,2,0) -> 1704000 | M10: 1593000 | N10: 1 | O10: =N10*M10 -> 1593000 | P10: vendido | R10: ENF SPE COMERCIAL LTDA
A11: Sem Carta | B11: FCC | C11: 32744 | D11: - | E11: 1 | F11: Imóvel Urbano | G11: Residencial | H11: 1º CRI | I11: Ribeirão Preto/SP | J11: 45117.595 | K11: Nível 2 | L11: =VLOOKUP(C11,[14]Planilha1!M:N,2,0) -> 1026000 | M11: 980000 | N11: 1 | O11: =N11*M11 -> 980000 | R11: 23299 | S11: 3833000 | U11: Tipologia | V11: Total | W11: Liberado | X11: %
A12: Sem Carta | B12: FCC | C12: 5104 | D12: - | E12: 1 | F12: Imóvel Urbano | G12: Comercial | H12: 1º CRI | I12: Ribeirão Preto/SP | J12: 45117.623 | K12: Nível 2 | L12: =VLOOKUP(C12,[14]Planilha1!M:N,2,0) -> 717000 | M12: 727000 | N12: 1 | O12: =N12*M12 -> 727000 | R12: 6660 | S12: 641129.69 | U12: Comercial | V12: =SUMIF($G$4:$G$45,U12,$O$4:$O$45) -> 9942900.7 | W12: =S18 -> 6404351.7 | X12: =W12/V12 -> 0.64411301
A13: Previsão 03/10 | B13: FCC | C13: 76858 | D13: 1 | E13: =IFERROR(VLOOKUP(C13,$U$22:$U$27,1,0),"-") -> - | F13: Imóvel Urbano | G13: Comercial | H13: 1º CRI | I13: Ribeirão Preto/SP | J13: 45222.679 | K13: Nível 2 | L13: =VLOOKUP(C13,[14]Planilha1!M:N,2,0) -> 778000 | M13: 590500 | N13: 1 | O13: =N13*M13 -> 590500 | R13: 11055 | S13: 610712.44 | U13: Residencial | V13: =SUMIF($G$4:$G$45,U13,$O$4:$O$45) -> 7928666.7 | W13: =S48 -> 6512666.7 | X13: =W13/V13 -> 0.82140755
A14: Sem Carta | B14: FCC | C14: 62872 | D14: - | E14: 1 | F14: Imóvel Urbano | G14: Comercial | H14: 2º CRI | I14: Ribeirão Preto/SP | J14: 45190.675 | K14: Nível 3 | L14: =VLOOKUP(C14,[14]Planilha1!M:N,2,0) -> 501000 | M14: 533549 | N14: 1 | O14: =N14*M14 -> 533549 | P14: vendido | R14: 11054 | S14: 245759.53 | U14: Total | V14: =SUM(V12:V13) -> 17871567 | W14: =SUM(W12:W13) -> 12917018 | X14: =W14/V14 -> 0.72276919
A15: Previsão 29/09 | B15: FCC | C15: 3417 | D15: 1 | E15: =IFERROR(VLOOKUP(C15,$U$22:$U$27,1,0),"-") -> - | F15: Imóvel Urbano | G15: Residencial | H15: 1º CRI | I15: Ribeirão Preto/SP | J15: 45219.681 | K15: Nível 2 | L15: =VLOOKUP(C15,[14]Planilha1!M:N,2,0) -> 835000 | M15: 462000 | N15: 1 | O15: =N15*M15 -> 462000 | R15: 83398 | S15: 355450
A16: Sem Carta | B16: FCC | C16: 5103 | D16: - | E16: 1 | F16: Imóvel Urbano | G16: Comercial | H16: 1º CRI | I16: Ribeirão Preto/SP | J16: 45219.687 | K16: Nível 2 | L16: =VLOOKUP(C16,[14]Planilha1!M:N,2,0) -> 637000 | M16: 439000 | N16: 1 | O16: =N16*M16 -> 439000 | R16: 76858 | S16: 590500 | V16: =V14-W14 -> 4954549
A17: Sem Carta | B17: FCC | C17: 52218 | D17: - | E17: 1 | F17: Imóvel Urbano | G17: Residencial | H17: 2º CRI | I17: Ribeirão Preto/SP | J17: 45219.716 | K17: Nível 2 | L17: =VLOOKUP(C17,[14]Planilha1!M:N,2,0) -> 608000 | M17: 436000 | N17: 1 | O17: =N17*M17 -> 436000 | R17: 96158 | S17: 127800
A18: Previsão 26/09 | B18: FCC | C18: 149 | D18: 1 | E18: =IFERROR(VLOOKUP(C18,$U$22:$U$27,1,0),"-") -> - | F18: Imóvel Urbano | G18: Residencial | H18: 2º CRI | I18: Ribeirão Preto/SP | J18: 45219.675 | K18: Nível 2 | L18: =VLOOKUP(C18,[14]Planilha1!M:N,2,0) -> 322000 | M18: 311000 | N18: 0.33333333 | O18: =N18*M18 -> 103666.67 | R18: 7 | S18: 6404351.7
A19: Registrado | B19: FCC | C19: 6529 | D19: 1 | E19: =IFERROR(VLOOKUP(C19,$U$22:$U$27,1,0),"-") -> - | F19: Imóvel Urbano | G19: Residencial | H19: 2º CRI | I19: Ribeirão Preto/SP | J19: 45219.694 | K19: Nível 2 | L19: =VLOOKUP(C19,[14]Planilha1!M:N,2,0) -> 269000 | M19: 230000 | N19: 1 | O19: =N19*M19 -> 230000
A20: Registrado | B20: FCC | C20: 53194 | D20: 1 | E20: =IFERROR(VLOOKUP(C20,$U$22:$U$27,1,0),"-") -> - | F20: Imóvel Urbano | G20: Residencial | H20: 2º CRI | I20: Ribeirão Preto/SP | J20: 45219.722 | K20: Nível 2 | L20: =VLOOKUP(C20,[14]Planilha1!M:N,2,0) -> 265000 | M20: 222000 | N20: 1 | O20: =N20*M20 -> 222000
A21: Previsão 26/09 | B21: FCC | C21: 78782 | D21: 1 | E21: =IFERROR(VLOOKUP(C21,$U$22:$U$27,1,0),"-") -> - | F21: Imóvel Urbano | G21: Residencial | H21: 2º CRI | I21: Ribeirão Preto/SP | J21: 45106.478 | K21: Nível 2 | L21: =VLOOKUP(C21,[14]Planilha1!M:N,2,0) -> 177625 | M21: 221000 | N21: 1 | O21: =N21*M21 -> 221000 | R21: ENF SPE RESIDENCIAL LTDA | U21: PROCURADORIA | W21: CONDOMÍNIO
A22: Previsão 26/09 | B22: FCC | C22: 59250 | D22: 1 | E22: =IFERROR(VLOOKUP(C22,$U$22:$U$27,1,0),"-") -> - | F22: Imóvel Urbano | G22: Residencial | H22: 2º CRI | I22: Ribeirão Preto/SP | J22: 45219.672 | K22: Nível 2 | L22: =VLOOKUP(C22,[14]Planilha1!M:N,2,0) -> 247000 | M22: 160000 | N22: 1 | O22: =N22*M22 -> 160000 | R22: 48207 | S22: 2217000 | U22: 5104 | V22: =VLOOKUP(U22,$C:$P,13,0) -> 727000 | W22: 36052 | X22: =VLOOKUP(W22,$C:$P,13,0) -> 123000
A23: Registrado | B23: FCC | C23: 78780 | D23: 1 | E23: =IFERROR(VLOOKUP(C23,$U$22:$U$27,1,0),"-") -> - | F23: Imóvel Urbano | G23: Residencial | H23: 2º CRI | I23: Ribeirão Preto/SP | J23: 45219.736 | K23: Nível 2 | L23: =VLOOKUP(C23,[14]Planilha1!M:N,2,0) -> 177625 | M23: 154000 | N23: 1 | O23: =N23*M23 -> 154000 | R23: 6529 | S23: 230000 | U23: 5103 | V23: =VLOOKUP(U23,$C:$P,13,0) -> 439000 | W23: 36053 | X23: =VLOOKUP(W23,$C:$P,13,0) -> 123000
A24: Registrado | B24: FCC | C24: 78781 | D24: 1 | E24: =IFERROR(VLOOKUP(C24,$U$22:$U$27,1,0),"-") -> - | F24: Imóvel Urbano | G24: Residencial | H24: 2º CRI | I24: Ribeirão Preto/SP | J24: 45219.736 | K24: Nível 2 | L24: =VLOOKUP(C24,[14]Planilha1!M:N,2,0) -> 177625 | M24: 154000 | N24: 1 | O24: =N24*M24 -> 154000 | R24: 6549 | S24: 822000 | U24: 52218 | V24: =VLOOKUP(U24,$C:$P,13,0) -> 436000 | X24: =SUM(X22:X23) -> 246000
A25: Registrado | B25: FCC | C25: 78783 | D25: 1 | E25: =IFERROR(VLOOKUP(C25,$U$22:$U$27,1,0),"-") -> - | F25: Imóvel Urbano | G25: Residencial | H25: 2º CRI | I25: Ribeirão Preto/SP | J25: 45219.736 | K25: Nível 2 | L25: =VLOOKUP(C25,[14]Planilha1!M:N,2,0) -> 177625 | M25: 154000 | N25: 1 | O25: =N25*M25 -> 154000 | R25: 3417 | S25: 462000 | U25: 72157 | V25: =VLOOKUP(U25,$C:$P,13,0) -> 1593000
A26: Registrado | B26: FCC | C26: 78784 | D26: 1 | E26: =IFERROR(VLOOKUP(C26,$U$22:$U$27,1,0),"-") -> - | F26: Imóvel Urbano | G26: Residencial | H26: 2º CRI | I26: Ribeirão Preto/SP | J26: 45219.736 | K26: Nível 2 | L26: =VLOOKUP(C26,[14]Planilha1!M:N,2,0) -> 177625 | M26: 154000 | N26: 1 | O26: =N26*M26 -> 154000 | R26: 149 | S26: 103666.67 | U26: 62872 | V26: =VLOOKUP(U26,$C:$P,13,0) -> 533549
A27: Registrado | B27: FCC | C27: 78785 | D27: 1 | E27: =IFERROR(VLOOKUP(C27,$U$22:$U$27,1,0),"-") -> - | F27: Imóvel Urbano | G27: Residencial | H27: 2º CRI | I27: Ribeirão Preto/SP | J27: 45219.736 | K27: Nível 2 | L27: =VLOOKUP(C27,[14]Planilha1!M:N,2,0) -> 177625 | M27: 154000 | N27: 1 | O27: =N27*M27 -> 154000 | R27: 53194 | S27: 222000 | U27: 32744 | V27: =VLOOKUP(U27,$C:$P,13,0) -> 980000
A28: Registrado | B28: FCC | C28: 78786 | D28: 1 | E28: =IFERROR(VLOOKUP(C28,$U$22:$U$27,1,0),"-") -> - | F28: Imóvel Urbano | G28: Residencial | H28: 2º CRI | I28: Ribeirão Preto/SP | J28: 45219.737 | K28: Nível 2 | L28: =VLOOKUP(C28,[14]Planilha1!M:N,2,0) -> 177625 | M28: 154000 | N28: 1 | O28: =N28*M28 -> 154000 | R28: 78782 | S28: 221000 | V28: =SUM(V22:V27) -> 4708549
A29: Registrado | B29: FCC | C29: 78787 | D29: 1 | E29: =IFERROR(VLOOKUP(C29,$U$22:$U$27,1,0),"-") -> - | F29: Imóvel Urbano | G29: Residencial | H29: 2º CRI | I29: Ribeirão Preto/SP | J29: 45219.737 | K29: Nível 2 | L29: =VLOOKUP(C29,[14]Planilha1!M:N,2,0) -> 177625 | M29: 154000 | N29: 1 | O29: =N29*M29 -> 154000 | R29: 59250 | S29: 160000
A30: Registrado | B30: FCC | C30: 59252 | D30: 1 | E30: =IFERROR(VLOOKUP(C30,$U$22:$U$27,1,0),"-") -> - | F30: Imóvel Urbano | G30: Residencial | H30: 2º CRI | I30: Ribeirão Preto/SP | J30: 45219.731 | K30: Nível 2 | L30: =VLOOKUP(C30,[14]Planilha1!M:N,2,0) -> 186500 | M30: 137000 | N30: 1 | O30: =N30*M30 -> 137000 | R30: 78780 | S30: 154000 | W30: #Mat. | X30: VF (R$ )
A31: Registrado | B31: FCC | C31: 59251 | D31: 1 | E31: =IFERROR(VLOOKUP(C31,$U$22:$U$27,1,0),"-") -> - | F31: Imóvel Urbano | G31: Residencial | H31: 2º CRI | I31: Ribeirão Preto/SP | J31: 45219.728 | K31: Nível 2 | L31: =VLOOKUP(C31,[14]Planilha1!M:N,2,0) -> 186500 | M31: 137000 | N31: 1 | O31: =N31*M31 -> 137000 | R31: 78781 | S31: 154000 | V31: Cartas Expedidas | W31: 33 | X31: =W14 -> 12917018 | Y31: =X31/$X$38 -> 0.72276919
A32: Previsão 26/09 | B32: FCC | C32: 102753 | D32: 1 | E32: =IFERROR(VLOOKUP(C32,$U$22:$U$27,1,0),"-") -> - | F32: Imóvel Urbano | G32: Residencial | H32: 1º CRI | I32: Ribeirão Preto/SP | J32: 45117.481 | K32: Nível 2 | L32: =VLOOKUP(C32,[14]Planilha1!M:N,2,0) -> 123500 | M32: 136000 | N32: 1 | O32: =N32*M32 -> 136000 | R32: 78783 | S32: 154000 | V32: Imóvel 96.153 | W32: 1 | X32: 109000 | Y32: =X32/$X$38 -> 0.0060990733
A33: Previsão 26/09 | B33: FCC | C33: 102754 | D33: 1 | E33: =IFERROR(VLOOKUP(C33,$U$22:$U$27,1,0),"-") -> - | F33: Imóvel Urbano | G33: Residencial | H33: 1º CRI | I33: Ribeirão Preto/SP | J33: 45117.485 | K33: Nível 2 | L33: =VLOOKUP(C33,[14]Planilha1!M:N,2,0) -> 123500 | M33: 136000 | N33: 1 | O33: =N33*M33 -> 136000 | R33: 78784 | S33: 154000
A34: Sem Carta | B34: FCC | C34: 36052 | D34: - | E34: Condomínio | F34: Imóvel Urbano | G34: Comercial | H34: 2º CRI | I34: Ribeirão Preto/SP | J34: 45219.701 | K34: Nível 2 | L34: =VLOOKUP(C34,[14]Planilha1!M:N,2,0) -> 132500 | M34: 123000 | N34: 1 | O34: =N34*M34 -> 123000 | R34: 78785 | S34: 154000 | V34: Cartas Pendentes | W34: =SUM(W35:W36) -> 8 | X34: =SUM(X35:X36) -> 4954549 | Y34: =X34/$X$38 -> 0.27723081
A35: Sem Carta | B35: FCC | C35: 36053 | D35: - | E35: Condomínio | F35: Imóvel Urbano | G35: Comercial | H35: 2º CRI | I35: Ribeirão Preto/SP | J35: 45219.713 | K35: Nível 2 | L35: =VLOOKUP(C35,[14]Planilha1!M:N,2,0) -> 132500 | M35: 123000 | N35: 1 | O35: =N35*M35 -> 123000 | R35: 78786 | S35: 154000 | V35: Procuradoria | W35: 6 | X35: =V28 -> 4708549
A36: Previsão 26/09 | B36: Posterior | C36: 6549 | D36: 1 | E36: =IFERROR(VLOOKUP(C36,$U$22:$U$27,1,0),"-") -> - | F36: Imóvel Urbano | G36: Residencial | H36: 1º CRI | I36: Ribeirão Preto/SP | J36: 45117.726 | K36: Nível 2 | L36: n/a | M36: 822000 | N36: 1 | O36: =N36*M36 -> 822000 | R36: 78787 | S36: 154000 | V36: Condomínio | W36: 2 | X36: =X24 -> 246000
A37: Previsão 05/09 | B37: Posterior | C37: 83398 | D37: 1 | E37: =IFERROR(VLOOKUP(C37,$U$22:$U$27,1,0),"-") -> - | F37: Imóvel Urbano | G37: Comercial | H37: 2º CRI | I37: Ribeirão Preto/SP | J37: 45112.497 | K37: Nível 2 | L37: n/a | M37: 710900 | N37: 0.5 | O37: =N37*M37 -> 355450 | R37: 59252 | S37: 137000
A38: Sem Previsão | B38: Posterior | C38: 96153 | D38: 1 | E38: =IFERROR(VLOOKUP(C38,$U$22:$U$27,1,0),"-") -> - | F38: Imóvel Urbano | G38: Residencial | H38: 1º CRI | I38: Ribeirão Preto/SP | J38: 45117.688 | K38: Nível 2 | L38: n/a | M38: 109000 | N38: 1 | O38: =N38*M38 -> 109000 | R38: 59251 | S38: 137000 | V38: Total Imóveis COZAC | W38: =W34+W31 -> 41 | X38: =X34+X31 -> 17871567 | Y38: =X38/$X$38 -> 1
A39: Registrado | B39: Posterior | C39: 96154 | D39: 1 | E39: =IFERROR(VLOOKUP(C39,$U$22:$U$27,1,0),"-") -> - | F39: Imóvel Urbano | G39: Residencial | H39: 1º CRI | I39: Ribeirão Preto/SP | J39: 45117.691 | K39: Nível 2 | L39: n/a | M39: 109000 | N39: 1 | O39: =N39*M39 -> 109000 | R39: 102753 | S39: 136000 | U39: PROCURADORIA
A40: Registrado | B40: Posterior | C40: 96155 | D40: 1 | E40: =IFERROR(VLOOKUP(C40,$U$22:$U$27,1,0),"-") -> - | F40: Imóvel Urbano | G40: Residencial | H40: 1º CRI | I40: Ribeirão Preto/SP | J40: 45117.692 | K40: Nível 2 | L40: n/a | M40: 109000 | N40: 1 | O40: =N40*M40 -> 109000 | R40: 102754 | S40: 136000 | U40: 5104
A41: Registrado | B41: Posterior | C41: 96157 | D41: 1 | E41: =IFERROR(VLOOKUP(C41,$U$22:$U$27,1,0),"-") -> - | F41: Imóvel Urbano | G41: Residencial | H41: 1º CRI | I41: Ribeirão Preto/SP | J41: 45117.713 | K41: Nível 2 | L41: n/a | M41: 62000 | N41: 1 | O41: =N41*M41 -> 62000 | R41: 96153 | S41: 109000 | U41: 5103
A42: Registrado | B42: Posterior | C42: 96156 | D42: 1 | E42: =IFERROR(VLOOKUP(C42,$U$22:$U$27,1,0),"-") -> - | F42: Imóvel Urbano | G42: Residencial | H42: 1º CRI | I42: Ribeirão Preto/SP | J42: 45117.711 | K42: Nível 2 | L42: n/a | M42: 62000 | N42: 1 | O42: =N42*M42 -> 62000 | R42: 96154 | S42: 109000 | U42: 52218
A43: Registrado | B43: Posterior | C43: 96158 | D43: 1 | E43: =IFERROR(VLOOKUP(C43,$U$22:$U$27,1,0),"-") -> - | F43: Imóvel Urbano | G43: Comercial | H43: 1º CRI | I43: Ribeirão Preto/SP | J43: 45110.619 | K43: Nível 2 | L43: n/a | M43: 127800 | N43: 1 | O43: =N43*M43 -> 127800 | R43: 96155 | S43: 109000 | U43: 72157
A44: Registrado | B44: Outros | C44: 116945 | D44: 1 | E44: =IFERROR(VLOOKUP(C44,$U$22:$U$27,1,0),"-") -> - | F44: Imóvel Urbano | G44: Residencial | H44: 2º CRI | I44: Ilha Comprida/SP | J44: 45121.464 | K44: Nível 2 | L44: n/a | M44: 0 | N44: 1 | O44: =N44*M44 -> 0 | R44: 96157 | S44: 62000 | U44: 62872
A45: Registrado | B45: Outros | C45: 116946 | D45: 1 | E45: =IFERROR(VLOOKUP(C45,$U$22:$U$27,1,0),"-") -> - | F45: Imóvel Urbano | G45: Residencial | H45: 2º CRI | I45: Ilha Comprida/SP | J45: 45121.465 | K45: Nível 2 | L45: n/a | M45: 0 | N45: 1 | O45: =N45*M45 -> 0 | R45: 96156 | S45: 62000 | U45: 32744
L46: =SUM(L5:L45) -> 23939000 | M46: =SUM(M5:M45) -> 21429554 | O46: =SUM(O5:O45) -> 17871567 | R46: 116945 | S46: 0
A47: {=_xlfn.UNIQUE(A5:A45)} -> Previsão 08/10 | R47: 116946 | S47: 0 | U47: CONDOMÍNIO
A48: Registrado | R48: 26 | S48: 6512666.7 | U48: 36052
A49: Previsão 05/09 | U49: 36053
A50: Sem Carta
A51: Previsão 03/10 | R51: COZAC: Registros
A52: Previsão 29/09 | C52: Matrícula | F52: Obs | R52: # | S52: VF | T52: Status
A53: Previsão 26/09 | C53: 96159 | F53: Arrematado por terceiros | R53: =COUNTIF($A$5:$A$45,T53) -> 19 | S53: =SUMIF($A$5:$A$45,T53,$O$5:$O$45) -> 4490800 | T53: Registrado
A54: Sem Previsão | R54: =COUNTIF($A$5:$A$45,T54) -> 4 | S54: =SUMIF($A$5:$A$45,T54,$O$5:$O$45) -> 1853051.7 | T54: Previsão 05/09
R55: =COUNTIF($A$5:$A$45,T55) -> 6 | S55: =SUMIF($A$5:$A$45,T55,$O$5:$O$45) -> 1578666.7 | T55: Previsão 26/09
J56: Opc. 1 | O56: Opc. 3 | R56: =COUNTIF($A$5:$A$45,T56) -> 1 | S56: =SUMIF($A$5:$A$45,T56,$O$5:$O$45) -> 462000 | T56: Previsão 29/09
C57: Matrícula | D57: Área Terreno | E57: Área Const. | F57: VM | G57: VF | J57: Vl. Laudo | L57: Matrícula | M57: Vl. Individualizado | O57: Vl. Laudo | R57: =COUNTIF($A$5:$A$45,T57) -> 1 | S57: =SUMIF($A$5:$A$45,T57,$O$5:$O$45) -> 3833000 | T57: Previsão 08/10
C58: 32744 | D58: 714.6 | E58: 600 | F58: 1381000 | G58: 980000 | I58: =J58/$J$60 -> 0.54384018 | J58: =G58/$G$60*J60 -> 1407458.4 | L58: 32744 | M58: =D63*K63+E63*K64 -> 1557113.2 | O58: =P58*$M$60 -> 1552800 | P58: 0.6 | R58: =COUNTIF($A$5:$A$45,T58) -> 1 | S58: =SUMIF($A$5:$A$45,T58,$O$5:$O$45) -> 590500 | T58: Previsão 03/10
C59: 6549 | D59: 757 | E59: 185 | F59: 1158000 | G59: 822000 | I59: =J59/$J$60 -> 0.45615982 | J59: =G59/$G$60*J60 -> 1180541.6 | L59: 6549 | M59: =D64*K63+E64*K64 -> 1030886.8 | O59: =P59*$M$60 -> 1035200 | P59: 0.4 | R59: =COUNTIF($A$5:$A$45,T59) -> 1 | S59: =SUMIF($A$5:$A$45,T59,$O$5:$O$45) -> 109000 | T59: Sem Previsão
C60: Total | D60: =SUM(D58:D59) -> 1471.6 | E60: =SUM(E58:E59) -> 785 | F60: =SUM(F58:F59) -> 2539000 | G60: =SUM(G58:G59) -> 1802000 | J60: 2588000 | L60: Vl. Laudo | M60: =SUM(M58:M59) -> 2588000 | O60: =SUM(O58:O59) -> 2588000 | R60: =COUNTIF($A$5:$A$45,T60) -> 8 | S60: =SUMIF($A$5:$A$45,T60,$O$5:$O$45) -> 4954549 | T60: Sem Carta
R61: =SUM(R53:R60) -> 41 | S61: =SUM(S53:S60) -> 17871567 | T61: Total
D62: Área Terreno | E62: Área Const. | I62: Vl. Laudo
D63: =D58/$D$60 -> 0.48559391 | E63: =E58/$E$60 -> 0.76433121 | H63: Vl. Terreno | I63: 1510038.8 | J63: =I63/I65 -> 0.58357665 | K63: =J63*$J$60 -> 1510296.4
D64: =D59/$D$60 -> 0.51440609 | E64: =E59/$E$60 -> 0.23566879 | H64: Vl. Construção | I64: 1077519.8 | J64: =I64/I65 -> 0.41642335 | K64: =J64*$J$60 -> 1077703.6
D65: =SUM(D63:D64) -> 1 | E65: =SUM(E63:E64) -> 1 | I65: =SUM(I63:I64) -> 2587558.6 | K65: =SUM(K63:K64) -> 2588000

Sheet Listagem Imobiliária-23-01-26
A1: Mensagens | B1: ID Caso | C1: Nome do Caso | D1: Matrícula(s) | E1: Valor Avaliação | F1: Valor Venda Forçada | G1: Valor Venda Forçada VP | H1: Classe Imóvel | I1: Tipo do Imóvel | J1: Cidade | K1: UF | L1: Resultado de localização | M1: Nível | N1: Tarefa Atual | O1: Solicitante | P1: Área Demandante | Q1: Responsável (Tarefa Atual) | R1: Status (Tarefa Atual) | S1: Prazo - Tarefa atual | T1: Data/Hora de Criação (Solicitação) | U1: Data/Hora de Criação (Tarefa atual) | V1: Data/Hora de Atribuição (Tarefa atual) | W1: Data/Hora de Conclusão (Tarefa atual) | X1: Data/Hora de Conclusão (Tarefa atual) | Y1: Tags | Z1: Finalidade da tarefa | AA1: Nome da Carteira | AB1: Logradouro | AC1: Bairro | AD1: Área Construída (m²) | AE1: Área Privativa (m²) | AF1: Área Terreno | AG1: Unid. Área Terreno | AH1: Tentativa de localização | AI1: Tipo de localização | AJ1: Resultado da Tarefa de localização | AK1: Complexidade da localização | AL1: Prazo entrega - Localização | AM1: Data/Hora de Criação de localização | AN1: Data/Hora de atribuição - Localização | AO1: Data/Hora de conclusão - Localização | AP1: Responsável localização | AQ1: Resultado da avaliação | AR1: Resultado da Tarefa de avaliação | AS1: Complexidade da avaliação | AT1: Prazo entrega - Avaliação | AU1: Data/Hora de Criação de avaliação | AV1: Data/Hora de atribuição - Avaliação | AW1: Data/Hora de conclusão - Avaliação | AX1: Responsável avaliação | AY1: Resultado da validação | AZ1: Resultado da Tarefa de validação | BA1: Complexidade da validação | BB1: Prazo entrega - Validação | BC1: Data/Hora de Criação de validação | BD1: Data/Hora de atribuição - Validação | BE1: Data/Hora de conclusão - Validação | BF1: Responsável validação | BG1: Correção diligente? | BH1: Revalidação? | BI1: Cancelado por: | BJ1: Justificativa do cancelamento: | BK1: Somente localização? | BL1: Comentário:
B2: 15292 | C2: COZAC | D2: 149 | E2: 297000 | F2: 228000 | H2: Imóvel Urbano | I2: Loja de rua | J2: Ribeirão Preto | K2: SP | L2: Localizado | M2: Nível 2 | N2: Validação Avaliação Urbano | O2: ANA CLARA | P2: Gestão BNDU | Q2: ANDERSON SCARPINO | R2: Concluída | S2: 18/07/2025 | T2: 05/06/2025 17:20 | U2: 18/07/2025 09:16 | V2: 18/07/2025 09:25 | W2: 18/07/2025 09:51 | X2: =W2*1 -> 45856.41 | Z2: Pesquisa de Bens | AA2: BANCO DO BRASIL (SGL_NAME) | AB2: Rua Comandante Marcondes Salgado | AC2: Centro | AD2: 99.27 | AF2: 130 | AG2: m2 | AH2: T1 | AI2: Remota | AJ2: Concluido | AK2: Normal | AL2: 04/04/2025 | AM2: 02/04/2025 16:10 | AN2: 02/04/2025 16:11 | AO2: 02/04/2025 19:11 | AP2: RAMON GOMES | AT2: 31/07/2025 | AU2: 18/07/2025 09:16 | AV2: 01/07/2025 11:55 | AW2: 18/07/2025 09:16 | AX2: Victor Libarino | BB2: 18/07/2025 | BC2: 18/07/2025 09:16 | BD2: 18/07/2025 09:25 | BE2: 18/07/2025 09:51 | BF2: ANDERSON SCARPINO | BH2: FALSE | BK2: FALSE
B3: 15292 | C3: COZAC | D3: 149 | E3: 405000 | F3: 311000 | H3: Imóvel Urbano | I3: Casa Residencial | J3: Ribeirão Preto | K3: SP | L3: Localizado | M3: Nível 2 | N3: Validação Avaliação Urbano | O3: LUCAS ORTEGA | Q3: ANDERSON SCARPINO | R3: Concluída | S3: 20/10/2023 | T3: 13/06/2023 15:01 | U3: 20/10/2023 16:12 | V3: 20/10/2023 16:12 | W3: 20/10/2023 16:39 | X3: =W3*1 -> 45219.694 | Z3: Acordo | AA3: BANCO DO BRASIL (SGL_NAME) | AB3: Rua Acre | AC3: Ipiranga | AD3: 200 | AF3: 480 | AG3: m2 | AH3: T1 | AI3: Remota | AJ3: Concluido | AL3: 05/04/2023 | AM3: 29/03/2023 17:40 | AN3: 29/03/2023 17:42 | AO3: 31/03/2023 09:55 | AP3: AGROFFICIO ATENDIMENTO | AT3: 10/07/2023 | AU3: 20/10/2023 16:12 | AV3: 10/07/2023 11:50 | AW3: 10/07/2023 12:16 | AX3: RAPHAEL PARENTE | BB3: 20/10/2023 | BC3: 20/10/2023 16:12 | BD3: 20/10/2023 16:12 | BE3: 20/10/2023 16:39 | BF3: ANDERSON SCARPINO | BG3: TRUE | BH3: TRUE | BK3: FALSE
B4: 15292 | C4: COZAC | D4: 149 | E4: 307028.72 | F4: 221060.68 | H4: Imóvel Urbano | I4: Casa Residencial | J4: Ribeirão Preto | K4: SP | L4: Localizado | M4: Nível 1 | N4: Validação Avaliação Urbano | O4: LUCAS ORTEGA | Q4: MATHEUS NAVARRO | R4: Concluída | S4: 20/04/2023 | T4: 29/03/2023 17:40 | U4: 10/04/2023 12:01 | V4: 14/04/2023 10:35 | W4: 19/04/2023 18:28 | X4: =W4*1 -> 45035.769 | Z4: Pesquisa de Bens | AA4: BANCO DO BRASIL (SGL_NAME) | AB4: Rua Acre | AC4: Ipiranga | AD4: 196.13 | AF4: 480 | AG4: m2 | AH4: T1 | AI4: Remota | AJ4: Concluido | AL4: 05/04/2023 | AM4: 29/03/2023 17:40 | AN4: 29/03/2023 17:42 | AO4: 31/03/2023 09:55 | AP4: AGROFFICIO ATENDIMENTO | AQ4: Avaliado | AR4: Concluido | AS4: Normal | AT4: 10/04/2023 | AU4: 10/04/2023 12:01 | AV4: 03/04/2023 09:08 | AW4: 10/04/2023 12:01 | AX4: RAIZA GONÇALVES | AY4: Avaliado | AZ4: Concluido | BA4: Normal | BB4: 20/04/2023 | BC4: 10/04/2023 12:01 | BD4: 14/04/2023 10:35 | BE4: 19/04/2023 18:28 | BF4: MATHEUS NAVARRO | BH4: FALSE | BK4: FALSE
B5: 15292 | C5: COZAC | D5: 149 | E5: 238460 | F5: 164537 | H5: Imóvel Urbano | I5: Casa Residencial | J5: Ribeirão Preto | K5: SP | L5: Localizado | M5: Nível 1 | N5: Validação Avaliação Urbano | O5: rd.avaliacao@enforcegroup.com.br | Q5: BRUNO ICARO | R5: Concluída | S5: 27/06/2022 | T5: 27/05/2022 08:40 | U5: 26/05/2022 21:00 | V5: 12/06/2022 21:00 | W5: 14/06/2022 21:00 | X5: =W5*1 -> 44726.875 | Y5: MIGRADO_ZOHO | Z5: Pesquisa de Bens | AA5: BANCO DO BRASIL (SGL_NAME) | AB5: Rua Acre, 1839 | AC5: Ipiranga | AD5: 330 | AE5: 0 | AF5: 480 | AG5: m2 | AH5: T1 | AI5: Remota | AJ5: Concluido | AL5: 02/06/2022 | AM5: 26/05/2022 21:00 | AN5: 26/05/2022 21:00 | AO5: 01/06/2022 21:00 | AP5: HERGOM | AQ5: Avaliado | AS5: Normal | AT5: 27/06/2022 | AU5: 26/05/2022 21:00 | AV5: 12/06/2022 21:00 | AW5: 14/06/2022 21:00 | AX5: BRUNO ICARO | AY5: Avaliado | BB5: 27/06/2022 | BC5: 14/06/2022 21:00 | BD5: 12/06/2022 21:00 | BE5: 29/06/2022 21:00 | BF5: MARINA FAHL | BH5: FALSE | BK5: FALSE
B6: 15292 | C6: COZAC | D6: 3417 | E6: 579000 | F6: 446000 | H6: Imóvel Urbano | I6: Casa Residencial | J6: Ribeirão Preto | K6: SP | L6: Localizado | M6: Nível 2 | N6: Validação Avaliação Urbano | O6: ANA CLARA | P6: Gestão BNDU | Q6: ANDERSON SCARPINO | R6: Concluída | S6: 10/07/2025 | T6: 05/06/2025 17:16 | U6: 10/07/2025 02:21 | V6: 10/07/2025 09:33 | W6: 10/07/2025 11:07 | X6: =W6*1 -> 45848.463 | Z6: Pesquisa de Bens | AA6: BANCO DO BRASIL (SGL_NAME) | AB6: Rua Conde Afonso Celso | AC6: Jardim Sumaré | AD6: 217.23 | AF6: 352 | AG6: m2 | AH6: T1 | AI6: Remota | AJ6: Concluido | AL6: 05/04/2023 | AM6: 28/03/2023 17:58 | AN6: 29/03/2023 09:03 | AO6: 31/03/2023 10:14 | AP6: AGROFFICIO ATENDIMENTO | AT6: 31/07/2025 | AU6: 10/07/2025 02:21 | AV6: 01/07/2025 11:55 | AW6: 10/07/2025 02:21 | AX6: Victor Libarino | BB6: 10/07/2025 | BC6: 10/07/2025 02:21 | BD6: 10/07/2025 09:33 | BE6: 10/07/2025 11:07 | BF6: ANDERSON SCARPINO | BH6: FALSE | BK6: FALSE
B7: 15292 | C7: COZAC | D7: 3417 | E7: 600000 | F7: 462000 | H7: Imóvel Urbano | I7: Casa Residencial | J7: Ribeirão Preto | K7: SP | L7: Localizado | M7: Nível 2 | N7: Validação Avaliação Urbano | O7: LUCAS ORTEGA | Q7: ANDERSON SCARPINO | R7: Concluída | S7: 20/10/2023 | T7: 13/06/2023 15:02 | U7: 20/10/2023 16:20 | V7: 20/10/2023 16:21 | W7: 20/10/2023 16:24 | X7: =W7*1 -> 45219.683 | Z7: Acordo | AA7: BANCO DO BRASIL (SGL_NAME) | AB7: Rua Conde Afonso Celso | AC7: Jardim Sumaré | AD7: 190 | AF7: 352 | AG7: m2 | AH7: T1 | AI7: Remota | AJ7: Concluido | AL7: 05/04/2023 | AM7: 28/03/2023 17:58 | AN7: 29/03/2023 09:03 | AO7: 31/03/2023 10:14 | AP7: AGROFFICIO ATENDIMENTO | AT7: 29/06/2023 | AU7: 20/10/2023 16:20 | AV7: 13/06/2023 15:22 | AW7: 03/07/2023 13:53 | AX7: RAPHAEL PARENTE | BB7: 20/10/2023 | BC7: 20/10/2023 16:20 | BD7: 20/10/2023 16:21 | BE7: 20/10/2023 16:24 | BF7: ANDERSON SCARPINO | BH7: TRUE | BK7: FALSE
B8: 15292 | C8: COZAC | D8: 3417 | E8: 573295.03 | F8: 412772.42 | H8: Imóvel Urbano | I8: Casa Residencial | J8: Ribeirão Preto | K8: SP | L8: Localizado | M8: Nível 1 | N8: Validação Avaliação Urbano | O8: NATHALIA DIAS | P8: Investigação | Q8: MATHEUS NAVARRO | R8: Concluída | S8: 20/04/2023 | T8: 28/03/2023 17:58 | U8: 06/04/2023 09:33 | V8: 14/04/2023 10:35 | W8: 19/04/2023 18:23 | X8: =W8*1 -> 45035.766 | Z8: Pesquisa de Bens | AA8: BANCO DO BRASIL (SGL_NAME) | AB8: Rua Conde Afonso Celso | AC8: Jardim Sumaré | AD8: 160 | AF8: 352 | AG8: m2 | AH8: T1 | AI8: Remota | AJ8: Concluido | AL8: 05/04/2023 | AM8: 28/03/2023 17:58 | AN8: 29/03/2023 09:03 | AO8: 31/03/2023 10:14 | AP8: AGROFFICIO ATENDIMENTO | AQ8: Avaliado | AR8: Concluido | AS8: Normal | AT8: 06/04/2023 | AU8: 06/04/2023 09:33 | AV8: 06/04/2023 09:22 | AW8: 06/04/2023 09:33 | AX8: RAIZA GONÇALVES | AY8: Avaliado | AZ8: Concluido | BA8: Réplica | BB8: 20/04/2023 | BC8: 06/04/2023 09:33 | BD8: 14/04/2023 10:35 | BE8: 19/04/2023 18:23 | BF8: MATHEUS NAVARRO | BG8: TRUE | BH8: FALSE | BK8: FALSE
B9: 15292 | C9: COZAC | D9: 3417 | E9: 850560 | F9: 637920 | H9: Imóvel Urbano | I9: Casa Residencial | J9: Ribeirão Preto | K9: SP | L9: Localizado | M9: Nível 0 | N9: Validação Avaliação Urbano | O9: rd.avaliacao@enforcegroup.com.br | Q9: MATHEUS NAVARRO | R9: Concluída | S9: 28/08/2022 | T9: 28/07/2022 14:45 | U9: 27/07/2022 21:00 | V9: 28/07/2022 21:00 | W9: 28/07/2022 21:00 | X9: =W9*1 -> 44770.875 | Y9: MIGRADO_ZOHO | Z9: Pesquisa de Bens | AA9: BANCO DO BRASIL (SGL_NAME) | AB9: Rua Conde Afonso Celso, 1453 | AC9: Jardim Sumaré | AD9: 350 | AE9: 0 | AF9: 1109 | AG9: m2 | AH9: T1 | AI9: Remota | AJ9: Concluido | AL9: 28/07/2022 | AM9: 27/07/2022 21:00 | AN9: 27/07/2022 21:00 | AO9: 27/07/2022 21:00 | AP9: SIGLOCAL | AQ9: Avaliado | AT9: 28/08/2022 | AU9: 27/07/2022 21:00 | AV9: 28/07/2022 21:00 | AW9: 28/07/2022 21:00 | AX9: MATHEUS NAVARRO | AY9: Avaliado | BB9: 28/08/2022 | BC9: 28/07/2022 21:00 | BD9: 28/07/2022 21:00 | BE9: 28/07/2022 21:00 | BF9: MATHEUS NAVARRO | BH9: FALSE | BK9: FALSE
B10: 15292 | C10: COZAC | D10: 3417 | E10: 528068 | F10: 380209 | H10: Imóvel Urbano | I10: Casa Residencial | J10: Ribeirão Preto | K10: SP | L10: Localizado | M10: Nível 1 | N10: Validação Avaliação Urbano | O10: rd.avaliacao@enforcegroup.com.br | Q10: JULIA JORGE | R10: Concluída | S10: 27/06/2022 | T10: 27/05/2022 08:48 | U10: 26/05/2022 21:00 | V10: 12/06/2022 21:00 | W10: 15/06/2022 21:00 | X10: =W10*1 -> 44727.875 | Y10: MIGRADO_ZOHO | Z10: Pesquisa de Bens | AA10: BANCO DO BRASIL (SGL_NAME) | AB10: Rua Conde Afonso Celso, 1453 | AC10: Jardim Sumaré | AD10: 190 | AE10: 0 | AF10: 352 | AG10: m2 | AH10: T1 | AI10: Remota | AJ10: Concluido | AL10: 02/06/2022 | AM10: 26/05/2022 21:00 | AN10: 26/05/2022 21:00 | AO10: 01/06/2022 21:00 | AP10: HERGOM | AQ10: Avaliado | AS10: Normal | AT10: 27/06/2022 | AU10: 26/05/2022 21:00 | AV10: 12/06/2022 21:00 | AW10: 15/06/2022 21:00 | AX10: JULIA JORGE | AY10: Avaliado | BB10: 27/06/2022 | BC10: 15/06/2022 21:00 | BD10: 12/06/2022 21:00 | BE10: 29/06/2022 21:00 | BF10: MARINA FAHL | BH10: FALSE | BK10: FALSE
B11: 15292 | C11: COZAC | D11: 5103 | E11: 536000 | F11: 391000 | H11: Imóvel Urbano | I11: Casa Residencial | J11: Ribeirão Preto | K11: SP | L11: Localizado | M11: Nível 2 | N11: Validação Avaliação Urbano | O11: FERNANDA GOMES | P11: Gestão BNDU | Q11: ANDERSON SCARPINO | R11: Concluída | S11: 13/01/2026 | T11: 19/12/2025 16:50 | U11: 11/01/2026 15:36 | V11: 13/01/2026 11:03 | W11: 13/01/2026 12:45 | X11: =W11*1 -> 46035.531 | Z11: Pesquisa de Bens | AA11: BANCO DO BRASIL (SGL_NAME) | AB11: Rua João Penteado | AC11: Jardim Sumaré | AD11: 336.6 | AF11: 312.5 | AG11: m2 | AH11: T1 | AI11: Remota | AJ11: Concluido | AL11: 05/04/2023 | AM11: 28/03/2023 17:56 | AN11: 29/03/2023 09:02 | AO11: 31/03/2023 10:48 | AP11: AGROFFICIO ATENDIMENTO | AT11: 16/01/2026 | AU11: 11/01/2026 15:36 | AV11: 19/12/2025 17:33 | AW11: 11/01/2026 15:36 | AX11: Victor Libarino - Financeiro (N2/N3) | BB11: 13/01/2026 | BC11: 11/01/2026 15:36 | BD11: 13/01/2026 11:03 | BE11: 13/01/2026 12:45 | BF11: ANDERSON SCARPINO | BH11: FALSE | BK11: FALSE
B12: 15292 | C12: COZAC | D12: 5103 | E12: 571000 | F12: 439000 | H12: Imóvel Urbano | I12: Casa Comercial | J12: Ribeirão Preto | K12: SP | L12: Localizado | M12: Nível 2 | N12: Validação Avaliação Urbano | O12: LUCAS ORTEGA | Q12: ANDERSON SCARPINO | R12: Concluída | S12: 20/10/2023 | T12: 13/06/2023 15:00 | U12: 20/10/2023 16:29 | V12: 20/10/2023 16:30 | W12: 20/10/2023 16:36 | X12: =W12*1 -> 45219.692 | Z12: Acordo | AA12: BANCO DO BRASIL (SGL_NAME) | AB12: Rua João Penteado | AC12: Jardim Sumaré | AD12: 324.6 | AF12: 312.5 | AG12: m2 | AH12: T1 | AI12: Remota | AJ12: Concluido | AL12: 05/04/2023 | AM12: 28/03/2023 17:56 | AN12: 29/03/2023 09:02 | AO12: 31/03/2023 10:48 | AP12: AGROFFICIO ATENDIMENTO | AT12: 06/07/2023 | AU12: 20/10/2023 16:29 | AV12: 13/06/2023 15:29 | AW12: 03/07/2023 10:48 | AX12: RAPHAEL PARENTE | BB12: 20/10/2023 | BC12: 20/10/2023 16:29 | BD12: 20/10/2023 16:30 | BE12: 20/10/2023 16:36 | BF12: ANDERSON SCARPINO | BH12: TRUE | BK12: FALSE
B13: 15292 | C13: COZAC | D13: 5103 | E13: 701861.9 | F13: 512359.18 | H13: Imóvel Urbano | I13: Casa Residencial | J13: Ribeirão Preto | K13: SP | L13: Localizado | M13: Nível 1 | N13: Validação Avaliação Urbano | O13: NATHALIA DIAS | P13: Investigação | Q13: MATHEUS NAVARRO | R13: Concluída | S13: 20/04/2023 | T13: 28/03/2023 17:56 | U13: 06/04/2023 11:17 | V13: 14/04/2023 10:35 | W13: 19/04/2023 18:13 | X13: =W13*1 -> 45035.759 | Z13: Pesquisa de Bens | AA13: BANCO DO BRASIL (SGL_NAME) | AB13: Rua João Penteado | AC13: Jardim Sumaré | AD13: 324.6 | AF13: 312.5 | AG13: m2 | AH13: T1 | AI13: Remota | AJ13: Concluido | AL13: 05/04/2023 | AM13: 28/03/2023 17:56 | AN13: 29/03/2023 09:02 | AO13: 31/03/2023 10:48 | AP13: AGROFFICIO ATENDIMENTO | AQ13: Avaliado | AR13: Concluido | AS13: Normal | AT13: 10/04/2023 | AU13: 06/04/2023 11:17 | AV13: 03/04/2023 09:08 | AW13: 06/04/2023 11:17 | AX13: RAIZA GONÇALVES | AY13: Avaliado | AZ13: Concluido | BA13: Normal | BB13: 20/04/2023 | BC13: 06/04/2023 11:17 | BD13: 14/04/2023 10:35 | BE13: 19/04/2023 18:13 | BF13: MATHEUS NAVARRO | BH13: FALSE | BK13: FALSE
B14: 15292 | C14: COZAC | D14: 5103 | E14: 524177 | F14: 382650 | H14: Imóvel Urbano | I14: Prédio Comercial | J14: Ribeirão Preto | K14: SP | L14: Localizado | M14: Nível 1 | N14: Validação Avaliação Urbano | O14: rd.avaliacao@enforcegroup.com.br | Q14: BRUNO ICARO | R14: Concluída | S14: 28/08/2022 | T14: 28/07/2022 14:42 | U14: 27/07/2022 21:00 | V14: 28/07/2022 21:00 | W14: 28/07/2022 21:00 | X14: =W14*1 -> 44770.875 | Y14: MIGRADO_ZOHO | Z14: Pesquisa de Bens | AA14: BANCO DO BRASIL (SGL_NAME) | AB14: Rua João Penteado, 90 | AC14: Jardim America | AD14: 250 | AE14: 0 | AF14: 312.5 | AG14: m2 | AH14: T1 | AI14: Remota | AJ14: Concluido | AL14: 28/07/2022 | AM14: 27/07/2022 21:00 | AN14: 27/07/2022 21:00 | AO14: 27/07/2022 21:00 | AP14: SIGLOCAL | AQ14: Avaliado | AS14: Normal | AT14: 28/08/2022 | AU14: 27/07/2022 21:00 | AV14: 28/07/2022 21:00 | AW14: 28/07/2022 21:00 | AX14: BRUNO ICARO | AY14: Avaliado | BB14: 28/08/2022 | BC14: 28/07/2022 21:00 | BD14: 28/07/2022 21:00 | BE14: 28/07/2022 21:00 | BF14: MATHEUS NAVARRO | BH14: FALSE | BK14: FALSE
B15: 15292 | C15: COZAC | D15: 5103 | E15: 596457 | F15: 417520 | H15: Imóvel Urbano | I15: Casa Residencial | J15: Ribeirão Preto | K15: SP | L15: Localizado | M15: Nível 1 | N15: Validação Avaliação Urbano | O15: rd.avaliacao@enforcegroup.com.br | Q15: JULIA JORGE | R15: Concluída | S15: 27/06/2022 | T15: 27/05/2022 08:48 | U15: 26/05/2022 21:00 | V15: 12/06/2022 21:00 | W15: 15/06/2022 21:00 | X15: =W15*1 -> 44727.875 | Y15: MIGRADO_ZOHO | Z15: Pesquisa de Bens | AA15: BANCO DO BRASIL (SGL_NAME) | AB15: Rua João Penteado, 90 | AC15: Jardim Sumaré | AD15: 230 | AE15: 0 | AF15: 312.5 | AG15: m2 | AH15: T1 | AI15: Remota | AJ15: Concluido | AL15: 02/06/2022 | AM15: 26/05/2022 21:00 | AN15: 26/05/2022 21:00 | AO15: 01/06/2022 21:00 | AP15: HERGOM | AQ15: Avaliado | AS15: Normal | AT15: 27/06/2022 | AU15: 26/05/2022 21:00 | AV15: 12/06/2022 21:00 | AW15: 15/06/2022 21:00 | AX15: JULIA JORGE | AY15: Avaliado | BB15: 27/06/2022 | BC15: 15/06/2022 21:00 | BD15: 12/06/2022 21:00 | BE15: 29/06/2022 21:00 | BF15: MARINA FAHL | BH15: FALSE | BK15: FALSE
B16: 15292 | C16: COZAC | D16: 5104 | E16: 1003000 | F16: 732000 | H16: Imóvel Urbano | I16: Prédio residencial | J16: Ribeirão Preto | K16: SP | L16: Localizado | M16: Nível 2 | N16: Validação Avaliação Urbano | O16: MATHEUS TORRES | P16: Gestão BNDU | Q16: ANDERSON SCARPINO | R16: Concluída | S16: 19/12/2025 | T16: 25/11/2025 16:09 | U16: 15/12/2025 11:07 | V16: 19/12/2025 08:49 | W16: 19/12/2025 09:30 | X16: =W16*1 -> 46010.396 | Z16: Pesquisa de Bens | AA16: BANCO DO BRASIL (SGL_NAME) | AB16: Avenida Santa Luzia | AC16: Jardim Sumaré | AD16: 669.16 | AF16: 433.01 | AG16: m2 | AH16: T1 | AI16: Remota | AJ16: Concluido | AL16: 05/04/2023 | AM16: 29/03/2023 17:31 | AN16: 29/03/2023 17:36 | AO16: 05/04/2023 15:17 | AP16: AGROFFICIO ATENDIMENTO | AT16: 22/12/2025 | AU16: 15/12/2025 11:07 | AV16: 01/12/2025 14:30 | AW16: 15/12/2025 11:07 | AX16: Victor Libarino (N2/N3) | BB16: 19/12/2025 | BC16: 15/12/2025 11:07 | BD16: 19/12/2025 08:49 | BE16: 19/12/2025 09:30 | BF16: ANDERSON SCARPINO | BH16: FALSE | BK16: FALSE
B17: 15292 | C17: COZAC | D17: 5104 | E17: 1024000 | F17: 727000 | H17: Imóvel Urbano | I17: Casa Comercial | J17: Ribeirão Preto | K17: SP | L17: Localizado | M17: Nível 2 | N17: Validação Avaliação Urbano | O17: LUCAS ORTEGA | Q17: ANDERSON SCARPINO | R17: Concluída | S17: 10/07/2023 | T17: 13/06/2023 15:02 | U17: 10/07/2023 14:57 | V17: 10/07/2023 15:05 | W17: 10/07/2023 15:05 | X17: =W17*1 -> 45117.628 | Z17: Prospecção | AA17: BANCO DO BRASIL (SGL_NAME) | AB17: Avenida Santa Luzia | AC17: Jardim Sumaré | AD17: 669.16 | AF17: 433.01 | AG17: m2 | AH17: T1 | AI17: Remota | AJ17: Concluido | AL17: 05/04/2023 | AM17: 29/03/2023 17:31 | AN17: 29/03/2023 17:36 | AO17: 05/04/2023 15:17 | AP17: AGROFFICIO ATENDIMENTO | AT17: 10/07/2023 | AU17: 10/07/2023 14:57 | AV17: 10/07/2023 14:33 | AW17: 10/07/2023 14:57 | AX17: RAPHAEL PARENTE | BB17: 10/07/2023 | BC17: 10/07/2023 14:57 | BD17: 10/07/2023 15:05 | BE17: 10/07/2023 15:05 | BF17: ANDERSON SCARPINO | BG17: TRUE | BH17: FALSE | BK17: FALSE
B18: 15292 | C18: COZAC | D18: 5104 | E18: 1322517.2 | F18: 965437.56 | H18: Imóvel Urbano | I18: Casa Residencial | J18: Ribeirão Preto | K18: SP | L18: Localizado | M18: Nível 1 | N18: Validação Avaliação Urbano | O18: NATHALIA DIAS | P18: Investigação | Q18: MATHEUS NAVARRO | R18: Concluída | S18: 20/04/2023 | T18: 29/03/2023 17:31 | U18: 18/04/2023 12:41 | V18: 18/04/2023 16:38 | W18: 19/04/2023 18:16 | X18: =W18*1 -> 45035.761 | Z18: Pesquisa de Bens | AA18: BANCO DO BRASIL (SGL_NAME) | AB18: Avenida Santa Luzia | AC18: Jardim Sumaré | AD18: 669.16 | AF18: 433.01 | AG18: m2 | AH18: T1 | AI18: Remota | AJ18: Concluido | AL18: 05/04/2023 | AM18: 29/03/2023 17:31 | AN18: 29/03/2023 17:36 | AO18: 05/04/2023 15:17 | AP18: AGROFFICIO ATENDIMENTO | AQ18: Avaliado | AR18: Concluido | AS18: Normal | AT18: 18/04/2023 | AU18: 18/04/2023 12:41 | AV18: 06/04/2023 08:21 | AW18: 18/04/2023 12:41 | AX18: RAIZA GONÇALVES | AY18: Avaliado | AZ18: Concluido | BA18: Réplica | BB18: 20/04/2023 | BC18: 18/04/2023 12:41 | BD18: 18/04/2023 16:38 | BE18: 19/04/2023 18:16 | BF18: MATHEUS NAVARRO | BH18: FALSE | BK18: FALSE
B19: 15292 | C19: COZAC | D19: 5104 | E19: 892466 | F19: 687199 | H19: Imóvel Urbano | I19: Prédio Comercial | J19: Ribeirão Preto | K19: SP | L19: Localizado | M19: Nível 1 | N19: Validação Avaliação Urbano | O19: rd.avaliacao@enforcegroup.com.br | Q19: BRUNO ICARO | R19: Concluída | S19: 28/08/2022 | T19: 28/07/2022 14:41 | U19: 27/07/2022 21:00 | V19: 28/07/2022 21:00 | W19: 28/07/2022 21:00 | X19: =W19*1 -> 44770.875 | Y19: MIGRADO_ZOHO | Z19: Pesquisa de Bens | AA19: BANCO DO BRASIL (SGL_NAME) | AB19: Avenida Santa Luzia, 111 | AC19: Jardim Sumare | AD19: 350 | AE19: 0 | AF19: 430 | AG19: m2 | AH19: T1 | AI19: Remota | AJ19: Concluido | AL19: 28/07/2022 | AM19: 27/07/2022 21:00 | AN19: 27/07/2022 21:00 | AO19: 27/07/2022 21:00 | AP19: SIGLOCAL | AQ19: Avaliado | AS19: Normal | AT19: 28/08/2022 | AU19: 27/07/2022 21:00 | AV19: 28/07/2022 21:00 | AW19: 28/07/2022 21:00 | AX19: BRUNO ICARO | AY19: Avaliado | BB19: 28/08/2022 | BC19: 28/07/2022 21:00 | BD19: 28/07/2022 21:00 | BE19: 28/07/2022 21:00 | BF19: MATHEUS NAVARRO | BH19: FALSE | BK19: FALSE
B20: 15292 | C20: COZAC | D20: 5104 | E20: 987573 | F20: 760431 | H20: Imóvel Urbano | I20: Prédio Comercial | J20: Ribeirão Preto | K20: SP | L20: Localizado | M20: Nível 1 | N20: Validação Avaliação Urbano | O20: rd.avaliacao@enforcegroup.com.br | Q20: BRUNO ICARO | R20: Concluída | S20: 27/06/2022 | T20: 27/05/2022 08:44 | U20: 26/05/2022 21:00 | V20: 12/06/2022 21:00 | W20: 14/06/2022 21:00 | X20: =W20*1 -> 44726.875 | Y20: MIGRADO_ZOHO | Z20: Pesquisa de Bens | AA20: BANCO DO BRASIL (SGL_NAME) | AB20: Avenida Santa Luzia, 111 | AC20: Jardim Sumaré | AD20: 699.16 | AE20: 0 | AF20: 433.01 | AG20: m2 | AH20: T1 | AI20: Remota | AJ20: Concluido | AL20: 02/06/2022 | AM20: 26/05/2022 21:00 | AN20: 26/05/2022 21:00 | AO20: 01/06/2022 21:00 | AP20: HERGOM | AQ20: Avaliado | AS20: Normal | AT20: 27/06/2022 | AU20: 26/05/2022 21:00 | AV20: 12/06/2022 21:00 | AW20: 14/06/2022 21:00 | AX20: BRUNO ICARO | AY20: Avaliado | BB20: 27/06/2022 | BC20: 14/06/2022 21:00 | BD20: 12/06/2022 21:00 | BE20: 29/06/2022 21:00 | BF20: MARINA FAHL | BH20: FALSE | BK20: FALSE
B21: 15292 | C21: COZAC | D21: 6529 | E21: 418000 | F21: 293000 | H21: Imóvel Urbano | I21: Terreno urbano | J21: Ribeirão Preto | K21: SP | L21: Localizado | M21: Nível 2 | N21: Validação Avaliação Urbano | O21: FERNANDA GOMES | P21: Gestão BNDU | Q21: ANDERSON SCARPINO | R21: Concluída | S21: 07/10/2025 | T21: 19/09/2025 10:11 | U21: 06/10/2025 17:49 | V21: 07/10/2025 09:12 | W21: 07/10/2025 10:19 | X21: =W21*1 -> 45937.43 | Z21: Pesquisa de Bens | AA21: BANCO DO BRASIL (SGL_NAME) | AB21: Rua Marino Paterlini | AC21: Presidente Médici | AF21: 395 | AG21: m2 | AH21: T1 | AI21: Remota | AJ21: Concluido | AL21: 04/04/2023 | AM21: 28/03/2023 17:10 | AN21: 29/03/2023 09:08 | AO21: 04/04/2023 11:27 | AP21: SIGLOCAL ACESSO | AT21: 08/10/2025 | AU21: 06/10/2025 17:49 | AV21: 24/09/2025 11:30 | AW21: 06/10/2025 17:49 | AX21: Victor Libarino | BB21: 07/10/2025 | BC21: 06/10/2025 17:49 | BD21: 07/10/2025 09:12 | BE21: 07/10/2025 10:19 | BF21: ANDERSON SCARPINO | BH21: FALSE | BK21: FALSE
B22: 15292 | C22: COZAC | D22: 6529 | E22: 284000 | F22: 230000 | H22: Imóvel Urbano | I22: Terreno urbano | J22: Ribeirão Preto | K22: SP | L22: Localizado | M22: Nível 2 | N22: Validação Avaliação Urbano | O22: THIAGO MACHADO | P22: GESTÃO PORTFÓLIO | Q22: ANDERSON SCARPINO | R22: Concluída | S22: 20/10/2023 | T22: 06/06/2023 16:39 | U22: 20/10/2023 16:40 | V22: 20/10/2023 16:40 | W22: 20/10/2023 16:43 | X22: =W22*1 -> 45219.697 | Z22: Acordo | AA22: BANCO DO BRASIL (SGL_NAME) | AB22: Rua Marino Paterlini | AC22: Presidente Médici | AF22: 395 | AG22: m2 | AH22: T1 | AI22: Remota | AJ22: Concluido | AL22: 04/04/2023 | AM22: 28/03/2023 17:10 | AN22: 29/03/2023 09:08 | AO22: 04/04/2023 11:27 | AP22: SIGLOCAL ACESSO | AT22: 10/07/2023 | AU22: 20/10/2023 16:40 | AV22: 10/07/2023 15:25 | AW22: 10/07/2023 15:32 | AX22: RAPHAEL PARENTE | BB22: 20/10/2023 | BC22: 20/10/2023 16:40 | BD22: 20/10/2023 16:40 | BE22: 20/10/2023 16:43 | BF22: ANDERSON SCARPINO | BG22: TRUE | BH22: TRUE | BK22: FALSE
B23: 15292 | C23: COZAC | D23: 6529 | E23: 219785.99 | F23: 178026.65 | H23: Imóvel Urbano | I23: Terreno urbano | J23: Ribeirão Preto | K23: SP | L23: Localizado | M23: Nível 1 | N23: Validação Avaliação Urbano | O23: NATHALIA DIAS | P23: Investigação | Q23: MATHEUS NAVARRO | R23: Concluída | S23: 20/04/2023 | T23: 28/03/2023 17:10 | U23: 17/04/2023 14:54 | V23: 17/04/2023 16:04 | W23: 20/04/2023 11:24 | X23: =W23*1 -> 45036.475 | Z23: Pesquisa de Bens | AA23: BANCO DO BRASIL (SGL_NAME) | AB23: Rua Marino Paterlini | AC23: Presidente Médici | AF23: 395 | AG23: m2 | AH23: T1 | AI23: Remota | AJ23: Concluido | AL23: 04/04/2023 | AM23: 28/03/2023 17:10 | AN23: 29/03/2023 09:08 | AO23: 04/04/2023 11:27 | AP23: SIGLOCAL ACESSO | AQ23: Avaliado | AR23: Concluido | AS23: Réplica | AT23: 18/04/2023 | AU23: 17/04/2023 14:54 | AV23: 06/04/2023 08:20 | AW23: 17/04/2023 14:54 | AX23: RAIZA GONÇALVES | AY23: Avaliado | AZ23: Concluido | BA23: Réplica | BB23: 20/04/2023 | BC23: 17/04/2023 14:54 | BD23: 17/04/2023 16:04 | BE23: 20/04/2023 11:24 | BF23: MATHEUS NAVARRO | BH23: FALSE | BK23: FALSE
B24: 15292 | C24: COZAC | D24: 6529 | E24: 222768 | F24: 178214 | H24: Imóvel Urbano | I24: Terreno urbano | J24: Ribeirão Preto | K24: SP | L24: Localizado | M24: Nível 0 | N24: Validação Avaliação Urbano | O24: rd.avaliacao@enforcegroup.com.br | Q24: ANDRE MAGIORE | R24: Concluída | S24: 28/08/2022 | T24: 28/07/2022 14:29 | U24: 27/07/2022 21:00 | V24: 31/07/2022 21:00 | W24: 31/07/2022 21:00 | X24: =W24*1 -> 44773.875 | Y24: MIGRADO_ZOHO | Z24: Pesquisa de Bens | AA24: BANCO DO BRASIL (SGL_NAME) | AB24: Rua Marino Paterlini | AC24: Presidente Medici | AD24: 0 | AE24: 0 | AF24: 395 | AG24: m2 | AH24: T1 | AI24: Remota | AJ24: Concluido | AL24: 28/07/2022 | AM24: 27/07/2022 21:00 | AN24: 27/07/2022 21:00 | AO24: 27/07/2022 21:00 | AP24: SIGLOCAL | AQ24: Avaliado | AS24: Normal | AT24: 28/08/2022 | AU24: 27/07/2022 21:00 | AV24: 31/07/2022 21:00 | AW24: 31/07/2022 21:00 | AX24: ANDRE MAGIORE | AY24: Avaliado | BB24: 28/08/2022 | BC24: 31/07/2022 21:00 | BD24: 31/07/2022 21:00 | BE24: 31/07/2022 21:00 | BF24: ANDERSON SCARPINO | BH24: FALSE | BK24: FALSE
B25: 15292 | C25: COZAC | D25: 6549 | E25: 0 | F25: 0 | H25: Imóvel Urbano | I25: Casa Residencial | J25: Ribeirão Preto | K25: SP | L25: Localizado | M25: Nível 2 | N25: Validação Avaliação Urbano | O25: ANA CLARA | P25: Gestão BNDU | Q25: ANDERSON SCARPINO | R25: Concluída | S25: 17/07/2025 | T25: 05/06/2025 17:12 | U25: 17/07/2025 16:34 | V25: 17/07/2025 17:04 | W25: 17/07/2025 17:13 | X25: =W25*1 -> 45855.717 | Z25: Pesquisa de Bens | AA25: BANCO DO BRASIL (SGL_NAME) | AB25: Rua Olavo Bilac | AC25: Jardim Sumare | AD25: 192.54 | AF25: 757 | AG25: m2 | AH25: T1 | AI25: Remota | AJ25: Concluido | AL25: 04/04/2023 | AM25: 28/03/2023 17:53 | AN25: 29/03/2023 09:04 | AO25: 04/04/2023 11:32 | AP25: SIGLOCAL ACESSO | AT25: 18/07/2025 | AU25: 17/07/2025 16:34 | AV25: 17/07/2025 14:35 | AW25: 17/07/2025 16:34 | AX25: Victor Libarino | BB25: 17/07/2025 | BC25: 17/07/2025 16:34 | BD25: 17/07/2025 17:04 | BE25: 17/07/2025 17:13 | BF25: ANDERSON SCARPINO | BG25: TRUE | BH25: FALSE | BK25: FALSE
B26: 15292 | C26: COZAC | D26: 6549 | E26: 1158000 | F26: 822000 | H26: Imóvel Urbano | I26: Casa Residencial | J26: Ribeirão Preto | K26: SP | L26: Localizado | M26: Nível 2 | N26: Validação Avaliação Urbano | O26: THIAGO MACHADO | P26: GESTÃO PORTFÓLIO | Q26: ANDERSON SCARPINO | R26: Concluída | S26: 10/07/2023 | T26: 06/06/2023 16:39 | U26: 10/07/2023 17:25 | V26: 10/07/2023 17:27 | W26: 10/07/2023 17:28 | X26: =W26*1 -> 45117.728 | Z26: Acordo | AA26: BANCO DO BRASIL (SGL_NAME) | AB26: Rua Olavo Bilac | AC26: Jardim Sumare | AD26: 185 | AF26: 757 | AG26: m2 | AH26: T1 | AI26: Remota | AJ26: Concluido | AL26: 04/04/2023 | AM26: 28/03/2023 17:53 | AN26: 29/03/2023 09:04 | AO26: 04/04/2023 11:32 | AP26: SIGLOCAL ACESSO | AT26: 10/07/2023 | AU26: 10/07/2023 17:25 | AV26: 10/07/2023 17:10 | AW26: 10/07/2023 17:25 | AX26: RAPHAEL PARENTE | BB26: 10/07/2023 | BC26: 10/07/2023 17:25 | BD26: 10/07/2023 17:27 | BE26: 10/07/2023 17:28 | BF26: ANDERSON SCARPINO | BG26: TRUE | BH26: FALSE | BK26: FALSE
B27: 15292 | C27: COZAC | D27: 6549 | E27: 1233597.7 | F27: 900526.33 | H27: Imóvel Urbano | I27: Casa Residencial | J27: Ribeirão Preto | K27: SP | L27: Localizado | M27: Nível 1 | N27: Validação Avaliação Urbano | O27: NATHALIA DIAS | P27: Investigação | Q27: MATHEUS NAVARRO | R27: Concluída | S27: 20/04/2023 | T27: 28/03/2023 17:53 | U27: 07/04/2023 18:00 | V27: 14/04/2023 10:36 | W27: 19/04/2023 18:27 | X27: =W27*1 -> 45035.769 | Z27: Pesquisa de Bens | AA27: BANCO DO BRASIL (SGL_NAME) | AB27: Rua Olavo Bilac | AC27: Jardim Sumare | AD27: 170 | AF27: 757 | AG27: m2 | AH27: T1 | AI27: Remota | AJ27: Concluido | AL27: 04/04/2023 | AM27: 28/03/2023 17:53 | AN27: 29/03/2023 09:04 | AO27: 04/04/2023 11:32 | AP27: SIGLOCAL ACESSO | AQ27: Avaliado | AR27: Concluido | AS27: Normal | AT27: 13/04/2023 | AU27: 07/04/2023 18:00 | AV27: 06/04/2023 08:20 | AW27: 07/04/2023 18:00 | AX27: RAIZA GONÇALVES | AY27: Avaliado | AZ27: Concluido | BA27: Normal | BB27: 20/04/2023 | BC27: 07/04/2023 18:00 | BD27: 14/04/2023 10:36 | BE27: 19/04/2023 18:27 | BF27: MATHEUS NAVARRO | BH27: FALSE | BK27: FALSE
B28: 15292 | C28: COZAC | D28: 6549 | E28: 0 | F28: 0 | H28: Imóvel Urbano | I28: Casa Residencial | J28: Ribeirão Preto | K28: SP | L28: Localizado | M28: Nível 0 | N28: Validação Avaliação Urbano | O28: rd.avaliacao@enforcegroup.com.br | Q28: MATHEUS NAVARRO | R28: Concluída | S28: 28/08/2022 | T28: 28/07/2022 17:26 | U28: 27/07/2022 21:00 | W28: 28/07/2022 21:00 | X28: =W28*1 -> 44770.875 | Y28: MIGRADO_ZOHO | Z28: Pesquisa de Bens | AA28: BANCO DO BRASIL (SGL_NAME) | AB28: Rua Olavo Bilac, 1384 x Rua Conde Afonso Celso | AC28: Jardim Sumaré | AD28: 0 | AE28: 0 | AF28: 0 | AG28: m2 | AH28: T1 | AI28: Remota | AJ28: Concluido | AL28: 28/07/2022 | AM28: 27/07/2022 21:00 | AN28: 27/07/2022 21:00 | AO28: 27/07/2022 21:00 | AP28: SIGLOCAL | AQ28: Impossível Avaliar | AT28: 28/08/2022 | AU28: 27/07/2022 21:00 | AW28: 28/07/2022 21:00 | AX28: MATHEUS NAVARRO | AY28: Impossível Avaliar | BB28: 28/08/2022 | BC28: 28/07/2022 21:00 | BE28: 28/07/2022 21:00 | BF28: MATHEUS NAVARRO | BH28: FALSE | BK28: FALSE
B29: 15292 | C29: COZAC | D29: 6549 | H29: Imóvel Urbano | I29: Casa Residencial | J29: Ribeirão Preto | K29: SP | L29: Localizado | M29: Nível 1 | N29: Validação Avaliação Urbano | O29: rd.avaliacao@enforcegroup.com.br | Q29: BRUNO ICARO | R29: Concluída | S29: 27/06/2022 | T29: 27/05/2022 08:41 | U29: 26/05/2022 21:00 | V29: 12/06/2022 21:00 | W29: 14/06/2022 21:00 | X29: =W29*1 -> 44726.875 | Y29: MIGRADO_ZOHO | Z29: Pesquisa de Bens | AA29: BANCO DO BRASIL (SGL_NAME) | AB29: Rua Olavo Bilac, 1384 x Rua Conde Afonso Celso | AC29: Jardim Sumaré | AD29: 0 | AE29: 0 | AF29: 0 | AG29: m2 | AH29: T1 | AI29: Remota | AJ29: Matrícula relacionada | AL29: 02/06/2022 | AM29: 26/05/2022 21:00 | AN29: 26/05/2022 21:00 | AO29: 01/06/2022 21:00 | AP29: HERGOM | AQ29: Impossível Avaliar | AT29: 27/06/2022 | AU29: 26/05/2022 21:00 | AV29: 12/06/2022 21:00 | AW29: 14/06/2022 21:00 | AX29: BRUNO ICARO | AY29: Impossível Avaliar | BB29: 27/06/2022 | BC29: 14/06/2022 21:00 | BD29: 12/06/2022 21:00 | BE29: 27/07/2022 21:00 | BH29: FALSE | BK29: FALSE
B30: 15292 | C30: COZAC | D30: 6660 | E30: 1923389.1 | F30: 1923389.1 | H30: Imóvel Urbano | I30: Gleba urbana | J30: Ribeirão Preto | K30: SP | L30: Localizado | M30: Nível 3 | N30: Validação Avaliação Urbano | O30: ANDERSON SCARPINO | P30: ENFORCE RJ E FALÊNCIA | Q30: ANDERSON SCARPINO | R30: Concluída | S30: 16/10/2023 | T30: 27/09/2023 07:45 | U30: 12/10/2023 20:49 | V30: 16/10/2023 09:05 | W30: 17/10/2023 12:01 | X30: =W30*1 -> 45216.501 | Z30: Acordo | AA30: BANCO DO BRASIL (SGL_NAME) | AB30: N/A | AC30: Chácara Santa Terezinha | AF30: 31305 | AG30: m2 | AH30: T1 | AI30: Remota | AJ30: Concluido | AK30: Complexa | AL30: 02/08/2023 | AM30: 01/08/2023 12:13 | AN30: 01/08/2023 12:17 | AO30: 01/08/2023 18:29 | AP30: AGROFFICIO ATENDIMENTO | AT30: 10/10/2023 | AU30: 12/10/2023 20:49 | AV30: 28/09/2023 09:39 | AW30: 12/10/2023 20:49 | AX30: AHEAD ARQUITETURA | BB30: 16/10/2023 | BC30: 12/10/2023 20:49 | BD30: 16/10/2023 09:05 | BE30: 17/10/2023 12:01 | BF30: ANDERSON SCARPINO | BH30: FALSE | BK30: FALSE
B31: 15292 | C31: COZAC | D31: 6660 | E31: 4047000 | F31: 4047000 | H31: Imóvel Urbano | I31: Gleba urbana | J31: Ribeirão Preto | K31: SP | L31: Localizado | M31: Nível 1 | N31: Validação Avaliação Urbano | O31: GUILHERME MARQUES | P31: ENFORCE RJ E FALÊNCIA | Q31: CLAUDIO OKADA | R31: Concluída | S31: 22/08/2023 | T31: 01/08/2023 12:13 | U31: 02/08/2023 12:29 | V31: 22/08/2023 16:07 | W31: 23/08/2023 16:54 | X31: =W31*1 -> 45161.704 | Z31: Acordo | AA31: BANCO DO BRASIL (SGL_NAME) | AB31: N/A | AC31: Chácara Santa Terezinha | AF31: 66000 | AG31: m2 | AH31: T1 | AI31: Remota | AJ31: Concluido | AK31: Complexa | AL31: 02/08/2023 | AM31: 01/08/2023 12:13 | AN31: 01/08/2023 12:17 | AO31: 01/08/2023 18:29 | AP31: AGROFFICIO ATENDIMENTO | AQ31: Avaliado | AR31: Concluido | AS31: Complexa | AT31: 02/08/2023 | AU31: 02/08/2023 12:29 | AV31: 02/08/2023 09:44 | AW31: 02/08/2023 12:29 | AX31: Bruno Ícaro | AY31: Avaliado | AZ31: Concluido | BA31: Complexa | BB31: 22/08/2023 | BC31: 02/08/2023 12:29 | BD31: 22/08/2023 16:07 | BE31: 23/08/2023 16:54 | BF31: CLAUDIO OKADA | BH31: FALSE | BK31: FALSE
B32: 15292 | C32: COZAC | D32: 6660 | H32: Imóvel Urbano | I32: Gleba urbana | J32: Ribeirão Preto | K32: SP | L32: Parcialmente Localizado | M32: Nível 0 | N32: Validação Avaliação Urbano | O32: NATHALIA DIAS | P32: Investigação | Q32: MATHEUS NAVARRO | R32: Concluída | S32: 20/04/2023 | T32: 28/03/2023 16:36 | U32: 17/04/2023 18:34 | V32: 20/04/2023 11:37 | W32: 20/04/2023 11:38 | X32: =W32*1 -> 45036.485 | Z32: Pesquisa de Bens | AA32: BANCO DO BRASIL (SGL_NAME) | AB32: Rua Carlos Augusto Brasão | AC32: Chácara Santa Terezinha | AF32: 31305.93 | AG32: m2 | AH32: T1 | AI32: Remota | AJ32: Concluido | AL32: 04/04/2023 | AM32: 28/03/2023 16:36 | AN32: 29/03/2023 09:08 | AO32: 04/04/2023 22:12 | AP32: SIGLOCAL ACESSO | AQ32: Impossível Avaliar | AR32: Concluido | AS32: Normal | AT32: 18/04/2023 | AU32: 17/04/2023 18:34 | AV32: 06/04/2023 08:20 | AW32: 17/04/2023 18:34 | AX32: RAIZA GONÇALVES | AY32: Impossível Avaliar | AZ32: Concluido | BA32: Normal | BB32: 20/04/2023 | BC32: 17/04/2023 18:34 | BD32: 20/04/2023 11:37 | BE32: 20/04/2023 11:38 | BF32: MATHEUS NAVARRO | BH32: FALSE | BK32: FALSE
B33: 15292 | C33: COZAC | D33: 6660 | E33: 6314775 | F33: 4104603 | H33: Imóvel Urbano | I33: Gleba Urbana | J33: Ribeirão Preto | K33: SP | L33: Parcialmente Localizado | M33: Nível 0 | N33: Validação Avaliação Urbano | O33: rd.avaliacao@enforcegroup.com.br | Q33: ANDRE MAGIORE | R33: Concluída | S33: 28/08/2022 | T33: 28/07/2022 14:21 | U33: 27/07/2022 21:00 | V33: 31/07/2022 21:00 | W33: 31/07/2022 21:00 | X33: =W33*1 -> 44773.875 | Y33: MIGRADO_ZOHO | Z33: Pesquisa de Bens | AA33: BANCO DO BRASIL (SGL_NAME) | AD33: 31300 | AH33: T1 | AI33: Remota | AJ33: Concluido | AL33: 28/07/2022 | AM33: 27/07/2022 21:00 | AN33: 27/07/2022 21:00 | AO33: 28/07/2022 21:00 | AP33: SIGLOCAL | AQ33: Avaliado | AS33: Normal | AT33: 28/08/2022 | AU33: 27/07/2022 21:00 | AV33: 31/07/2022 21:00 | AW33: 31/07/2022 21:00 | AX33: ANDRE MAGIORE | AY33: Avaliado | BB33: 28/08/2022 | BC33: 31/07/2022 21:00 | BD33: 31/07/2022 21:00 | BE33: 31/07/2022 21:00 | BF33: ANDERSON SCARPINO | BH33: FALSE | BK33: FALSE
B34: 15292 | C34: COZAC | D34: 6660 | E34: 266383 | F34: 191796 | H34: Imóvel Urbano | I34: Casa Residencial | J34: Ribeirão Preto | K34: SP | L34: Localizado | M34: Nível 1 | N34: Validação Avaliação Urbano | O34: rd.avaliacao@enforcegroup.com.br | Q34: JULIA JORGE | R34: Concluída | S34: 27/06/2022 | T34: 27/05/2022 08:53 | U34: 26/05/2022 21:00 | V34: 12/06/2022 21:00 | W34: 19/06/2022 21:00 | X34: =W34*1 -> 44731.875 | Y34: MIGRADO_ZOHO | Z34: Pesquisa de Bens | AA34: BANCO DO BRASIL (SGL_NAME) | AB34: Rua Barão de Cotegipe, 683 | AC34: Vila Tibério | AD34: 150 | AE34: 0 | AF34: 282 | AG34: m2 | AH34: T1 | AI34: Remota | AJ34: Concluido | AL34: 02/06/2022 | AM34: 26/05/2022 21:00 | AN34: 26/05/2022 21:00 | AO34: 01/06/2022 21:00 | AP34: HERGOM | AQ34: Avaliado | AS34: Normal | AT34: 27/06/2022 | AU34: 26/05/2022 21:00 | AV34: 12/06/2022 21:00 | AW34: 19/06/2022 21:00 | AX34: JULIA JORGE | AY34: Avaliado | BB34: 27/06/2022 | BC34: 19/06/2022 21:00 | BD34: 12/06/2022 21:00 | BE34: 29/06/2022 21:00 | BF34: MARINA FAHL | BH34: FALSE | BK34: FALSE
B35: 15292 | C35: COZAC | D35: 11054 | E35: 737278.6 | F35: 737278.6 | H35: Imóvel Urbano | I35: Gleba urbana | J35: Ribeirão Preto | K35: SP | L35: Localizado | M35: Nível 3 | N35: Validação Avaliação Urbano | O35: ANDERSON SCARPINO | P35: ENFORCE RJ E FALÊNCIA | Q35: ANDERSON SCARPINO | R35: Concluída | S35: 16/10/2023 | T35: 27/09/2023 07:51 | U35: 12/10/2023 20:49 | V35: 16/10/2023 09:05 | W35: 17/10/2023 12:09 | X35: =W35*1 -> 45216.506 | Z35: Acordo | AA35: BANCO DO BRASIL (SGL_NAME) | AB35: Rua Carlos Augusto Brasão | AC35: Loteamento Santa Terezinha | AF35: 12000 | AG35: m2 | AH35: T1 | AI35: Remota | AJ35: Concluido | AK35: Complexa | AL35: 02/08/2023 | AM35: 01/08/2023 12:14 | AN35: 01/08/2023 12:18 | AO35: 01/08/2023 18:21 | AP35: AGROFFICIO ATENDIMENTO | AT35: 10/10/2023 | AU35: 12/10/2023 20:49 | AV35: 28/09/2023 09:39 | AW35: 12/10/2023 20:49 | AX35: AHEAD ARQUITETURA | BB35: 16/10/2023 | BC35: 12/10/2023 20:49 | BD35: 16/10/2023 09:05 | BE35: 17/10/2023 12:09 | BF35: ANDERSON SCARPINO | BH35: FALSE | BK35: FALSE
B36: 15292 | C36: COZAC | D36: 11054 | E36: 0 | F36: 0 | H36: Imóvel Urbano | I36: Gleba urbana | J36: Ribeirão Preto | K36: SP | L36: Localizado | M36: Nível 1 | N36: Validação Avaliação Urbano | O36: GUILHERME MARQUES | P36: ENFORCE RJ E FALÊNCIA | Q36: CLAUDIO OKADA | R36: Concluída | S36: 03/08/2023 | T36: 01/08/2023 12:14 | U36: 02/08/2023 12:29 | V36: 02/08/2023 15:21 | W36: 22/08/2023 16:11 | X36: =W36*1 -> 45160.674 | Z36: Acordo | AA36: BANCO DO BRASIL (SGL_NAME) | AB36: Rua Carlos Augusto Brasão | AC36: Loteamento Santa Terezinha | AF36: 12000 | AG36: m2 | AH36: T1 | AI36: Remota | AJ36: Concluido | AK36: Complexa | AL36: 02/08/2023 | AM36: 01/08/2023 12:14 | AN36: 01/08/2023 12:18 | AO36: 01/08/2023 18:21 | AP36: AGROFFICIO ATENDIMENTO | AQ36: Impossível Avaliar | AR36: Matrícula relacionada | AS36: Complexa | AT36: 02/08/2023 | AU36: 02/08/2023 12:29 | AV36: 02/08/2023 09:45 | AW36: 02/08/2023 12:29 | AX36: Bruno Ícaro | AY36: Impossível Avaliar | AZ36: Matrícula relacionada | BA36: Complexa | BB36: 03/08/2023 | BC36: 02/08/2023 12:29 | BD36: 02/08/2023 15:21 | BE36: 22/08/2023 16:11 | BF36: CLAUDIO OKADA | BH36: FALSE | BK36: FALSE
B37: 15292 | C37: COZAC | D37: 11054 | E37: 3763636.4 | F37: 1505454.6 | H37: Imóvel Urbano | I37: Gleba urbana | J37: Ribeirão Preto | K37: SP | L37: Parcialmente Localizado | M37: Nível 0 | N37: Validação Avaliação Urbano | O37: TIFANY ARAUJO | P37: Investigação | Q37: CLAUDIO OKADA | R37: Concluída | S37: 03/05/2023 | T37: 20/04/2023 16:41 | U37: 03/05/2023 09:53 | V37: 03/05/2023 10:21 | W37: 03/05/2023 10:33 | X37: =W37*1 -> 45049.44 | Z37: Pesquisa de Bens | AA37: BANCO DO BRASIL (SGL_NAME) | AB37: N/A | AC37: Morro Do Cipó | AF37: 12000 | AG37: m2 | AH37: T2 | AI37: Remota | AJ37: Concluido | AL37: 26/04/2023 | AM37: 24/04/2023 12:12 | AN37: 24/04/2023 12:32 | AO37: 26/04/2023 14:39 | AP37: SIGLOCAL ACESSO | AQ37: Avaliado | AR37: Concluido | AS37: Normal | AT37: 03/05/2023 | AU37: 03/05/2023 09:53 | AV37: 02/05/2023 11:24 | AW37: 03/05/2023 09:53 | AX37: Bruno Ícaro | AY37: Avaliado | AZ37: Concluido | BA37: Normal | BB37: 03/05/2023 | BC37: 03/05/2023 09:53 | BD37: 03/05/2023 10:21 | BE37: 03/05/2023 10:33 | BF37: CLAUDIO OKADA | BH37: FALSE | BK37: FALSE
B38: 15292 | C38: COZAC | D38: 11054 | E38: 2810000 | F38: 1967000 | H38: Imóvel Urbano | I38: Gleba Urbana | J38: Ribeirão Preto | K38: SP | L38: Parcialmente Localizado | M38: Nível 0 | N38: Validação Avaliação Urbano | O38: rd.avaliacao@enforcegroup.com.br | Q38: ANDRE MAGIORE | R38: Concluída | S38: 28/08/2022 | T38: 28/07/2022 14:26 | U38: 27/07/2022 21:00 | V38: 31/07/2022 21:00 | W38: 31/07/2022 21:00 | X38: =W38*1 -> 44773.875 | Y38: MIGRADO_ZOHO | Z38: Pesquisa de Bens | AA38: BANCO DO BRASIL (SGL_NAME) | AF38: 12000 | AG38: m2 | AH38: T1 | AI38: Remota | AJ38: Concluido | AL38: 28/07/2022 | AM38: 27/07/2022 21:00 | AN38: 27/07/2022 21:00 | AO38: 28/07/2022 21:00 | AP38: SIGLOCAL | AQ38: Avaliado | AS38: Normal | AT38: 28/08/2022 | AU38: 27/07/2022 21:00 | AV38: 31/07/2022 21:00 | AW38: 31/07/2022 21:00 | AX38: ANDRE MAGIORE | AY38: Avaliado | BB38: 28/08/2022 | BC38: 31/07/2022 21:00 | BD38: 31/07/2022 21:00 | BE38: 31/07/2022 21:00 | BF38: ANDERSON SCARPINO | BH38: FALSE | BK38: FALSE
B39: 15292 | C39: COZAC | D39: 11054 | E39: 145777 | F39: 102044 | H39: Imóvel Urbano | I39: Casa Residencial | J39: Ribeirão Preto | K39: SP | L39: Localizado | M39: Nível 1 | N39: Validação Avaliação Urbano | O39: rd.avaliacao@enforcegroup.com.br | Q39: JULIA JORGE | R39: Concluída | S39: 27/06/2022 | T39: 27/05/2022 08:51 | U39: 26/05/2022 21:00 | V39: 12/06/2022 21:00 | W39: 15/06/2022 21:00 | X39: =W39*1 -> 44727.875 | Y39: MIGRADO_ZOHO | Z39: Pesquisa de Bens | AA39: BANCO DO BRASIL (SGL_NAME) | AB39: Rua Antônio Gouveia, 785/781 | AC39: Campos Elísios | AD39: 69 | AE39: 0 | AF39: 102 | AG39: m2 | AH39: T1 | AI39: Remota | AJ39: Concluido | AL39: 02/06/2022 | AM39: 26/05/2022 21:00 | AN39: 26/05/2022 21:00 | AO39: 01/06/2022 21:00 | AP39: HERGOM | AQ39: Avaliado | AS39: Réplica | AT39: 27/06/2022 | AU39: 26/05/2022 21:00 | AV39: 12/06/2022 21:00 | AW39: 15/06/2022 21:00 | AX39: JULIA JORGE | AY39: Avaliado | BB39: 27/06/2022 | BC39: 15/06/2022 21:00 | BD39: 12/06/2022 21:00 | BE39: 29/06/2022 21:00 | BF39: MARINA FAHL | BH39: FALSE | BK39: FALSE
B40: 15292 | C40: COZAC | D40: 11055 | E40: 1832137.3 | F40: 1832137.3 | H40: Imóvel Urbano | I40: Gleba urbana | J40: Ribeirão Preto | K40: SP | L40: Localizado | M40: Nível 3 | N40: Validação Avaliação Urbano | O40: ANDERSON SCARPINO | P40: ENFORCE RJ E FALÊNCIA | Q40: ANDERSON SCARPINO | R40: Concluída | S40: 16/10/2023 | T40: 27/09/2023 07:55 | U40: 12/10/2023 20:49 | V40: 16/10/2023 09:05 | W40: 17/10/2023 11:55 | X40: =W40*1 -> 45216.497 | Z40: Acordo | AA40: BANCO DO BRASIL (SGL_NAME) | AB40: Rua Carlos Augusto Brasão | AC40: Loteamento Santa Terezinha | AF40: 29820 | AG40: m2 | AH40: T1 | AI40: Remota | AJ40: Concluido | AK40: Complexa | AL40: 02/08/2023 | AM40: 01/08/2023 12:14 | AN40: 01/08/2023 12:17 | AO40: 01/08/2023 18:26 | AP40: AGROFFICIO ATENDIMENTO | AT40: 10/10/2023 | AU40: 12/10/2023 20:49 | AV40: 28/09/2023 09:39 | AW40: 12/10/2023 20:49 | AX40: AHEAD ARQUITETURA | BB40: 16/10/2023 | BC40: 12/10/2023 20:49 | BD40: 16/10/2023 09:05 | BE40: 17/10/2023 11:55 | BF40: ANDERSON SCARPINO | BH40: FALSE | BK40: FALSE
B41: 15292 | C41: COZAC | D41: 11055 | E41: 0 | F41: 0 | H41: Imóvel Urbano | I41: Gleba urbana | J41: Ribeirão Preto | K41: SP | L41: Localizado | M41: Nível 1 | N41: Validação Avaliação Urbano | O41: GUILHERME MARQUES | P41: ENFORCE RJ E FALÊNCIA | Q41: CLAUDIO OKADA | R41: Concluída | S41: 03/08/2023 | T41: 01/08/2023 12:14 | U41: 02/08/2023 12:29 | V41: 02/08/2023 15:21 | W41: 22/08/2023 16:11 | X41: =W41*1 -> 45160.674 | Z41: Acordo | AA41: BANCO DO BRASIL (SGL_NAME) | AB41: Rua Carlos Augusto Brasão | AC41: Loteamento Santa Terezinha | AF41: 29820 | AG41: m2 | AH41: T1 | AI41: Remota | AJ41: Concluido | AK41: Complexa | AL41: 02/08/2023 | AM41: 01/08/2023 12:14 | AN41: 01/08/2023 12:17 | AO41: 01/08/2023 18:26 | AP41: AGROFFICIO ATENDIMENTO | AQ41: Impossível Avaliar | AR41: Matrícula relacionada | AS41: Complexa | AT41: 02/08/2023 | AU41: 02/08/2023 12:29 | AV41: 02/08/2023 09:45 | AW41: 02/08/2023 12:29 | AX41: Bruno Ícaro | AY41: Impossível Avaliar | AZ41: Matrícula relacionada | BA41: Complexa | BB41: 03/08/2023 | BC41: 02/08/2023 12:29 | BD41: 02/08/2023 15:21 | BE41: 22/08/2023 16:11 | BF41: CLAUDIO OKADA | BH41: FALSE | BK41: FALSE
B42: 15292 | C42: COZAC | D42: 11055 | H42: Imóvel Rural | I42: Gleba rural | J42: Ribeirão Preto | K42: SP | L42: Não Localizado | M42: Nível 1 | N42: Localizar Imóvel | O42: NATHALIA DIAS | P42: Investigação | Q42: AGROFFICIO ATENDIMENTO | R42: Concluída | S42: 13/04/2023 | T42: 28/03/2023 17:05 | U42: 10/04/2023 14:25 | V42: 10/04/2023 14:39 | W42: 13/04/2023 10:13 | X42: =W42*1 -> 45029.426 | Z42: Pesquisa de Bens | AA42: BANCO DO BRASIL (SGL_NAME) | AB42: N/A | AC42: Sítio Santa Justa | AF42: 2.98 | AG42: m2 | AH42: T3 | AI42: Remota | AJ42: Concluido | AL42: 13/04/2023 | AM42: 10/04/2023 14:25 | AN42: 10/04/2023 14:39 | AO42: 13/04/2023 10:13 | AP42: AGROFFICIO ATENDIMENTO | BG42: FALSE | BH42: FALSE | BK42: FALSE
B43: 15292 | C43: COZAC | D43: 11055 | E43: 6016185 | F43: 3910520 | H43: Imóvel Urbano | I43: Gleba Urbana | J43: Ribeirão Preto | K43: SP | L43: Parcialmente Localizado | M43: Nível 0 | N43: Validação Avaliação Urbano | O43: rd.avaliacao@enforcegroup.com.br | Q43: ANDRE MAGIORE | R43: Concluída | S43: 28/08/2022 | T43: 28/07/2022 14:45 | U43: 27/07/2022 21:00 | V43: 31/07/2022 21:00 | W43: 31/07/2022 21:00 | X43: =W43*1 -> 44773.875 | Y43: MIGRADO_ZOHO | Z43: Pesquisa de Bens | AA43: BANCO DO BRASIL (SGL_NAME) | AF43: 29820 | AG43: m2 | AH43: T1 | AI43: Remota | AJ43: Concluido | AL43: 28/07/2022 | AM43: 27/07/2022 21:00 | AN43: 27/07/2022 21:00 | AO43: 28/07/2022 21:00 | AP43: SIGLOCAL | AQ43: Avaliado | AS43: Normal | AT43: 28/08/2022 | AU43: 27/07/2022 21:00 | AV43: 31/07/2022 21:00 | AW43: 31/07/2022 21:00 | AX43: ANDRE MAGIORE | AY43: Avaliado | BB43: 28/08/2022 | BC43: 31/07/2022 21:00 | BD43: 31/07/2022 21:00 | BE43: 31/07/2022 21:00 | BF43: ANDERSON SCARPINO | BH43: FALSE | BK43: FALSE
B44: 15292 | C44: COZAC | D44: 11055 | E44: 145777 | F44: 102044 | H44: Imóvel Urbano | I44: Casa Residencial | J44: Ribeirão Preto | K44: SP | L44: Localizado | M44: Nível 1 | N44: Validação Avaliação Urbano | O44: rd.avaliacao@enforcegroup.com.br | Q44: JULIA JORGE | R44: Concluída | S44: 27/06/2022 | T44: 27/05/2022 08:40 | U44: 26/05/2022 21:00 | V44: 12/06/2022 21:00 | W44: 15/06/2022 21:00 | X44: =W44*1 -> 44727.875 | Y44: MIGRADO_ZOHO | Z44: Pesquisa de Bens | AA44: BANCO DO BRASIL (SGL_NAME) | AB44: Rua Antônio Gouveia, 767 | AC44: Campos Elísios | AD44: 69 | AE44: 0 | AF44: 102 | AG44: m2 | AH44: T1 | AI44: Remota | AJ44: Concluido | AL44: 02/06/2022 | AM44: 26/05/2022 21:00 | AN44: 26/05/2022 21:00 | AO44: 01/06/2022 21:00 | AP44: HERGOM | AQ44: Avaliado | AS44: Normal | AT44: 27/06/2022 | AU44: 26/05/2022 21:00 | AV44: 12/06/2022 21:00 | AW44: 15/06/2022 21:00 | AX44: JULIA JORGE | AY44: Avaliado | BB44: 27/06/2022 | BC44: 15/06/2022 21:00 | BD44: 12/06/2022 21:00 | BE44: 29/06/2022 21:00 | BF44: MARINA FAHL | BH44: FALSE | BK44: FALSE
B45: 15292 | C45: COZAC | D45: 23299 | E45: 7158000 | F45: 4796000 | H45: Imóvel Urbano | I45: Terreno urbano | J45: Ribeirão Preto | K45: SP | L45: Localizado | M45: Nível 2 | N45: Validação Avaliação Urbano | O45: IVO LAMAS | P45: GESTÃO PORTFÓLIO | Q45: ANDERSON SCARPINO | R45: Concluída | S45: 14/08/2025 | T45: 30/07/2025 12:13 | U45: 13/08/2025 20:31 | V45: 14/08/2025 09:20 | W45: 14/08/2025 10:07 | X45: =W45*1 -> 45883.422 | Z45: Análise de Processo | AA45: BANCO DO BRASIL (SGL_NAME) | AB45: Rua Abrahão Issa Halach, 1030 | AC45: Ribeirânia | AF45: 4455.09 | AG45: m2 | AH45: T1 | AI45: Remota | AJ45: Concluido | AL45: 28/07/2022 | AM45: 13/10/2022 20:50 | AN45: 27/07/2022 21:00 | AO45: 27/07/2022 21:00 | AP45: SIGLOCAL | AT45: 14/08/2025 | AU45: 13/08/2025 20:31 | AV45: 13/08/2025 09:39 | AW45: 13/08/2025 20:31 | AX45: Victor Libarino | BB45: 14/08/2025 | BC45: 13/08/2025 20:31 | BD45: 14/08/2025 09:20 | BE45: 14/08/2025 10:07 | BF45: ANDERSON SCARPINO | BG45: TRUE | BH45: FALSE | BK45: FALSE
B46: 15292 | C46: COZAC | D46: 23299 | E46: 5681000 | F46: 3833000 | H46: Imóvel Urbano | I46: Terreno urbano | J46: Ribeirão Preto | K46: SP | L46: Localizado | M46: Nível 2 | N46: Validação Avaliação Urbano | O46: THIAGO MACHADO | P46: GESTÃO PORTFÓLIO | Q46: ANDERSON SCARPINO | R46: Concluída | S46: 20/09/2023 | T46: 06/06/2023 16:18 | U46: 20/09/2023 08:52 | V46: 20/09/2023 08:52 | W46: 20/09/2023 09:15 | X46: =W46*1 -> 45189.385 | Z46: Acordo | AA46: BANCO DO BRASIL (SGL_NAME) | AB46: Rua Abrahão Issa Halach, 1030 | AC46: Ribeirânia | AF46: 4455.09 | AG46: m2 | AH46: T1 | AI46: Remota | AJ46: Concluido | AL46: 28/07/2022 | AM46: 13/10/2022 20:50 | AN46: 27/07/2022 21:00 | AO46: 27/07/2022 21:00 | AP46: SIGLOCAL | AT46: 05/07/2023 | AU46: 20/09/2023 08:52 | AV46: 05/07/2023 14:36 | AW46: 05/07/2023 14:37 | AX46: ANDERSON SCARPINO | BB46: 20/09/2023 | BC46: 20/09/2023 08:52 | BD46: 20/09/2023 08:52 | BE46: 20/09/2023 09:15 | BF46: ANDERSON SCARPINO | BG46: TRUE | BH46: TRUE | BK46: FALSE
B47: 15292 | C47: COZAC | D47: 23299 | E47: 3048592 | F47: 1219436.8 | H47: Imóvel Urbano | I47: Terreno urbano | J47: Ribeirão Preto | K47: SP | L47: Parcialmente Localizado | M47: Nível 0 | N47: Validação Avaliação Urbano | O47: NATHALIA DIAS | P47: Investigação | Q47: CLAUDIO OKADA | R47: Concluída | S47: 17/04/2023 | T47: 28/03/2023 17:48 | U47: 10/04/2023 19:22 | V47: 17/04/2023 09:39 | W47: 17/04/2023 10:14 | X47: =W47*1 -> 45033.426 | Z47: Pesquisa de Bens | AA47: BANCO DO BRASIL (SGL_NAME) | AB47: Rua Abrahão Issa Halack | AC47: Riberânia | AD47: 528.22 | AF47: 4455.09 | AG47: m2 | AH47: T1 | AI47: Remota | AJ47: Concluido | AL47: 05/04/2023 | AM47: 28/03/2023 17:48 | AN47: 29/03/2023 09:03 | AO47: 31/03/2023 12:07 | AP47: AGROFFICIO ATENDIMENTO | AQ47: Avaliado | AR47: Concluido | AS47: Normal | AT47: 10/04/2023 | AU47: 10/04/2023 19:22 | AV47: 03/04/2023 09:08 | AW47: 10/04/2023 19:22 | AX47: RAIZA GONÇALVES | AY47: Avaliado | AZ47: Concluido | BA47: Normal | BB47: 17/04/2023 | BC47: 10/04/2023 19:22 | BD47: 17/04/2023 09:39 | BE47: 17/04/2023 10:14 | BF47: CLAUDIO OKADA | BH47: FALSE | BK47: FALSE
B48: 15292 | C48: COZAC | D48: 23299 | E48: 9356985 | F48: 6549889 | H48: Imóvel Urbano | I48: Terreno urbano | J48: Ribeirão Preto | K48: SP | L48: Localizado | M48: Nível 0 | N48: Validação Avaliação Urbano | O48: rd.avaliacao@enforcegroup.com.br | Q48: ANDRE MAGIORE | R48: Concluída | S48: 28/08/2022 | T48: 28/07/2022 14:34 | U48: 27/07/2022 21:00 | V48: 31/07/2022 21:00 | W48: 31/07/2022 21:00 | X48: =W48*1 -> 44773.875 | Y48: MIGRADO_ZOHO | Z48: Pesquisa de Bens | AA48: BANCO DO BRASIL (SGL_NAME) | AB48: Rua Abrahão Issa Halach, 1030 | AC48: Ribeirânia | AD48: 0 | AE48: 0 | AF48: 5800 | AG48: m2 | AH48: T1 | AI48: Remota | AJ48: Concluido | AL48: 28/07/2022 | AM48: 27/07/2022 21:00 | AN48: 27/07/2022 21:00 | AO48: 27/07/2022 21:00 | AP48: SIGLOCAL | AQ48: Avaliado | AS48: Normal | AT48: 28/08/2022 | AU48: 27/07/2022 21:00 | AV48: 31/07/2022 21:00 | AW48: 31/07/2022 21:00 | AX48: ANDRE MAGIORE | AY48: Avaliado | BB48: 28/08/2022 | BC48: 31/07/2022 21:00 | BD48: 31/07/2022 21:00 | BE48: 31/07/2022 21:00 | BF48: ANDERSON SCARPINO | BH48: FALSE | BK48: FALSE
B49: 15292 | C49: COZAC | D49: 32744 | E49: 2741000 | F49: 1645000 | H49: Imóvel Urbano | I49: Casa Residencial | J49: Ribeirão Preto | K49: SP | L49: Localizado | M49: Nível 2 | N49: Validação Avaliação Urbano | O49: ANA CLARA | P49: Gestão BNDU | Q49: ANDERSON SCARPINO | R49: Concluída | S49: 17/07/2025 | T49: 05/06/2025 17:11 | U49: 17/07/2025 17:20 | V49: 17/07/2025 17:21 | W49: 17/07/2025 17:22 | X49: =W49*1 -> 45855.724 | Z49: Pesquisa de Bens | AA49: BANCO DO BRASIL (SGL_NAME) | AB49: Rua Olavo Bilac | AC49: Jardim Sumare | AD49: 400 | AF49: 714.6 | AG49: m2 | AH49: T1 | AI49: Remota | AJ49: Concluido | AL49: 04/04/2023 | AM49: 28/03/2023 17:57 | AN49: 29/03/2023 09:04 | AO49: 04/04/2023 11:34 | AP49: SIGLOCAL ACESSO | AT49: 18/07/2025 | AU49: 17/07/2025 17:20 | AV49: 17/07/2025 12:25 | AW49: 17/07/2025 16:32 | AX49: Victor Libarino | BB49: 17/07/2025 | BC49: 17/07/2025 17:20 | BD49: 17/07/2025 17:21 | BE49: 17/07/2025 17:22 | BF49: ANDERSON SCARPINO | BG49: TRUE | BH49: TRUE | BK49: FALSE
B50: 15292 | C50: COZAC | D50: 32744 | E50: 1381000 | F50: 980000 | H50: Imóvel Urbano | I50: Casa Residencial | J50: Ribeirão Preto | K50: SP | L50: Localizado | M50: Nível 2 | N50: Validação Avaliação Urbano | O50: THIAGO MACHADO | P50: GESTÃO PORTFÓLIO | Q50: ANDERSON SCARPINO | R50: Concluída | S50: 10/07/2023 | T50: 06/06/2023 16:18 | U50: 10/07/2023 14:17 | V50: 10/07/2023 14:26 | W50: 10/07/2023 14:29 | X50: =W50*1 -> 45117.603 | Z50: Acordo | AA50: BANCO DO BRASIL (SGL_NAME) | AB50: Rua Olavo Bilac | AC50: Jardim Sumare | AD50: 600 | AF50: 714.6 | AG50: m2 | AH50: T1 | AI50: Remota | AJ50: Concluido | AL50: 04/04/2023 | AM50: 28/03/2023 17:57 | AN50: 29/03/2023 09:04 | AO50: 04/04/2023 11:34 | AP50: SIGLOCAL ACESSO | AT50: 10/07/2023 | AU50: 10/07/2023 14:17 | AV50: 10/07/2023 12:26 | AW50: 10/07/2023 14:17 | AX50: RAPHAEL PARENTE | BB50: 10/07/2023 | BC50: 10/07/2023 14:17 | BD50: 10/07/2023 14:26 | BE50: 10/07/2023 14:29 | BF50: ANDERSON SCARPINO | BG50: TRUE | BH50: FALSE | BK50: FALSE
B51: 15292 | C51: COZAC | D51: 32744 | E51: 1332165.4 | F51: 959159.07 | H51: Imóvel Urbano | I51: Casa Residencial | J51: Ribeirão Preto | K51: SP | L51: Localizado | M51: Nível 1 | N51: Validação Avaliação Urbano | O51: NATHALIA DIAS | P51: Investigação | Q51: MATHEUS NAVARRO | R51: Concluída | S51: 20/04/2023 | T51: 28/03/2023 17:57 | U51: 17/04/2023 13:03 | V51: 17/04/2023 16:04 | W51: 19/04/2023 18:20 | X51: =W51*1 -> 45035.764 | Z51: Pesquisa de Bens | AA51: BANCO DO BRASIL (SGL_NAME) | AB51: Rua Olavo Bilac | AC51: Jardim Sumare | AD51: 400 | AF51: 714.6 | AG51: m2 | AH51: T1 | AI51: Remota | AJ51: Concluido | AL51: 04/04/2023 | AM51: 28/03/2023 17:57 | AN51: 29/03/2023 09:04 | AO51: 04/04/2023 11:34 | AP51: SIGLOCAL ACESSO | AQ51: Avaliado | AR51: Concluido | AS51: Normal | AT51: 18/04/2023 | AU51: 17/04/2023 13:03 | AV51: 06/04/2023 08:20 | AW51: 17/04/2023 13:03 | AX51: RAIZA GONÇALVES | AY51: Avaliado | AZ51: Concluido | BA51: Normal | BB51: 20/04/2023 | BC51: 17/04/2023 13:03 | BD51: 17/04/2023 16:04 | BE51: 19/04/2023 18:20 | BF51: MATHEUS NAVARRO | BH51: FALSE | BK51: FALSE
B52: 15292 | C52: COZAC | D52: 32744 | E52: 1573452 | F52: 1180089 | H52: Imóvel Urbano | I52: Casa Residencial | J52: Ribeirão Preto | K52: SP | L52: Localizado | M52: Nível 0 | N52: Validação Avaliação Urbano | O52: rd.avaliacao@enforcegroup.com.br | Q52: MATHEUS NAVARRO | R52: Concluída | S52: 28/08/2022 | T52: 28/07/2022 14:44 | U52: 27/07/2022 21:00 | V52: 31/07/2022 21:00 | W52: 31/07/2022 21:00 | X52: =W52*1 -> 44773.875 | Y52: MIGRADO_ZOHO | Z52: Pesquisa de Bens | AA52: BANCO DO BRASIL (SGL_NAME) | AB52: Rua Olavo Bilac, 1380 | AC52: Jardim Sumaré | AD52: 500 | AE52: 0 | AF52: 714.6 | AG52: m2 | AH52: T1 | AI52: Remota | AJ52: Concluido | AL52: 28/07/2022 | AM52: 27/07/2022 21:00 | AN52: 27/07/2022 21:00 | AO52: 27/07/2022 21:00 | AP52: SIGLOCAL | AQ52: Avaliado | AT52: 28/08/2022 | AU52: 27/07/2022 21:00 | AV52: 31/07/2022 21:00 | AW52: 31/07/2022 21:00 | AX52: MATHEUS NAVARRO | AY52: Avaliado | BB52: 28/08/2022 | BC52: 31/07/2022 21:00 | BD52: 31/07/2022 21:00 | BE52: 31/07/2022 21:00 | BF52: MATHEUS NAVARRO | BH52: FALSE | BK52: FALSE
B53: 15292 | C53: COZAC | D53: 32744 | E53: 2046104 | F53: 1534578 | H53: Imóvel Urbano | I53: Casa Residencial | J53: Ribeirão Preto | K53: SP | L53: Localizado | M53: Nível 1 | N53: Validação Avaliação Urbano | O53: rd.avaliacao@enforcegroup.com.br | Q53: JULIA JORGE | R53: Concluída | S53: 27/06/2022 | T53: 27/05/2022 08:48 | U53: 26/05/2022 21:00 | V53: 12/06/2022 21:00 | W53: 19/06/2022 21:00 | X53: =W53*1 -> 44731.875 | Y53: MIGRADO_ZOHO | Z53: Pesquisa de Bens | AA53: BANCO DO BRASIL (SGL_NAME) | AB53: Rua Olavo Bilac, 1380 | AC53: Jardim América | AD53: 1044.61 | AE53: 0 | AF53: 1471.6 | AG53: m2 | AH53: T1 | AI53: Remota | AJ53: Concluido | AL53: 02/06/2022 | AM53: 26/05/2022 21:00 | AN53: 26/05/2022 21:00 | AO53: 01/06/2022 21:00 | AP53: HERGOM | AQ53: Avaliado | AS53: Normal | AT53: 27/06/2022 | AU53: 26/05/2022 21:00 | AV53: 12/06/2022 21:00 | AW53: 19/06/2022 21:00 | AX53: JULIA JORGE | AY53: Avaliado | BB53: 27/06/2022 | BC53: 19/06/2022 21:00 | BD53: 12/06/2022 21:00 | BE53: 29/06/2022 21:00 | BF53: MARINA FAHL | BH53: FALSE | BK53: FALSE
B54: 15292 | C54: COZAC | D54: 36052 | E54: 159000 | F54: 122000 | H54: Imóvel Urbano | I54: Apartamento Padrão | J54: Ribeirão Preto | K54: SP | L54: Localizado | M54: Nível 2 | N54: Validação Avaliação Urbano | O54: FERNANDA GOMES | P54: Gestão BNDU | Q54: ANDERSON SCARPINO | R54: Concluída | S54: 16/01/2026 | T54: 19/12/2025 16:55 | U54: 16/01/2026 18:11 | V54: 16/01/2026 18:13 | W54: 16/01/2026 18:15 | X54: =W54*1 -> 46038.76 | Z54: Pesquisa de Bens | AA54: BANCO DO BRASIL (SGL_NAME) | AB54: Rua Visconde de Inhaúma | AC54: Centro | AD54: 78.9 | AE54: 64.4 | AG54: m2 | AH54: T1 | AI54: Remota | AJ54: Concluido | AL54: 05/04/2023 | AM54: 28/03/2023 17:44 | AN54: 29/03/2023 09:03 | AO54: 30/03/2023 17:13 | AP54: AGROFFICIO ATENDIMENTO | AT54: 16/01/2026 | AU54: 16/01/2026 18:11 | AV54: 19/12/2025 17:33 | AW54: 16/01/2026 18:11 | AX54: Victor Libarino - Financeiro (N2/N3) | BB54: 16/01/2026 | BC54: 16/01/2026 18:11 | BD54: 16/01/2026 18:13 | BE54: 16/01/2026 18:15 | BF54: ANDERSON SCARPINO | BH54: FALSE | BK54: FALSE
B55: 15292 | C55: COZAC | D55: 36052 | E55: 165000 | F55: 123000 | H55: Imóvel Urbano | I55: Sala comercial | J55: Ribeirão Preto | K55: SP | L55: Localizado | M55: Nível 2 | N55: Validação Avaliação Urbano | O55: THIAGO MACHADO | P55: GESTÃO PORTFÓLIO | Q55: ANDERSON SCARPINO | R55: Concluída | S55: 20/10/2023 | T55: 06/06/2023 16:18 | U55: 20/10/2023 16:50 | V55: 20/10/2023 16:51 | W55: 20/10/2023 16:53 | X55: =W55*1 -> 45219.703 | Z55: Acordo | AA55: BANCO DO BRASIL (SGL_NAME) | AB55: Rua Visconde de Inhaúma | AC55: Centro | AD55: 78.9 | AE55: 64.4 | AG55: m2 | AH55: T1 | AI55: Remota | AJ55: Concluido | AL55: 05/04/2023 | AM55: 28/03/2023 17:44 | AN55: 29/03/2023 09:03 | AO55: 30/03/2023 17:13 | AP55: AGROFFICIO ATENDIMENTO | AT55: 10/07/2023 | AU55: 20/10/2023 16:50 | AV55: 10/07/2023 12:29 | AW55: 10/07/2023 14:46 | AX55: RAPHAEL PARENTE | BB55: 20/10/2023 | BC55: 20/10/2023 16:50 | BD55: 20/10/2023 16:51 | BE55: 20/10/2023 16:53 | BF55: ANDERSON SCARPINO | BG55: TRUE | BH55: TRUE | BK55: FALSE
B56: 15292 | C56: COZAC | D56: 36052 | E56: 110378.82 | F56: 110378.82 | H56: Imóvel Urbano | I56: Sala comercial | J56: Ribeirão Preto | K56: SP | L56: Localizado | M56: Nível 1 | N56: Validação Avaliação Urbano | O56: NATHALIA DIAS | P56: Investigação | Q56: MATHEUS NAVARRO | R56: Concluída | S56: 20/04/2023 | T56: 28/03/2023 17:44 | U56: 06/04/2023 17:46 | V56: 14/04/2023 10:35 | W56: 19/04/2023 18:10 | X56: =W56*1 -> 45035.757 | Z56: Pesquisa de Bens | AA56: BANCO DO BRASIL (SGL_NAME) | AB56: Rua Visconde de Inhaúma | AC56: Centro | AD56: 78.9 | AE56: 64.4 | AG56: m2 | AH56: T1 | AI56: Remota | AJ56: Concluido | AL56: 05/04/2023 | AM56: 28/03/2023 17:44 | AN56: 29/03/2023 09:03 | AO56: 30/03/2023 17:13 | AP56: AGROFFICIO ATENDIMENTO | AQ56: Avaliado | AR56: Concluido | AS56: Réplica | AT56: 10/04/2023 | AU56: 06/04/2023 17:46 | AV56: 03/04/2023 09:08 | AW56: 06/04/2023 17:45 | AX56: RAIZA GONÇALVES | AY56: Avaliado | AZ56: Concluido | BA56: Réplica | BB56: 20/04/2023 | BC56: 06/04/2023 17:46 | BD56: 14/04/2023 10:35 | BE56: 19/04/2023 18:10 | BF56: MATHEUS NAVARRO | BH56: FALSE | BK56: FALSE
B57: 15292 | C57: COZAC | D57: 36052 | E57: 146258 | F57: 117006 | H57: Imóvel Urbano | I57: Apartamento Padrão | J57: Ribeirão Preto | K57: SP | L57: Localizado | M57: Nível 0 | N57: Validação Avaliação Urbano | O57: rd.avaliacao@enforcegroup.com.br | Q57: MATHEUS NAVARRO | R57: Concluída | S57: 28/08/2022 | T57: 28/07/2022 14:31 | U57: 27/07/2022 21:00 | V57: 28/07/2022 21:00 | W57: 28/07/2022 21:00 | X57: =W57*1 -> 44770.875 | Y57: MIGRADO_ZOHO | Z57: Pesquisa de Bens | AA57: BANCO DO BRASIL (SGL_NAME) | AB57: Rua Visconde de Inhaúma, 490 | AC57: Centro | AD57: 0 | AE57: 64.4 | AF57: 0 | AG57: m2 | AH57: T1 | AI57: Remota | AJ57: Concluido | AL57: 28/07/2022 | AM57: 27/07/2022 21:00 | AN57: 27/07/2022 21:00 | AO57: 27/07/2022 21:00 | AP57: SIGLOCAL | AQ57: Avaliado | AT57: 28/08/2022 | AU57: 27/07/2022 21:00 | AV57: 28/07/2022 21:00 | AW57: 28/07/2022 21:00 | AX57: MATHEUS NAVARRO | AY57: Avaliado | BB57: 28/08/2022 | BC57: 28/07/2022 21:00 | BD57: 28/07/2022 21:00 | BE57: 28/07/2022 21:00 | BF57: MATHEUS NAVARRO | BH57: FALSE | BK57: FALSE
B58: 15292 | C58: COZAC | D58: 36052 | E58: 179991 | F58: 122394 | H58: Imóvel Urbano | I58: Casa Residencial | J58: Ribeirão Preto | K58: SP | L58: Localizado | M58: Nível 1 | N58: Validação Avaliação Urbano | O58: rd.avaliacao@enforcegroup.com.br | Q58: JULIA JORGE | R58: Concluída | S58: 27/06/2022 | T58: 27/05/2022 09:02 | U58: 26/05/2022 21:00 | V58: 12/06/2022 21:00 | W58: 19/06/2022 21:00 | X58: =W58*1 -> 44731.875 | Y58: MIGRADO_ZOHO | Z58: Pesquisa de Bens | AA58: BANCO DO BRASIL (SGL_NAME) | AB58: Rua Victório Farnocchi, 155 | AC58: Quintino Facci II | AD58: 110 | AE58: 0 | AF58: 200 | AG58: m2 | AH58: T1 | AI58: Remota | AJ58: Concluido | AL58: 02/06/2022 | AM58: 26/05/2022 21:00 | AN58: 26/05/2022 21:00 | AO58: 01/06/2022 21:00 | AP58: HERGOM | AQ58: Avaliado | AS58: Normal | AT58: 27/06/2022 | AU58: 26/05/2022 21:00 | AV58: 12/06/2022 21:00 | AW58: 19/06/2022 21:00 | AX58: JULIA JORGE | AY58: Avaliado | BB58: 27/06/2022 | BC58: 19/06/2022 21:00 | BD58: 12/06/2022 21:00 | BE58: 29/06/2022 21:00 | BF58: MARINA FAHL | BH58: FALSE | BK58: FALSE
B59: 15292 | C59: COZAC | D59: 36053 | E59: 137000 | F59: 105000 | H59: Imóvel Urbano | I59: Apartamento Padrão | J59: Ribeirão Preto | K59: SP | L59: Localizado | M59: Nível 2 | N59: Validação Avaliação Urbano | O59: FERNANDA GOMES | P59: Gestão BNDU | Q59: ANDERSON SCARPINO | R59: Concluída | S59: 13/01/2026 | T59: 19/12/2025 16:57 | U59: 11/01/2026 20:14 | V59: 13/01/2026 11:03 | W59: 13/01/2026 12:49 | X59: =W59*1 -> 46035.534 | Z59: Pesquisa de Bens | AA59: BANCO DO BRASIL (SGL_NAME) | AB59: Rua Visconde De Inhaúma | AC59: Centro | AD59: 78.9 | AE59: 64.4 | AG59: m2 | AH59: T1 | AI59: Remota | AJ59: Concluido | AL59: 05/04/2023 | AM59: 28/03/2023 17:43 | AN59: 29/03/2023 09:03 | AO59: 30/03/2023 17:13 | AP59: AGROFFICIO ATENDIMENTO | AT59: 16/01/2026 | AU59: 11/01/2026 20:14 | AV59: 19/12/2025 17:33 | AW59: 11/01/2026 20:14 | AX59: Victor Libarino - Financeiro (N2/N3) | BB59: 13/01/2026 | BC59: 11/01/2026 20:14 | BD59: 13/01/2026 11:03 | BE59: 13/01/2026 12:49 | BF59: ANDERSON SCARPINO | BH59: FALSE | BK59: FALSE
B60: 15292 | C60: COZAC | D60: 36053 | E60: 165000 | F60: 123000 | H60: Imóvel Urbano | I60: Sala comercial | J60: Ribeirão Preto | K60: SP | L60: Localizado | M60: Nível 2 | N60: Validação Avaliação Urbano | O60: THIAGO MACHADO | P60: GESTÃO PORTFÓLIO | Q60: ANDERSON SCARPINO | R60: Concluída | S60: 20/10/2023 | T60: 06/06/2023 16:18 | U60: 20/10/2023 17:07 | V60: 20/10/2023 17:08 | W60: 20/10/2023 17:10 | X60: =W60*1 -> 45219.715 | Z60: Acordo | AA60: BANCO DO BRASIL (SGL_NAME) | AB60: Rua Visconde De Inhaúma | AC60: Centro | AD60: 78.9 | AE60: 64.4 | AG60: m2 | AH60: T1 | AI60: Remota | AJ60: Concluido | AL60: 05/04/2023 | AM60: 28/03/2023 17:43 | AN60: 29/03/2023 09:03 | AO60: 30/03/2023 17:13 | AP60: AGROFFICIO ATENDIMENTO | AT60: 10/07/2023 | AU60: 20/10/2023 17:07 | AV60: 10/07/2023 12:29 | AW60: 10/07/2023 14:41 | AX60: RAPHAEL PARENTE | BB60: 20/10/2023 | BC60: 20/10/2023 17:07 | BD60: 20/10/2023 17:08 | BE60: 20/10/2023 17:10 | BF60: ANDERSON SCARPINO | BG60: TRUE | BH60: TRUE | BK60: FALSE
B61: 15292 | C61: COZAC | D61: 36053 | E61: 110378.82 | F61: 110378.82 | H61: Imóvel Urbano | I61: Sala comercial | J61: Ribeirão Preto | K61: SP | L61: Localizado | M61: Nível 1 | N61: Validação Avaliação Urbano | O61: NATHALIA DIAS | P61: Investigação | Q61: MATHEUS NAVARRO | R61: Concluída | S61: 20/04/2023 | T61: 28/03/2023 17:43 | U61: 06/04/2023 17:42 | V61: 14/04/2023 10:35 | W61: 19/04/2023 18:11 | X61: =W61*1 -> 45035.758 | Z61: Pesquisa de Bens | AA61: BANCO DO BRASIL (SGL_NAME) | AB61: Rua Visconde De Inhaúma | AC61: Centro | AD61: 78.9 | AE61: 64.4 | AG61: m2 | AH61: T1 | AI61: Remota | AJ61: Concluido | AL61: 05/04/2023 | AM61: 28/03/2023 17:43 | AN61: 29/03/2023 09:03 | AO61: 30/03/2023 17:13 | AP61: AGROFFICIO ATENDIMENTO | AQ61: Avaliado | AR61: Concluido | AS61: Normal | AT61: 10/04/2023 | AU61: 06/04/2023 17:42 | AV61: 03/04/2023 09:08 | AW61: 06/04/2023 17:42 | AX61: RAIZA GONÇALVES | AY61: Avaliado | AZ61: Concluido | BA61: Normal | BB61: 20/04/2023 | BC61: 06/04/2023 17:42 | BD61: 14/04/2023 10:35 | BE61: 19/04/2023 18:11 | BF61: MATHEUS NAVARRO | BH61: FALSE | BK61: FALSE
B62: 15292 | C62: COZAC | D62: 36053 | E62: 111515 | F62: 111515 | H62: Imóvel Urbano | I62: Sala Comercial | J62: Ribeirão Preto | K62: SP | L62: Localizado | M62: Nível 0 | N62: Validação Avaliação Urbano | O62: rd.avaliacao@enforcegroup.com.br | Q62: ANDRE MAGIORE | R62: Concluída | S62: 01/09/2022 | T62: 01/08/2022 09:31 | U62: 31/07/2022 21:00 | V62: 31/07/2022 21:00 | W62: 31/07/2022 21:00 | X62: =W62*1 -> 44773.875 | Y62: MIGRADO_ZOHO | Z62: Pesquisa de Bens | AA62: BANCO DO BRASIL (SGL_NAME) | AB62: Rua Visconde De Inhaúma, 490 | AC62: Centro | AD62: 0 | AE62: 64.4 | AF62: 0 | AG62: m2 | AH62: T1 | AI62: Remota | AJ62: Concluido | AL62: 01/08/2022 | AM62: 31/07/2022 21:00 | AN62: 31/07/2022 21:00 | AO62: 31/07/2022 21:00 | AP62: SIGLOCAL | AQ62: Avaliado | AS62: Normal | AT62: 01/09/2022 | AU62: 31/07/2022 21:00 | AV62: 31/07/2022 21:00 | AW62: 31/07/2022 21:00 | AX62: ANDRE MAGIORE | AY62: Avaliado | BB62: 01/09/2022 | BC62: 31/07/2022 21:00 | BD62: 31/07/2022 21:00 | BE62: 31/07/2022 21:00 | BF62: ANDERSON SCARPINO | BH62: FALSE | BK62: FALSE
B63: 15292 | C63: COZAC | D63: 36053 | E63: 179991 | F63: 122394 | H63: Imóvel Urbano | I63: Casa Residencial | J63: Ribeirão Preto | K63: SP | L63: Localizado | M63: Nível 1 | N63: Validação Avaliação Urbano | O63: rd.avaliacao@enforcegroup.com.br | Q63: JULIA JORGE | R63: Concluída | S63: 27/06/2022 | T63: 27/05/2022 11:54 | U63: 26/05/2022 21:00 | V63: 12/06/2022 21:00 | W63: 19/06/2022 21:00 | X63: =W63*1 -> 44731.875 | Y63: MIGRADO_ZOHO | Z63: Pesquisa de Bens | AA63: BANCO DO BRASIL (SGL_NAME) | AB63: Rua Victório Farnocchi, 165 | AC63: Quintino Facci Ii | AD63: 110 | AE63: 0 | AF63: 200 | AG63: m2 | AH63: T1 | AI63: Remota | AJ63: Concluido | AL63: 02/06/2022 | AM63: 26/05/2022 21:00 | AN63: 26/05/2022 21:00 | AO63: 01/06/2022 21:00 | AP63: HERGOM | AQ63: Avaliado | AS63: Réplica | AT63: 27/06/2022 | AU63: 26/05/2022 21:00 | AV63: 12/06/2022 21:00 | AW63: 19/06/2022 21:00 | AX63: JULIA JORGE | AY63: Avaliado | BB63: 27/06/2022 | BC63: 19/06/2022 21:00 | BD63: 12/06/2022 21:00 | BE63: 29/06/2022 21:00 | BF63: MARINA FAHL | BH63: FALSE | BK63: FALSE
B64: 15292 | C64: COZAC | D64: 48207 | E64: 3074000 | F64: 2460000 | H64: Imóvel Urbano | I64: Terreno urbano | J64: Ribeirão Preto | K64: SP | L64: Localizado | M64: Nível 3 | N64: Validação Avaliação Urbano | O64: IVO LAMAS | P64: Avaliação Urbana | Q64: ANDERSON SCARPINO | R64: Concluída | S64: 07/10/2025 | T64: 30/04/2025 18:07 | U64: 07/10/2025 17:42 | V64: 07/10/2025 17:43 | W64: 07/10/2025 17:44 | X64: =W64*1 -> 45937.739 | Z64: Prospecção | AA64: BANCO DO BRASIL (SGL_NAME) | AB64: Rua Aldo Focosi | AC64: Iguatemi | AF64: 3085.8 | AG64: m2 | AH64: T1 | AI64: Remota | AJ64: Concluido | AL64: 04/04/2023 | AM64: 28/03/2023 16:32 | AN64: 29/03/2023 09:04 | AO64: 04/04/2023 11:37 | AP64: SIGLOCAL ACESSO | AT64: 31/05/2025 | AU64: 07/10/2025 17:42 | AV64: 09/05/2025 10:33 | AW64: 16/05/2025 14:27 | AX64: Victor Libarino | BB64: 07/10/2025 | BC64: 07/10/2025 17:42 | BD64: 07/10/2025 17:43 | BE64: 07/10/2025 17:44 | BF64: ANDERSON SCARPINO | BH64: TRUE | BK64: FALSE
B65: 15292 | C65: COZAC | D65: 48207 | E65: 3167056 | F65: 2217000 | H65: Imóvel Urbano | I65: Terreno urbano | J65: Ribeirão Preto | K65: SP | L65: Localizado | M65: Nível 3 | N65: Validação Avaliação Urbano | O65: LUCAS ORTEGA | Q65: ANDERSON SCARPINO | R65: Concluída | S65: 20/09/2023 | T65: 13/06/2023 09:44 | U65: 20/09/2023 15:31 | V65: 20/09/2023 15:32 | W65: 20/09/2023 15:35 | X65: =W65*1 -> 45189.649 | Z65: Acordo | AA65: BANCO DO BRASIL (SGL_NAME) | AB65: Rua Aldo Focosi | AC65: Iguatemi | AF65: 3085.8 | AG65: m2 | AH65: T1 | AI65: Remota | AJ65: Concluido | AL65: 04/04/2023 | AM65: 28/03/2023 16:32 | AN65: 29/03/2023 09:04 | AO65: 04/04/2023 11:37 | AP65: SIGLOCAL ACESSO | AT65: 30/06/2023 | AU65: 20/09/2023 15:31 | AV65: 13/06/2023 10:57 | AW65: 28/06/2023 12:07 | AX65: AHEAD ARQUITETURA | BB65: 20/09/2023 | BC65: 20/09/2023 15:31 | BD65: 20/09/2023 15:32 | BE65: 20/09/2023 15:35 | BF65: ANDERSON SCARPINO | BH65: TRUE | BK65: FALSE
B66: 15292 | C66: COZAC | D66: 48207 | E66: 4842088.3 | F66: 3922091.5 | H66: Imóvel Urbano | I66: Terreno urbano | J66: Ribeirão Preto | K66: SP | L66: Localizado | M66: Nível 1 | N66: Validação Avaliação Urbano | O66: NATHALIA DIAS | P66: Investigação | Q66: MATHEUS NAVARRO | R66: Concluída | S66: 20/04/2023 | T66: 28/03/2023 16:32 | U66: 17/04/2023 17:24 | V66: 17/04/2023 17:38 | W66: 20/04/2023 11:11 | X66: =W66*1 -> 45036.466 | Z66: Pesquisa de Bens | AA66: BANCO DO BRASIL (SGL_NAME) | AB66: Rua Aldo Focosi | AC66: Iguatemi | AF66: 3085.8 | AG66: m2 | AH66: T1 | AI66: Remota | AJ66: Concluido | AL66: 04/04/2023 | AM66: 28/03/2023 16:32 | AN66: 29/03/2023 09:04 | AO66: 04/04/2023 11:37 | AP66: SIGLOCAL ACESSO | AQ66: Avaliado | AR66: Concluido | AS66: Normal | AT66: 18/04/2023 | AU66: 17/04/2023 17:24 | AV66: 06/04/2023 08:20 | AW66: 17/04/2023 17:24 | AX66: RAIZA GONÇALVES | AY66: Avaliado | AZ66: Concluido | BA66: Normal | BB66: 20/04/2023 | BC66: 17/04/2023 17:24 | BD66: 17/04/2023 17:38 | BE66: 20/04/2023 11:11 | BF66: MATHEUS NAVARRO | BH66: FALSE | BK66: FALSE
B67: 15292 | C67: COZAC | D67: 48207 | E67: 3760168 | F67: 3196142 | H67: Imóvel Urbano | I67: Terreno urbano | J67: Ribeirão Preto | K67: SP | L67: Localizado | M67: Nível 1 | N67: Validação Avaliação Urbano | O67: rd.avaliacao@enforcegroup.com.br | Q67: BRUNO ICARO | R67: Concluída | S67: 28/08/2022 | T67: 28/07/2022 13:45 | U67: 27/07/2022 21:00 | V67: 28/07/2022 21:00 | W67: 28/07/2022 21:00 | X67: =W67*1 -> 44770.875 | Y67: MIGRADO_ZOHO | Z67: Pesquisa de Bens | AA67: BANCO DO BRASIL (SGL_NAME) | AB67: Rua Aldo Focosi | AC67: Presidente Medici | AD67: 0 | AE67: 0 | AF67: 3085.8 | AG67: m2 | AH67: T1 | AI67: Remota | AJ67: Concluido | AL67: 28/07/2022 | AM67: 27/07/2022 21:00 | AN67: 27/07/2022 21:00 | AO67: 27/07/2022 21:00 | AP67: SIGLOCAL | AQ67: Avaliado | AS67: Complexa | AT67: 28/08/2022 | AU67: 27/07/2022 21:00 | AV67: 28/07/2022 21:00 | AW67: 28/07/2022 21:00 | AX67: BRUNO ICARO | AY67: Avaliado | BB67: 28/08/2022 | BC67: 28/07/2022 21:00 | BD67: 28/07/2022 21:00 | BE67: 31/07/2022 21:00 | BF67: BRUNA ALCANTARA | BH67: FALSE | BK67: FALSE
B68: 15292 | C68: COZAC | D68: 52218 | E68: 656000 | F68: 459000 | H68: Imóvel Urbano | I68: Casa Comercial | J68: Ribeirão Preto | K68: SP | L68: Localizado | M68: Nível 2 | N68: Validação Avaliação Urbano | O68: ANA CLARA | P68: Gestão BNDU | Q68: ANDERSON SCARPINO | R68: Concluída | S68: 17/07/2025 | T68: 05/06/2025 17:18 | U68: 17/07/2025 16:46 | V68: 17/07/2025 17:04 | W68: 17/07/2025 17:27 | X68: =W68*1 -> 45855.727 | Z68: Pesquisa de Bens | AA68: BANCO DO BRASIL (SGL_NAME) | AB68: Rua Altino Arantes | AC68: Jardim Sumaré | AD68: 331.05 | AF68: 336 | AG68: m2 | AH68: T1 | AI68: Remota | AJ68: Concluido | AL68: 05/04/2023 | AM68: 28/03/2023 18:13 | AN68: 29/03/2023 09:03 | AO68: 31/03/2023 15:44 | AP68: AGROFFICIO ATENDIMENTO | AT68: 18/07/2025 | AU68: 17/07/2025 16:46 | AV68: 17/07/2025 15:15 | AW68: 17/07/2025 16:46 | AX68: Victor Libarino | BB68: 17/07/2025 | BC68: 17/07/2025 16:46 | BD68: 17/07/2025 17:04 | BE68: 17/07/2025 17:27 | BF68: ANDERSON SCARPINO | BG68: TRUE | BH68: FALSE | BK68: FALSE
B69: 15292 | C69: COZAC | D69: 52218 | E69: 567000 | F69: 436000 | H69: Imóvel Urbano | I69: Casa Residencial | J69: Ribeirão Preto | K69: SP | L69: Localizado | M69: Nível 2 | N69: Validação Avaliação Urbano | O69: LUCAS ORTEGA | Q69: ANDERSON SCARPINO | R69: Concluída | S69: 20/10/2023 | T69: 13/06/2023 14:56 | U69: 20/10/2023 17:11 | V69: 20/10/2023 17:12 | W69: 20/10/2023 17:16 | X69: =W69*1 -> 45219.719 | Z69: Acordo | AA69: BANCO DO BRASIL (SGL_NAME) | AB69: Rua Altino Arantes | AC69: Jardim Sumaré | AD69: 180 | AF69: 336 | AG69: m2 | AH69: T1 | AI69: Remota | AJ69: Concluido | AL69: 05/04/2023 | AM69: 28/03/2023 18:13 | AN69: 29/03/2023 09:03 | AO69: 31/03/2023 15:44 | AP69: AGROFFICIO ATENDIMENTO | AT69: 10/07/2023 | AU69: 20/10/2023 17:11 | AV69: 10/07/2023 12:37 | AW69: 10/07/2023 15:05 | AX69: RAPHAEL PARENTE | BB69: 20/10/2023 | BC69: 20/10/2023 17:11 | BD69: 20/10/2023 17:12 | BE69: 20/10/2023 17:16 | BF69: ANDERSON SCARPINO | BG69: TRUE | BH69: TRUE | BK69: FALSE
B70: 15292 | C70: COZAC | D70: 52218 | E70: 638763.36 | F70: 459909.62 | H70: Imóvel Urbano | I70: Casa Residencial | J70: Ribeirão Preto | K70: SP | L70: Localizado | M70: Nível 1 | N70: Validação Avaliação Urbano | O70: NATHALIA DIAS | P70: Investigação | Q70: MATHEUS NAVARRO | R70: Concluída | S70: 20/04/2023 | T70: 28/03/2023 18:13 | U70: 06/04/2023 09:41 | V70: 14/04/2023 10:35 | W70: 19/04/2023 18:30 | X70: =W70*1 -> 45035.771 | Z70: Pesquisa de Bens | AA70: BANCO DO BRASIL (SGL_NAME) | AB70: Rua Altino Arantes | AC70: Jardim Sumaré | AD70: 180 | AF70: 336 | AG70: m2 | AH70: T1 | AI70: Remota | AJ70: Concluido | AL70: 05/04/2023 | AM70: 28/03/2023 18:13 | AN70: 29/03/2023 09:03 | AO70: 31/03/2023 15:44 | AP70: AGROFFICIO ATENDIMENTO | AQ70: Avaliado | AR70: Concluido | AS70: Réplica | AT70: 06/04/2023 | AU70: 06/04/2023 09:41 | AV70: 06/04/2023 09:22 | AW70: 06/04/2023 09:41 | AX70: RAIZA GONÇALVES | AY70: Avaliado | AZ70: Concluido | BA70: Réplica | BB70: 20/04/2023 | BC70: 06/04/2023 09:41 | BD70: 14/04/2023 10:35 | BE70: 19/04/2023 18:30 | BF70: MATHEUS NAVARRO | BG70: TRUE | BH70: FALSE | BK70: FALSE
B71: 15292 | C71: COZAC | D71: 52218 | E71: 950578 | F71: 693922 | H71: Imóvel Urbano | I71: Loja de rua | J71: Ribeirão Preto | K71: SP | L71: Localizado | M71: Nível 1 | N71: Validação Avaliação Urbano | O71: rd.avaliacao@enforcegroup.com.br | Q71: BRUNO ICARO | R71: Concluída | S71: 28/08/2022 | T71: 28/07/2022 14:49 | U71: 27/07/2022 21:00 | V71: 28/07/2022 21:00 | W71: 28/07/2022 21:00 | X71: =W71*1 -> 44770.875 | Y71: MIGRADO_ZOHO | Z71: Pesquisa de Bens | AA71: BANCO DO BRASIL (SGL_NAME) | AB71: Rua Altíno Arantes, 1478 | AC71: Jardim Sumaré | AD71: 200 | AE71: 0 | AF71: 336 | AG71: m2 | AH71: T1 | AI71: Remota | AJ71: Concluido | AL71: 28/07/2022 | AM71: 27/07/2022 21:00 | AN71: 27/07/2022 21:00 | AO71: 27/07/2022 21:00 | AP71: SIGLOCAL | AQ71: Avaliado | AS71: Normal | AT71: 28/08/2022 | AU71: 27/07/2022 21:00 | AV71: 28/07/2022 21:00 | AW71: 28/07/2022 21:00 | AX71: BRUNO ICARO | AY71: Avaliado | BB71: 28/08/2022 | BC71: 28/07/2022 21:00 | BD71: 28/07/2022 21:00 | BE71: 28/07/2022 21:00 | BF71: MATHEUS NAVARRO | BH71: FALSE | BK71: FALSE
B72: 15292 | C72: COZAC | D72: 52218 | E72: 475513 | F72: 342369 | H72: Imóvel Urbano | I72: Prédio Comercial | J72: Ribeirão Preto | K72: SP | L72: Localizado | M72: Nível 1 | N72: Validação Avaliação Urbano | O72: rd.avaliacao@enforcegroup.com.br | Q72: JULIA JORGE | R72: Concluída | S72: 27/06/2022 | T72: 27/05/2022 08:53 | U72: 26/05/2022 21:00 | V72: 12/06/2022 21:00 | W72: 15/06/2022 21:00 | X72: =W72*1 -> 44727.875 | Y72: MIGRADO_ZOHO | Z72: Pesquisa de Bens | AA72: BANCO DO BRASIL (SGL_NAME) | AB72: Rua Altino Arantes, 1478 | AC72: Jardim Sumaré | AD72: 180 | AE72: 0 | AF72: 336 | AG72: m2 | AH72: T1 | AI72: Remota | AJ72: Concluido | AL72: 02/06/2022 | AM72: 26/05/2022 21:00 | AN72: 26/05/2022 21:00 | AO72: 01/06/2022 21:00 | AP72: HERGOM | AQ72: Avaliado | AS72: Normal | AT72: 27/06/2022 | AU72: 26/05/2022 21:00 | AV72: 12/06/2022 21:00 | AW72: 15/06/2022 21:00 | AX72: JULIA JORGE | AY72: Avaliado | BB72: 27/06/2022 | BC72: 15/06/2022 21:00 | BD72: 12/06/2022 21:00 | BE72: 29/06/2022 21:00 | BF72: MARINA FAHL | BH72: FALSE | BK72: FALSE
B73: 15292 | C73: COZAC | D73: 53194 | E73: 414000 | F73: 290000 | H73: Imóvel Urbano | I73: Terreno urbano | J73: Ribeirão Preto | K73: SP | L73: Localizado | M73: Nível 2 | N73: Validação Avaliação Urbano | O73: FERNANDA GOMES | P73: Gestão BNDU | Q73: ANDERSON SCARPINO | R73: Concluída | S73: 07/10/2025 | T73: 19/09/2025 10:30 | U73: 06/10/2025 17:48 | V73: 07/10/2025 09:12 | W73: 07/10/2025 10:18 | X73: =W73*1 -> 45937.429 | Z73: Pesquisa de Bens | AA73: BANCO DO BRASIL (SGL_NAME) | AB73: Rua Marino Paterlini | AC73: Presidente Médici | AF73: 390 | AG73: m2 | AH73: T1 | AI73: Remota | AJ73: Concluido | AL73: 04/04/2023 | AM73: 28/03/2023 17:10 | AN73: 29/03/2023 09:29 | AO73: 04/04/2023 11:29 | AP73: SIGLOCAL ACESSO | AT73: 08/10/2025 | AU73: 06/10/2025 17:48 | AV73: 24/09/2025 11:30 | AW73: 06/10/2025 17:48 | AX73: Victor Libarino | BB73: 07/10/2025 | BC73: 06/10/2025 17:48 | BD73: 07/10/2025 09:12 | BE73: 07/10/2025 10:18 | BF73: ANDERSON SCARPINO | BH73: FALSE | BK73: FALSE
B74: 15292 | C74: COZAC | D74: 53194 | E74: 282000 | F74: 222000 | H74: Imóvel Urbano | I74: Terreno urbano | J74: Ribeirão Preto | K74: SP | L74: Localizado | M74: Nível 2 | N74: Validação Avaliação Urbano | O74: ANDERSON SCARPINO | P74: Avaliação Urbana | Q74: ANDERSON SCARPINO | R74: Concluída | S74: 20/10/2023 | T74: 21/09/2023 16:07 | U74: 20/10/2023 17:20 | V74: 20/10/2023 17:27 | W74: 20/10/2023 17:38 | X74: =W74*1 -> 45219.735 | Z74: Acordo | AA74: BANCO DO BRASIL (SGL_NAME) | AB74: Rua Marino Paterlini | AC74: Presidente Médici | AF74: 390 | AG74: m2 | AH74: T1 | AI74: Remota | AJ74: Concluido | AL74: 04/04/2023 | AM74: 28/03/2023 17:10 | AN74: 29/03/2023 09:29 | AO74: 04/04/2023 11:29 | AP74: SIGLOCAL ACESSO | AT74: 26/09/2023 | AU74: 20/10/2023 17:20 | AV74: 21/09/2023 16:08 | AW74: 26/09/2023 18:16 | AX74: RAPHAEL PARENTE | BB74: 20/10/2023 | BC74: 20/10/2023 17:20 | BD74: 20/10/2023 17:27 | BE74: 20/10/2023 17:38 | BF74: ANDERSON SCARPINO | BH74: TRUE | BK74: FALSE
B75: 15292 | C75: COZAC | D75: 53194 | E75: 627000 | F75: 445000 | H75: Imóvel Urbano | I75: Casa Comercial | J75: Ribeirão Preto | K75: SP | L75: Parcialmente Localizado | M75: Nível 3 | N75: Validação Avaliação Urbano | O75: THIAGO MACHADO | P75: GESTÃO PORTFÓLIO | Q75: ANDERSON SCARPINO | R75: Concluída | S75: 10/07/2023 | T75: 22/06/2023 18:39 | U75: 10/07/2023 15:11 | V75: 10/07/2023 15:19 | W75: 10/07/2023 15:22 | X75: =W75*1 -> 45117.64 | Z75: Acordo | AA75: BANCO DO BRASIL (SGL_NAME) | AB75: Rua 7 de Setembro, 1364 | AC75: Centro | AD75: 225.56 | AF75: 523.74 | AG75: m2 | AH75: T1 | AI75: Remota | AJ75: Concluido | AL75: 02/06/2022 | AM75: 20/10/2022 21:16 | AN75: 26/05/2022 21:00 | AO75: 01/06/2022 21:00 | AP75: HERGOM | AT75: 10/07/2023 | AU75: 10/07/2023 15:11 | AV75: 10/07/2023 12:38 | AW75: 10/07/2023 15:11 | AX75: RAPHAEL PARENTE | BB75: 10/07/2023 | BC75: 10/07/2023 15:11 | BD75: 10/07/2023 15:19 | BE75: 10/07/2023 15:22 | BF75: ANDERSON SCARPINO | BG75: TRUE | BH75: FALSE | BK75: FALSE
B76: 15292 | C76: COZAC | D76: 53194 | E76: 217696.1 | F76: 176333.84 | H76: Imóvel Urbano | I76: Terreno urbano | J76: Ribeirão Preto | K76: SP | L76: Localizado | M76: Nível 1 | N76: Validação Avaliação Urbano | O76: NATHALIA DIAS | P76: Investigação | Q76: MATHEUS NAVARRO | R76: Concluída | S76: 20/04/2023 | T76: 28/03/2023 17:09 | U76: 17/04/2023 14:51 | V76: 17/04/2023 16:04 | W76: 20/04/2023 11:21 | X76: =W76*1 -> 45036.473 | Z76: Pesquisa de Bens | AA76: BANCO DO BRASIL (SGL_NAME) | AB76: Rua Marino Paterlini | AC76: Presidente Médici | AF76: 390 | AG76: m2 | AH76: T1 | AI76: Remota | AJ76: Concluido | AL76: 04/04/2023 | AM76: 28/03/2023 17:10 | AN76: 29/03/2023 09:29 | AO76: 04/04/2023 11:29 | AP76: SIGLOCAL ACESSO | AQ76: Avaliado | AR76: Concluido | AS76: Normal | AT76: 18/04/2023 | AU76: 17/04/2023 14:51 | AV76: 06/04/2023 08:21 | AW76: 17/04/2023 14:51 | AX76: RAIZA GONÇALVES | AY76: Avaliado | AZ76: Concluido | BA76: Normal | BB76: 20/04/2023 | BC76: 17/04/2023 14:51 | BD76: 17/04/2023 16:04 | BE76: 20/04/2023 11:21 | BF76: MATHEUS NAVARRO | BH76: FALSE | BK76: FALSE
B77: 15292 | C77: COZAC | D77: 53194 | E77: 219948 | F77: 175958 | H77: Imóvel Urbano | I77: Terreno urbano | J77: Ribeirão Preto | K77: SP | L77: Localizado | M77: Nível 0 | N77: Validação Avaliação Urbano | O77: rd.avaliacao@enforcegroup.com.br | Q77: ANDRE MAGIORE | R77: Concluída | S77: 28/08/2022 | T77: 28/07/2022 14:49 | U77: 27/07/2022 21:00 | V77: 31/07/2022 21:00 | W77: 31/07/2022 21:00 | X77: =W77*1 -> 44773.875 | Y77: MIGRADO_ZOHO | Z77: Pesquisa de Bens | AA77: BANCO DO BRASIL (SGL_NAME) | AB77: Rua Marino Paterlini | AC77: Presidente Medici | AD77: 0 | AE77: 0 | AF77: 390 | AG77: m2 | AH77: T1 | AI77: Remota | AJ77: Concluido | AL77: 28/07/2022 | AM77: 27/07/2022 21:00 | AN77: 27/07/2022 21:00 | AO77: 27/07/2022 21:00 | AP77: SIGLOCAL | AQ77: Avaliado | AS77: Normal | AT77: 28/08/2022 | AU77: 27/07/2022 21:00 | AV77: 31/07/2022 21:00 | AW77: 31/07/2022 21:00 | AX77: ANDRE MAGIORE | AY77: Avaliado | BB77: 28/08/2022 | BC77: 31/07/2022 21:00 | BD77: 31/07/2022 21:00 | BE77: 31/07/2022 21:00 | BH77: FALSE | BK77: FALSE
B78: 15292 | C78: COZAC | D78: 53194 | E78: 581714 | F78: 436285 | H78: Imóvel Urbano | I78: Prédio Comercial | J78: Ribeirão Preto | K78: SP | L78: Parcialmente Localizado | M78: Nível 0 | N78: Validação Avaliação Urbano | O78: rd.avaliacao@enforcegroup.com.br | Q78: JULIA JORGE | R78: Concluída | S78: 27/06/2022 | T78: 27/05/2022 09:02 | U78: 26/05/2022 21:00 | V78: 05/06/2022 21:00 | W78: 07/06/2022 21:00 | X78: =W78*1 -> 44719.875 | Y78: MIGRADO_ZOHO | Z78: Pesquisa de Bens | AA78: BANCO DO BRASIL (SGL_NAME) | AB78: Rua 7 de Setembro, 1364 | AC78: Centro | AD78: 225.56 | AE78: 0 | AF78: 523.74 | AG78: m2 | AH78: T1 | AI78: Remota | AJ78: Concluido | AL78: 02/06/2022 | AM78: 26/05/2022 21:00 | AN78: 26/05/2022 21:00 | AO78: 01/06/2022 21:00 | AP78: HERGOM | AQ78: Avaliado | AS78: Normal | AT78: 27/06/2022 | AU78: 26/05/2022 21:00 | AV78: 05/06/2022 21:00 | AW78: 07/06/2022 21:00 | AX78: JULIA JORGE | AY78: Avaliado | BB78: 27/06/2022 | BC78: 07/06/2022 21:00 | BD78: 05/06/2022 21:00 | BE78: 29/06/2022 21:00 | BF78: MARINA FAHL | BH78: FALSE | BK78: FALSE
B79: 15292 | C79: COZAC | D79: 59250 | E79: 232000 | F79: 165000 | H79: Imóvel Urbano | I79: Apartamento Padrão | J79: Ribeirão Preto | K79: SP | L79: Localizado | M79: Nível 2 | N79: Validação Avaliação Urbano | O79: ANA CLARA | P79: Gestão BNDU | Q79: ANDERSON SCARPINO | R79: Concluída | S79: 19/11/2025 | T79: 12/11/2025 11:33 | U79: 19/11/2025 10:03 | V79: 19/11/2025 10:07 | W79: 19/11/2025 10:09 | X79: =W79*1 -> 45980.423 | Z79: Pesquisa de Bens | AA79: BANCO DO BRASIL (SGL_NAME) | AB79: Rua Sacadura Cabral | AC79: Campos Eliseos | AD79: 142.19 | AE79: 97.83 | AG79: m2 | AH79: T1 | AI79: Remota | AJ79: Concluido | AL79: 05/04/2023 | AM79: 29/03/2023 11:01 | AN79: 29/03/2023 11:22 | AO79: 05/04/2023 14:39 | AP79: AGROFFICIO ATENDIMENTO | AT79: 21/11/2025 | AU79: 19/11/2025 10:03 | AV79: 12/11/2025 15:21 | AW79: 19/11/2025 10:03 | AX79: Victor Libarino (N2/N3) | BB79: 19/11/2025 | BC79: 19/11/2025 10:03 | BD79: 19/11/2025 10:07 | BE79: 19/11/2025 10:09 | BF79: ANDERSON SCARPINO | BH79: FALSE | BK79: FALSE
B80: 15292 | C80: COZAC | D80: 59250 | E80: 203000 | F80: 160000 | H80: Imóvel Urbano | I80: Apartamento Padrão | J80: Ribeirão Preto | K80: SP | L80: Localizado | M80: Nível 2 | N80: Validação Avaliação Urbano | O80: THIAGO MACHADO | P80: GESTÃO PORTFÓLIO | Q80: ANDERSON SCARPINO | R80: Concluída | S80: 20/10/2023 | T80: 06/06/2023 16:18 | U80: 20/10/2023 16:07 | V80: 20/10/2023 16:08 | W80: 20/10/2023 16:10 | X80: =W80*1 -> 45219.674 | Z80: Acordo | AA80: BANCO DO BRASIL (SGL_NAME) | AB80: Rua Sacadura Cabral | AC80: Campos Eliseos | AD80: 142.19 | AE80: 97.83 | AG80: m2 | AH80: T1 | AI80: Remota | AJ80: Concluido | AL80: 05/04/2023 | AM80: 29/03/2023 11:01 | AN80: 29/03/2023 11:22 | AO80: 05/04/2023 14:39 | AP80: AGROFFICIO ATENDIMENTO | AT80: 20/06/2023 | AU80: 20/10/2023 16:07 | AV80: 12/06/2023 17:12 | AW80: 29/06/2023 11:44 | AX80: RAPHAEL PARENTE | BB80: 20/10/2023 | BC80: 20/10/2023 16:07 | BD80: 20/10/2023 16:08 | BE80: 20/10/2023 16:10 | BF80: ANDERSON SCARPINO | BH80: TRUE | BK80: FALSE
B81: 15292 | C81: COZAC | D81: 59250 | E81: 253361.73 | F81: 182420.45 | H81: Imóvel Urbano | I81: Apartamento Padrão | J81: Ribeirão Preto | K81: SP | L81: Localizado | M81: Nível 1 | N81: Validação Avaliação Urbano | O81: NATHALIA DIAS | P81: Investigação | Q81: MATHEUS NAVARRO | R81: Concluída | S81: 20/04/2023 | T81: 29/03/2023 11:01 | U81: 17/04/2023 10:02 | V81: 17/04/2023 16:04 | W81: 20/04/2023 09:53 | X81: =W81*1 -> 45036.412 | Z81: Pesquisa de Bens | AA81: BANCO DO BRASIL (SGL_NAME) | AB81: Rua Sacadura Cabral | AC81: Campos Eliseos | AD81: 142.19 | AE81: 97.83 | AG81: m2 | AH81: T1 | AI81: Remota | AJ81: Concluido | AL81: 05/04/2023 | AM81: 29/03/2023 11:01 | AN81: 29/03/2023 11:22 | AO81: 05/04/2023 14:39 | AP81: AGROFFICIO ATENDIMENTO | AQ81: Avaliado | AR81: Concluido | AS81: Réplica | AT81: 18/04/2023 | AU81: 17/04/2023 10:02 | AV81: 06/04/2023 08:21 | AW81: 17/04/2023 10:02 | AX81: RAIZA GONÇALVES | AY81: Avaliado | AZ81: Concluido | BA81: Réplica | BB81: 20/04/2023 | BC81: 17/04/2023 10:02 | BD81: 17/04/2023 16:04 | BE81: 20/04/2023 09:53 | BF81: MATHEUS NAVARRO | BH81: FALSE | BK81: FALSE
B82: 15292 | C82: COZAC | D82: 59250 | E82: 322806 | F82: 242104 | H82: Imóvel Urbano | I82: Apartamento Padrão | J82: Ribeirão Preto | K82: SP | L82: Localizado | M82: Nível 0 | N82: Validação Avaliação Urbano | O82: rd.avaliacao@enforcegroup.com.br | Q82: MATHEUS NAVARRO | R82: Concluída | S82: 01/09/2022 | T82: 01/08/2022 10:01 | U82: 31/07/2022 21:00 | V82: 31/07/2022 21:00 | W82: 31/07/2022 21:00 | X82: =W82*1 -> 44773.875 | Y82: MIGRADO_ZOHO | Z82: Pesquisa de Bens | AA82: BANCO DO BRASIL (SGL_NAME) | AB82: Rua Sacadura Cabral, 39 | AC82: Vila Tamandaré | AD82: 0 | AE82: 97.82 | AF82: 0 | AG82: m2 | AH82: T1 | AI82: Remota | AJ82: Concluido | AL82: 01/08/2022 | AM82: 31/07/2022 21:00 | AN82: 31/07/2022 21:00 | AO82: 31/07/2022 21:00 | AP82: SIGLOCAL | AQ82: Avaliado | AT82: 01/09/2022 | AU82: 31/07/2022 21:00 | AV82: 31/07/2022 21:00 | AW82: 31/07/2022 21:00 | AX82: MATHEUS NAVARRO | AY82: Avaliado | BB82: 01/09/2022 | BC82: 31/07/2022 21:00 | BD82: 31/07/2022 21:00 | BE82: 31/07/2022 21:00 | BF82: MATHEUS NAVARRO | BH82: FALSE | BK82: FALSE
B83: 15292 | C83: COZAC | D83: 59250 | H83: Imóvel Urbano | I83: Terreno urbano | J83: Ribeirão Preto | K83: SP | L83: Não Localizado | M83: Nível 1 | N83: Validação Avaliação Urbano | O83: rd.avaliacao@enforcegroup.com.br | R83: Concluída | S83: 21/07/2022 | T83: 21/06/2022 12:13 | U83: 20/06/2022 21:00 | W83: 27/07/2022 21:00 | X83: =W83*1 -> 44769.875 | Y83: MIGRADO_ZOHO | Z83: Pesquisa de Bens | AA83: BANCO DO BRASIL (SGL_NAME) | AB83: N/A | AC83: Jardim Clicia | AF83: 250 | AG83: m2 | AH83: T1 | AI83: Remota | AJ83: Matrícula encerrada | AL83: 23/06/2022 | AM83: 20/06/2022 21:00 | AN83: 20/06/2022 21:00 | AO83: 23/06/2022 21:00 | AP83: HERGOM | AQ83: Avaliado | AT83: 21/07/2022 | AU83: 20/06/2022 21:00 | AW83: 27/07/2022 21:00 | AY83: Avaliado | BB83: 21/07/2022 | BC83: 27/07/2022 21:00 | BE83: 27/07/2022 21:00 | BH83: FALSE | BK83: FALSE
B84: 15292 | C84: COZAC | D84: 59251 | E84: 199000 | F84: 142000 | H84: Imóvel Urbano | I84: Apartamento Padrão | J84: Ribeirão Preto | K84: SP | L84: Localizado | M84: Nível 2 | N84: Validação Avaliação Urbano | O84: ANA CLARA | P84: Gestão BNDU | Q84: ANDERSON SCARPINO | R84: Concluída | S84: 10/07/2025 | T84: 08/07/2025 15:44 | U84: 10/07/2025 01:05 | V84: 10/07/2025 09:33 | W84: 10/07/2025 10:57 | X84: =W84*1 -> 45848.456 | Z84: Pesquisa de Bens | AA84: BANCO DO BRASIL (SGL_NAME) | AB84: Rua Sacadura Cabral | AC84: Campos Eliseos | AD84: 107.09 | AE84: 73.68 | AG84: m2 | AH84: T1 | AI84: Remota | AJ84: Concluido | AL84: 05/04/2023 | AM84: 28/03/2023 17:02 | AN84: 29/03/2023 09:03 | AO84: 05/04/2023 14:40 | AP84: AGROFFICIO ATENDIMENTO | AT84: 09/07/2025 | AU84: 10/07/2025 01:05 | AV84: 08/07/2025 15:51 | AW84: 10/07/2025 01:05 | AX84: Victor Libarino | BB84: 10/07/2025 | BC84: 10/07/2025 01:05 | BD84: 10/07/2025 09:33 | BE84: 10/07/2025 10:57 | BF84: ANDERSON SCARPINO | BH84: FALSE | BK84: FALSE
B85: 15292 | C85: COZAC | D85: 59251 | E85: 294000 | F85: 206000 | H85: Imóvel Urbano | I85: Casa Residencial | J85: Ribeirão Preto | K85: SP | L85: Localizado | M85: Nível 2 | N85: Validação Avaliação Urbano | O85: ANA CLARA | P85: Gestão BNDU | Q85: ANDERSON SCARPINO | R85: Concluída | S85: 08/07/2025 | T85: 05/06/2025 17:47 | U85: 08/07/2025 10:07 | V85: 08/07/2025 14:38 | W85: 08/07/2025 15:15 | X85: =W85*1 -> 45846.635 | Z85: Pesquisa de Bens | AA85: BANCO DO BRASIL (SGL_NAME) | AB85: Rua Piauí, 744 | AC85: Ipiranga | AD85: 120 | AF85: 192 | AG85: m2 | AH85: T1 | AI85: Remota | AJ85: Concluido | AL85: 02/06/2022 | AM85: 25/10/2022 11:57 | AN85: 26/05/2022 21:00 | AO85: 01/06/2022 21:00 | AP85: HERGOM | AT85: 31/07/2025 | AU85: 08/07/2025 10:07 | AV85: 01/07/2025 11:55 | AW85: 08/07/2025 10:07 | AX85: Victor Libarino | BB85: 08/07/2025 | BC85: 08/07/2025 10:07 | BD85: 08/07/2025 14:38 | BE85: 08/07/2025 15:15 | BF85: ANDERSON SCARPINO | BH85: FALSE | BK85: FALSE
B86: 15292 | C86: COZAC | D86: 59251 | E86: 170000 | F86: 137000 | H86: Imóvel Urbano | I86: Apartamento Padrão | J86: Ribeirão Preto | K86: SP | L86: Localizado | M86: Nível 2 | N86: Validação Avaliação Urbano | O86: THIAGO MACHADO | P86: GESTÃO PORTFÓLIO | Q86: ANDERSON SCARPINO | R86: Concluída | S86: 20/10/2023 | T86: 06/06/2023 16:39 | U86: 20/10/2023 17:28 | V86: 20/10/2023 17:28 | W86: 20/10/2023 17:31 | X86: =W86*1 -> 45219.73 | Z86: Acordo | AA86: BANCO DO BRASIL (SGL_NAME) | AB86: Rua Sacadura Cabral | AC86: Campos Eliseos | AD86: 107.09 | AE86: 73.68 | AG86: m2 | AH86: T1 | AI86: Remota | AJ86: Concluido | AL86: 05/04/2023 | AM86: 28/03/2023 17:02 | AN86: 29/03/2023 09:03 | AO86: 05/04/2023 14:40 | AP86: AGROFFICIO ATENDIMENTO | AT86: 20/06/2023 | AU86: 20/10/2023 17:28 | AV86: 12/06/2023 17:11 | AW86: 29/06/2023 12:01 | AX86: RAPHAEL PARENTE | BB86: 20/10/2023 | BC86: 20/10/2023 17:28 | BD86: 20/10/2023 17:28 | BE86: 20/10/2023 17:31 | BF86: ANDERSON SCARPINO | BH86: TRUE | BK86: FALSE
B87: 15292 | C87: COZAC | D87: 59251 | E87: 196331.45 | F87: 141358.65 | H87: Imóvel Urbano | I87: Apartamento Padrão | J87: Ribeirão Preto | K87: SP | L87: Localizado | M87: Nível 1 | N87: Validação Avaliação Urbano | O87: NATHALIA DIAS | P87: Investigação | Q87: MATHEUS NAVARRO | R87: Concluída | S87: 20/04/2023 | T87: 28/03/2023 17:02 | U87: 17/04/2023 10:03 | V87: 17/04/2023 16:04 | W87: 20/04/2023 09:54 | X87: =W87*1 -> 45036.412 | Z87: Pesquisa de Bens | AA87: BANCO DO BRASIL (SGL_NAME) | AB87: Rua Sacadura Cabral | AC87: Campos Eliseos | AD87: 107.09 | AE87: 73.68 | AG87: m2 | AH87: T1 | AI87: Remota | AJ87: Concluido | AL87: 05/04/2023 | AM87: 28/03/2023 17:02 | AN87: 29/03/2023 09:03 | AO87: 05/04/2023 14:40 | AP87: AGROFFICIO ATENDIMENTO | AQ87: Avaliado | AR87: Concluido | AS87: Réplica | AT87: 18/04/2023 | AU87: 17/04/2023 10:03 | AV87: 06/04/2023 08:21 | AW87: 17/04/2023 10:03 | AX87: RAIZA GONÇALVES | AY87: Avaliado | AZ87: Concluido | BA87: Réplica | BB87: 20/04/2023 | BC87: 17/04/2023 10:03 | BD87: 17/04/2023 16:04 | BE87: 20/04/2023 09:54 | BF87: MATHEUS NAVARRO | BH87: FALSE | BK87: FALSE
B88: 15292 | C88: COZAC | D88: 59251 | E88: 243144 | F88: 194515 | H88: Imóvel Urbano | I88: Apartamento Padrão | J88: Ribeirão Preto | K88: SP | L88: Localizado | M88: Nível 0 | N88: Validação Avaliação Urbano | O88: rd.avaliacao@enforcegroup.com.br | Q88: MATHEUS NAVARRO | R88: Concluída | S88: 28/08/2022 | T88: 28/07/2022 14:25 | U88: 27/07/2022 21:00 | V88: 28/07/2022 21:00 | W88: 28/07/2022 21:00 | X88: =W88*1 -> 44770.875 | Y88: MIGRADO_ZOHO | Z88: Pesquisa de Bens | AA88: BANCO DO BRASIL (SGL_NAME) | AB88: Rua Sacadura Cabral, 39 | AC88: Vila Tamandare | AD88: 0 | AE88: 73.68 | AF88: 0 | AG88: m2 | AH88: T1 | AI88: Remota | AJ88: Concluido | AL88: 28/07/2022 | AM88: 27/07/2022 21:00 | AN88: 27/07/2022 21:00 | AO88: 27/07/2022 21:00 | AP88: SIGLOCAL | AQ88: Avaliado | AT88: 28/08/2022 | AU88: 27/07/2022 21:00 | AV88: 28/07/2022 21:00 | AW88: 28/07/2022 21:00 | AX88: MATHEUS NAVARRO | AY88: Avaliado | BB88: 28/08/2022 | BC88: 28/07/2022 21:00 | BD88: 28/07/2022 21:00 | BE88: 28/07/2022 21:00 | BF88: MATHEUS NAVARRO | BH88: FALSE | BK88: FALSE
B89: 15292 | C89: COZAC | D89: 59251 | E89: 314340 | F89: 226325 | H89: Imóvel Urbano | I89: Casa Residencial | J89: Ribeirão Preto | K89: SP | L89: Localizado | M89: Nível 1 | N89: Validação Avaliação Urbano | O89: rd.avaliacao@enforcegroup.com.br | Q89: JULIA JORGE | R89: Concluída | S89: 27/06/2022 | T89: 27/05/2022 08:51 | U89: 26/05/2022 21:00 | V89: 12/06/2022 21:00 | W89: 16/06/2022 21:00 | X89: =W89*1 -> 44728.875 | Y89: MIGRADO_ZOHO | Z89: Pesquisa de Bens | AA89: BANCO DO BRASIL (SGL_NAME) | AB89: Rua Piauí, 744 | AC89: Ipiranga | AD89: 120 | AE89: 0 | AF89: 192 | AG89: m2 | AH89: T1 | AI89: Remota | AJ89: Concluido | AL89: 02/06/2022 | AM89: 26/05/2022 21:00 | AN89: 26/05/2022 21:00 | AO89: 01/06/2022 21:00 | AP89: HERGOM | AQ89: Avaliado | AS89: Normal | AT89: 27/06/2022 | AU89: 26/05/2022 21:00 | AV89: 12/06/2022 21:00 | AW89: 16/06/2022 21:00 | AX89: JULIA JORGE | AY89: Avaliado | BB89: 27/06/2022 | BC89: 16/06/2022 21:00 | BD89: 12/06/2022 21:00 | BE89: 29/06/2022 21:00 | BF89: MARINA FAHL | BH89: FALSE | BK89: FALSE
B90: 15292 | C90: COZAC | D90: 59252 | E90: 200000 | F90: 142000 | H90: Imóvel Urbano | I90: Apartamento Padrão | J90: Ribeirão Preto | K90: SP | L90: Localizado | M90: Nível 2 | N90: Validação Avaliação Urbano | O90: ANA CLARA | P90: Gestão BNDU | Q90: ANDERSON SCARPINO | R90: Concluída | S90: 07/07/2025 | T90: 05/06/2025 17:46 | U90: 07/07/2025 15:49 | V90: 07/07/2025 16:18 | W90: 08/07/2025 14:36 | X90: =W90*1 -> 45846.608 | Z90: Pesquisa de Bens | AA90: BANCO DO BRASIL (SGL_NAME) | AB90: Rua Sacadura Cabral | AC90: Campos Eliseos | AD90: 107.4 | AE90: 73.89 | AG90: m2 | AH90: T1 | AI90: Remota | AJ90: Concluido | AL90: 05/04/2023 | AM90: 28/03/2023 17:00 | AN90: 29/03/2023 09:03 | AO90: 05/04/2023 14:43 | AP90: AGROFFICIO ATENDIMENTO | AT90: 31/07/2025 | AU90: 07/07/2025 15:49 | AV90: 01/07/2025 11:54 | AW90: 07/07/2025 15:49 | AX90: Victor Libarino | BB90: 07/07/2025 | BC90: 07/07/2025 15:49 | BD90: 07/07/2025 16:18 | BE90: 08/07/2025 14:36 | BF90: ANDERSON SCARPINO | BH90: FALSE | BK90: FALSE
B91: 15292 | C91: COZAC | D91: 59252 | E91: 170000 | F91: 137000 | H91: Imóvel Urbano | I91: Apartamento Padrão | J91: Ribeirão Preto | K91: SP | L91: Localizado | M91: Nível 2 | N91: Validação Avaliação Urbano | O91: THIAGO MACHADO | P91: GESTÃO PORTFÓLIO | Q91: ANDERSON SCARPINO | R91: Concluída | S91: 20/10/2023 | T91: 06/06/2023 16:39 | U91: 20/10/2023 17:32 | V91: 20/10/2023 17:32 | W91: 20/10/2023 17:34 | X91: =W91*1 -> 45219.732 | Z91: Acordo | AA91: BANCO DO BRASIL (SGL_NAME) | AB91: Rua Sacadura Cabral | AC91: Campos Eliseos | AD91: 107.4 | AE91: 73.89 | AG91: m2 | AH91: T1 | AI91: Remota | AJ91: Concluido | AL91: 05/04/2023 | AM91: 28/03/2023 17:00 | AN91: 29/03/2023 09:03 | AO91: 05/04/2023 14:43 | AP91: AGROFFICIO ATENDIMENTO | AT91: 20/06/2023 | AU91: 20/10/2023 17:32 | AV91: 12/06/2023 17:12 | AW91: 29/06/2023 16:29 | AX91: RAPHAEL PARENTE | BB91: 20/10/2023 | BC91: 20/10/2023 17:32 | BD91: 20/10/2023 17:32 | BE91: 20/10/2023 17:34 | BF91: ANDERSON SCARPINO | BH91: TRUE | BK91: FALSE
B92: 15292 | C92: COZAC | D92: 59252 | E92: 196812.62 | F92: 141705.09 | H92: Imóvel Urbano | I92: Apartamento Padrão | J92: Ribeirão Preto | K92: SP | L92: Localizado | M92: Nível 1 | N92: Validação Avaliação Urbano | O92: NATHALIA DIAS | P92: Investigação | Q92: MATHEUS NAVARRO | R92: Concluída | S92: 20/04/2023 | T92: 28/03/2023 17:00 | U92: 17/04/2023 09:59 | V92: 17/04/2023 16:04 | W92: 20/04/2023 09:54 | X92: =W92*1 -> 45036.412 | Z92: Pesquisa de Bens | AA92: BANCO DO BRASIL (SGL_NAME) | AB92: Rua Sacadura Cabral | AC92: Campos Eliseos | AD92: 107.4 | AE92: 73.89 | AG92: m2 | AH92: T1 | AI92: Remota | AJ92: Concluido | AL92: 05/04/2023 | AM92: 28/03/2023 17:00 | AN92: 29/03/2023 09:03 | AO92: 05/04/2023 14:43 | AP92: AGROFFICIO ATENDIMENTO | AQ92: Avaliado | AR92: Concluido | AS92: Normal | AT92: 18/04/2023 | AU92: 17/04/2023 09:59 | AV92: 06/04/2023 08:21 | AW92: 17/04/2023 09:59 | AX92: RAIZA GONÇALVES | AY92: Avaliado | AZ92: Concluido | BA92: Réplica | BB92: 20/04/2023 | BC92: 17/04/2023 09:59 | BD92: 17/04/2023 16:04 | BE92: 20/04/2023 09:54 | BF92: MATHEUS NAVARRO | BH92: FALSE | BK92: FALSE
B93: 15292 | C93: COZAC | D93: 59252 | E93: 163931 | F93: 131145 | H93: Imóvel Urbano | I93: Casa Residencial | J93: Ribeirão Preto | K93: SP | L93: Localizado | M93: Nível 0 | N93: Validação Avaliação Urbano | O93: rd.avaliacao@enforcegroup.com.br | Q93: MATHEUS NAVARRO | R93: Concluída | S93: 28/08/2022 | T93: 28/07/2022 14:23 | U93: 27/07/2022 21:00 | V93: 27/07/2022 21:00 | W93: 27/07/2022 21:00 | X93: =W93*1 -> 44769.875 | Y93: MIGRADO_ZOHO | Z93: Pesquisa de Bens | AA93: BANCO DO BRASIL (SGL_NAME) | AB93: Travessa Mesquita, 28 | AC93: Vila Virginia | AD93: 70 | AE93: 0 | AF93: 169.95 | AG93: m2 | AH93: T1 | AI93: Remota | AJ93: Concluido | AL93: 28/07/2022 | AM93: 27/07/2022 21:00 | AN93: 27/07/2022 21:00 | AO93: 27/07/2022 21:00 | AP93: SIGLOCAL | AQ93: Avaliado | AT93: 28/08/2022 | AU93: 27/07/2022 21:00 | AV93: 27/07/2022 21:00 | AW93: 27/07/2022 21:00 | AX93: MATHEUS NAVARRO | AY93: Avaliado | BB93: 28/08/2022 | BC93: 27/07/2022 21:00 | BD93: 27/07/2022 21:00 | BE93: 27/07/2022 21:00 | BF93: MATHEUS NAVARRO | BH93: FALSE | BK93: FALSE
B94: 15292 | C94: COZAC | D94: 59252 | E94: 203217 | F94: 172734 | H94: Imóvel Urbano | I94: Casa Residencial | J94: Ribeirão Preto | K94: SP | L94: Localizado | M94: Nível 1 | N94: Validação Avaliação Urbano | O94: rd.avaliacao@enforcegroup.com.br | Q94: JULIA JORGE | R94: Concluída | S94: 27/06/2022 | T94: 27/05/2022 08:53 | U94: 26/05/2022 21:00 | V94: 12/06/2022 21:00 | W94: 15/06/2022 21:00 | X94: =W94*1 -> 44727.875 | Y94: MIGRADO_ZOHO | Z94: Pesquisa de Bens | AA94: BANCO DO BRASIL (SGL_NAME) | AB94: Rua Júlio de Mesquita, 794 | AC94: Vila Virgínia | AD94: 79.24 | AE94: 0 | AF94: 169.95 | AG94: m2 | AH94: T1 | AI94: Remota | AJ94: Concluido | AL94: 02/06/2022 | AM94: 26/05/2022 21:00 | AN94: 26/05/2022 21:00 | AO94: 01/06/2022 21:00 | AP94: HERGOM | AQ94: Avaliado | AS94: Normal | AT94: 27/06/2022 | AU94: 26/05/2022 21:00 | AV94: 12/06/2022 21:00 | AW94: 15/06/2022 21:00 | AX94: JULIA JORGE | AY94: Avaliado | BB94: 27/06/2022 | BC94: 15/06/2022 21:00 | BD94: 12/06/2022 21:00 | BE94: 29/06/2022 21:00 | BF94: MARINA FAHL | BH94: FALSE | BK94: FALSE
B95: 15292 | C95: COZAC | D95: 62872 | E95: 1002000 | F95: 701000 | H95: Imóvel Urbano | I95: Terreno urbano | J95: Ribeirão Preto | K95: SP | L95: Localizado | M95: Nível 3 | N95: Validação Avaliação Urbano | O95: IVO LAMAS | P95: GESTÃO PORTFÓLIO | Q95: ANDERSON SCARPINO | R95: Concluída | S95: 14/08/2025 | T95: 29/07/2025 11:47 | U95: 13/08/2025 20:22 | V95: 14/08/2025 09:20 | W95: 14/08/2025 10:16 | X95: =W95*1 -> 45883.428 | Z95: Análise de Processo | AA95: BANCO DO BRASIL (SGL_NAME) | AB95: Avenida Cavalheiro Paschoal Innecchi | AC95: Independência | AF95: 964.28 | AG95: m2 | AH95: T1 | AI95: Remota | AJ95: Concluido | AL95: 04/04/2023 | AM95: 28/03/2023 17:03 | AN95: 29/03/2023 09:04 | AO95: 04/04/2023 11:39 | AP95: SIGLOCAL ACESSO | AT95: 14/08/2025 | AU95: 13/08/2025 20:22 | AV95: 13/08/2025 09:39 | AW95: 13/08/2025 20:22 | AX95: Victor Libarino | BB95: 14/08/2025 | BC95: 13/08/2025 20:22 | BD95: 14/08/2025 09:20 | BE95: 14/08/2025 10:16 | BF95: ANDERSON SCARPINO | BG95: TRUE | BH95: FALSE | BK95: FALSE
B96: 15292 | C96: COZAC | D96: 62872 | E96: 751500 | F96: 533549 | H96: Imóvel Urbano | I96: Terreno urbano | J96: Ribeirão Preto | K96: SP | L96: Localizado | M96: Nível 3 | N96: Validação Avaliação Urbano | O96: THIAGO MACHADO | P96: GESTÃO PORTFÓLIO | Q96: ANDERSON SCARPINO | R96: Concluída | S96: 21/09/2023 | T96: 06/06/2023 16:39 | U96: 21/09/2023 16:12 | V96: 21/09/2023 16:13 | W96: 21/09/2023 16:16 | X96: =W96*1 -> 45190.678 | Z96: Acordo | AA96: BANCO DO BRASIL (SGL_NAME) | AB96: Avenida Cavalheiro Paschoal Innecchi | AC96: Independência | AF96: 964.28 | AG96: m2 | AH96: T1 | AI96: Remota | AJ96: Concluido | AL96: 04/04/2023 | AM96: 28/03/2023 17:03 | AN96: 29/03/2023 09:04 | AO96: 04/04/2023 11:39 | AP96: SIGLOCAL ACESSO | AT96: 23/06/2023 | AU96: 21/09/2023 16:12 | AV96: 13/06/2023 11:59 | AW96: 23/06/2023 15:52 | AX96: MK ENG DE AVALIACAO | BB96: 21/09/2023 | BC96: 21/09/2023 16:12 | BD96: 21/09/2023 16:13 | BE96: 21/09/2023 16:16 | BF96: ANDERSON SCARPINO | BH96: TRUE | BK96: FALSE
B97: 15292 | C97: COZAC | D97: 62872 | E97: 396932.03 | F97: 297699.02 | H97: Imóvel Urbano | I97: Terreno urbano | J97: Ribeirão Preto | K97: SP | L97: Localizado | M97: Nível 1 | N97: Validação Avaliação Urbano | O97: NATHALIA DIAS | P97: Investigação | Q97: MATHEUS NAVARRO | R97: Concluída | S97: 20/04/2023 | T97: 28/03/2023 17:03 | U97: 07/04/2023 16:29 | V97: 14/04/2023 10:35 | W97: 20/04/2023 09:56 | X97: =W97*1 -> 45036.414 | Z97: Pesquisa de Bens | AA97: BANCO DO BRASIL (SGL_NAME) | AB97: Avenida Cavalheiro Paschoal Innecchi | AC97: Independência | AF97: 964.28 | AG97: m2 | AH97: T1 | AI97: Remota | AJ97: Concluido | AL97: 04/04/2023 | AM97: 28/03/2023 17:03 | AN97: 29/03/2023 09:04 | AO97: 04/04/2023 11:39 | AP97: SIGLOCAL ACESSO | AQ97: Avaliado | AR97: Concluido | AS97: Normal | AT97: 13/04/2023 | AU97: 07/04/2023 16:29 | AV97: 06/04/2023 08:20 | AW97: 07/04/2023 16:29 | AX97: RAIZA GONÇALVES | AY97: Avaliado | AZ97: Concluido | BA97: Normal | BB97: 20/04/2023 | BC97: 07/04/2023 16:29 | BD97: 14/04/2023 10:35 | BE97: 20/04/2023 09:56 | BF97: MATHEUS NAVARRO | BH97: FALSE | BK97: FALSE
B98: 15292 | C98: COZAC | D98: 62872 | E98: 662942 | F98: 530354 | H98: Imóvel Urbano | I98: Terreno urbano | J98: Ribeirão Preto | K98: SP | L98: Localizado | M98: Nível 0 | N98: Validação Avaliação Urbano | O98: rd.avaliacao@enforcegroup.com.br | Q98: ANDRE MAGIORE | R98: Concluída | S98: 28/08/2022 | T98: 28/07/2022 14:39 | U98: 27/07/2022 21:00 | V98: 31/07/2022 21:00 | W98: 31/07/2022 21:00 | X98: =W98*1 -> 44773.875 | Y98: MIGRADO_ZOHO | Z98: Pesquisa de Bens | AA98: BANCO DO BRASIL (SGL_NAME) | AB98: Avenida Cavalheiro Paschoal Innecchi | AC98: Independência | AD98: 0 | AE98: 0 | AF98: 964.28 | AG98: m2 | AH98: T1 | AI98: Remota | AJ98: Concluido | AL98: 28/07/2022 | AM98: 27/07/2022 21:00 | AN98: 27/07/2022 21:00 | AO98: 27/07/2022 21:00 | AP98: SIGLOCAL | AQ98: Avaliado | AS98: Normal | AT98: 28/08/2022 | AU98: 27/07/2022 21:00 | AV98: 31/07/2022 21:00 | AW98: 31/07/2022 21:00 | AX98: ANDRE MAGIORE | AY98: Avaliado | BB98: 28/08/2022 | BC98: 31/07/2022 21:00 | BD98: 31/07/2022 21:00 | BE98: 31/07/2022 21:00 | BF98: ANDERSON SCARPINO | BH98: FALSE | BK98: FALSE
B99: 15292 | C99: COZAC | D99: 62872 | E99: 185619 | F99: 133646 | H99: Imóvel Urbano | I99: Casa Residencial | J99: Ribeirão Preto | K99: SP | L99: Localizado | M99: Nível 1 | N99: Validação Avaliação Urbano | O99: rd.avaliacao@enforcegroup.com.br | Q99: JULIA JORGE | R99: Concluída | S99: 27/06/2022 | T99: 27/05/2022 08:59 | U99: 26/05/2022 21:00 | V99: 12/06/2022 21:00 | W99: 19/06/2022 21:00 | X99: =W99*1 -> 44731.875 | Y99: MIGRADO_ZOHO | Z99: Pesquisa de Bens | AA99: BANCO DO BRASIL (SGL_NAME) | AB99: Rua Renato Barillari, 406 | AC99: Parque Ribeirão Preto | AD99: 82.36 | AE99: 0 | AF99: 150 | AG99: m2 | AH99: T1 | AI99: Remota | AJ99: Concluido | AL99: 02/06/2022 | AM99: 26/05/2022 21:00 | AN99: 26/05/2022 21:00 | AO99: 01/06/2022 21:00 | AP99: HERGOM | AQ99: Avaliado | AS99: Normal | AT99: 27/06/2022 | AU99: 26/05/2022 21:00 | AV99: 12/06/2022 21:00 | AW99: 19/06/2022 21:00 | AX99: JULIA JORGE | AY99: Avaliado | BB99: 27/06/2022 | BC99: 19/06/2022 21:00 | BD99: 12/06/2022 21:00 | BE99: 29/06/2022 21:00 | BF99: MARINA FAHL | BH99: FALSE | BK99: FALSE
B100: 15292 | C100: COZAC | D100: 72157 | E100: 2969000 | F100: 1781000 | H100: Imóvel Urbano | I100: Terreno urbano | J100: Ribeirão Preto | K100: SP | L100: Localizado | M100: Nível 3 | N100: Validação Avaliação Urbano | O100: IVO LAMAS | P100: GESTÃO PORTFÓLIO | Q100: ANDERSON SCARPINO | R100: Concluída | S100: 14/08/2025 | T100: 29/07/2025 11:49 | U100: 13/08/2025 20:20 | V100: 14/08/2025 09:20 | W100: 14/08/2025 10:11 | X100: =W100*1 -> 45883.424 | Z100: Análise de Processo | AA100: BANCO DO BRASIL (SGL_NAME) | AB100: Rua Américo Sampaio | AC100: Independência | AD100: 879.25 | AF100: 3406.5 | AG100: m2 | AH100: T1 | AI100: Remota | AJ100: Concluido | AL100: 05/04/2023 | AM100: 28/03/2023 17:05 | AN100: 29/03/2023 09:03 | AO100: 30/03/2023 19:44 | AP100: AGROFFICIO ATENDIMENTO | AT100: 14/08/2025 | AU100: 13/08/2025 20:20 | AV100: 13/08/2025 09:39 | AW100: 13/08/2025 20:20 | AX100: Victor Libarino | BB100: 14/08/2025 | BC100: 13/08/2025 20:20 | BD100: 14/08/2025 09:20 | BE100: 14/08/2025 10:11 | BF100: ANDERSON SCARPINO | BG100: TRUE | BH100: FALSE | BK100: FALSE
...

Sheet Contrato
B2: Data Base | C2: 45978 | E2: Cobrar | L2: Cenário - A | M2: Cenário - B | O2: Cenário - C
E3: INPC | L3: V. Forçada | M3: V. Mercado | O3: 2x V. Forçada
L4: ='Resumo Imóveis 2 - VENDAS'!I46/10^6 -> 17.871567 | M4: ='Resumo Imóveis 2 - VENDAS'!G46/10^6 -> 21.429554 | O4: =L4*2 -> 35.743135
C5: Saldo para Repagamento | P5: 0.6 | Q5: =1-P5 -> 0.4
C6: Tipo | D6: Vl. Desembolso | E6: Vl. Atualizado | F6: Atualização | I6: Data | J6: Saldo Atualiz. | L6: Sobejo - A | M6: Sobejo - B | O6: Sobejo - C | P6: Investidor | Q6: Controlador
B7: DESEMBOLSOS | C7: Compras de Crédito | D7: =Desembolsos!$B$27 -> 2846895.5 | E7: =Desembolsos!E27 -> 11573900 | F7: 30%a.a. | I7: 45978 | J7: 20.358823 | L7: - | M7: =$M$4-J7 -> 1.0707306 | O7: =$O$4-J7 -> 15.384311 | P7: =IFERROR($P$5*O7,"-") -> 9.2305868 | Q7: =IFERROR($Q$5*O7,"-") -> 6.1537245
B8: DESEMBOLSOS | C8: Compras de Crédito (Tribut.) | D8: ='Despesas - NPL'!H2 -> 3511359.7 | E8: ='Despesas - NPL'!K2 -> 23729063 | F8: 30%a.a. | I8: 45992 | J8: 20.492451 | L8: - | M8: =$M$4-J8 -> 0.93710261 | O8: =$O$4-J8 -> 15.250683 | P8: =IFERROR($P$5*O8,"-") -> 9.15041 | Q8: =IFERROR($Q$5*O8,"-") -> 6.1002733
B9: DESPESAS | C9: Despesas NPL | D9: ='Despesas - NPL'!H1 -> 1550332.6 | E9: ='Despesas - NPL'!L1 -> 1773514.3 | F9: CDI | I9: =EDATE(I8,1) -> 46023 | J9: 20.797693 | L9: - | M9: =$M$4-J9 -> 0.63186112 | O9: =$O$4-J9 -> 14.945442 | P9: =IFERROR($P$5*O9,"-") -> 8.9672651 | Q9: =IFERROR($Q$5*O9,"-") -> 5.9781767
B10: DESPESAS | C10: Despesas SPE | D10: ='Despesas - SPE'!G2 -> 2227253.4 | E10: ='Despesas - SPE'!K2 -> 2260325.1 | F10: CDI | I10: =EDATE(I9,1) -> 46054 | J10: 21.11375 | L10: - | M10: =$M$4-J10 -> 0.31580391 | O10: =$O$4-J10 -> 14.629385 | P10: =IFERROR($P$5*O10,"-") -> 8.7776307 | Q10: =IFERROR($Q$5*O10,"-") -> 5.8517538
C11: Saldo Total | D11: =SUM(D7:D10) -> 10135841 | E11: =SUM(E7:E10) -> 39336802 | I11: =EDATE(I10,1) -> 46082 | J11: 21.404372 | L11: - | M11: =$M$4-J11 -> 0.025182058 | O11: =$O$4-J11 -> 14.338763 | P11: =IFERROR($P$5*O11,"-") -> 8.6032576 | Q11: =IFERROR($Q$5*O11,"-") -> 5.7355051
I12: =EDATE(I11,1) -> 46113 | J12: 21.721086 | L12: - | M12: - | O12: =$O$4-J12 -> 14.022048 | P12: =IFERROR($P$5*O12,"-") -> 8.413229 | Q12: =IFERROR($Q$5*O12,"-") -> 5.6088193
I13: =EDATE(I12,1) -> 46143 | J13: 22.034309 | L13: - | M13: - | O13: =$O$4-J13 -> 13.708826 | P13: =IFERROR($P$5*O13,"-") -> 8.2252956 | Q13: =IFERROR($Q$5*O13,"-") -> 5.4835304
E14: =E11/10^6 -> 39.336802 | I14: =EDATE(I13,1) -> 46174 | J14: 22.357667 | L14: - | M14: - | O14: =$O$4-J14 -> 13.385467 | P14: =IFERROR($P$5*O14,"-") -> 8.0312803 | Q14: =IFERROR($Q$5*O14,"-") -> 5.3541869
E15: 45985 | F15: 40.273009 | I15: =EDATE(I14,1) -> 46204 | J15: 22.665882 | L15: - | M15: - | O15: =$O$4-J15 -> 13.077253 | P15: =IFERROR($P$5*O15,"-") -> 7.8463515 | Q15: =IFERROR($Q$5*O15,"-") -> 5.230901
E16: 46015 | F16: 41.208984 | I16: =EDATE(I15,1) -> 46235 | J16: 22.990847 | L16: - | M16: - | O16: =$O$4-J16 -> 12.752288 | P16: =IFERROR($P$5*O16,"-") -> 7.6513726 | Q16: =IFERROR($Q$5*O16,"-") -> 5.1009151
E17: 46357 | F17: 54.168808 | I17: =EDATE(I16,1) -> 46266 | J17: 23.322303 | L17: - | M17: - | O17: =$O$4-J17 -> 12.420832 | P17: =IFERROR($P$5*O17,"-") -> 7.4524991 | Q17: =IFERROR($Q$5*O17,"-") -> 4.9683327
E18: 46722 | F18: 72.859582 | I18: =EDATE(I17,1) -> 46296 | J18: 23.657647 | L18: - | M18: - | O18: =$O$4-J18 -> 12.085488 | P18: =IFERROR($P$5*O18,"-") -> 7.2512929 | Q18: =IFERROR($Q$5*O18,"-") -> 4.8341953
E19: 47088 | F19: 98.401372 | I19: =EDATE(I18,1) -> 46327 | J19: 24.022793 | L19: - | M19: - | O19: =$O$4-J19 -> 11.720342 | P19: =IFERROR($P$5*O19,"-") -> 7.0322052 | Q19: =IFERROR($Q$5*O19,"-") -> 4.6881368
E20: 47453 | F20: 133.48944 | I20: =EDATE(I19,1) -> 46357 | J20: 24.385179 | L20: - | M20: - | O20: =$O$4-J20 -> 11.357956 | P20: =IFERROR($P$5*O20,"-") -> 6.8147736 | Q20: =IFERROR($Q$5*O20,"-") -> 4.5431824
I21: =EDATE(I20,1) -> 46388 | J21: 24.779145 | L21: - | M21: - | O21: =$O$4-J21 -> 10.96399 | P21: =IFERROR($P$5*O21,"-") -> 6.578394 | Q21: =IFERROR($Q$5*O21,"-") -> 4.385596
I22: =EDATE(I21,1) -> 46419 | J22: 25.184658 | L22: - | M22: - | O22: =$O$4-J22 -> 10.558477 | P22: =IFERROR($P$5*O22,"-") -> 6.3350859 | Q22: =IFERROR($Q$5*O22,"-") -> 4.2233906
I23: =EDATE(I22,1) -> 46447 | J23: 25.558187 | L23: - | M23: - | O23: =$O$4-J23 -> 10.184948 | P23: =IFERROR($P$5*O23,"-") -> 6.1109686 | Q23: =IFERROR($Q$5*O23,"-") -> 4.0739791
I24: =EDATE(I23,1) -> 46478 | J24: 25.967657 | L24: - | M24: - | O24: =$O$4-J24 -> 9.7754781 | P24: =IFERROR($P$5*O24,"-") -> 5.8652869 | Q24: =IFERROR($Q$5*O24,"-") -> 3.9101912
I25: =EDATE(I24,1) -> 46508 | J25: 26.372735 | L25: - | M25: - | O25: =$O$4-J25 -> 9.3703995 | P25: =IFERROR($P$5*O25,"-") -> 5.6222397 | Q25: =IFERROR($Q$5*O25,"-") -> 3.7481598
I26: =EDATE(I25,1) -> 46539 | J26: 26.798927 | L26: - | M26: - | O26: =$O$4-J26 -> 8.9442074 | P26: =IFERROR($P$5*O26,"-") -> 5.3665244 | Q26: =IFERROR($Q$5*O26,"-") -> 3.5776829
I27: =EDATE(I26,1) -> 46569 | J27: =J26*H27 -> 0 | L27: - | M27: - | O27: =$O$4-J27 -> 35.743135 | P27: =IFERROR($P$5*O27,"-") -> 21.445881 | Q27: =IFERROR($Q$5*O27,"-") -> 14.297254
I28: =EDATE(I27,1) -> 46600 | J28: =J27*H28 -> 0 | L28: - | M28: - | O28: =$O$4-J28 -> 35.743135 | P28: =IFERROR($P$5*O28,"-") -> 21.445881 | Q28: =IFERROR($Q$5*O28,"-") -> 14.297254
I29: =EDATE(I28,1) -> 46631 | J29: =J28*H29 -> 0 | L29: - | M29: - | O29: =$O$4-J29 -> 35.743135 | P29: =IFERROR($P$5*O29,"-") -> 21.445881 | Q29: =IFERROR($Q$5*O29,"-") -> 14.297254
I30: =EDATE(I29,1) -> 46661 | J30: =J29*H30 -> 0 | L30: - | M30: - | O30: =$O$4-J30 -> 35.743135 | P30: =IFERROR($P$5*O30,"-") -> 21.445881 | Q30: =IFERROR($Q$5*O30,"-") -> 14.297254
I31: =EDATE(I30,1) -> 46692 | J31: =J30*H31 -> 0 | L31: - | M31: - | O31: =$O$4-J31 -> 35.743135 | P31: =IFERROR($P$5*O31,"-") -> 21.445881 | Q31: =IFERROR($Q$5*O31,"-") -> 14.297254
I32: =EDATE(I31,1) -> 46722 | J32: =J31*H32 -> 0 | L32: - | M32: - | O32: =$O$4-J32 -> 35.743135 | P32: =IFERROR($P$5*O32,"-") -> 21.445881 | Q32: =IFERROR($Q$5*O32,"-") -> 14.297254
I33: =EDATE(I32,1) -> 46753 | J33: =J32*H33 -> 0 | L33: - | M33: - | O33: =$O$4-J33 -> 35.743135 | P33: =IFERROR($P$5*O33,"-") -> 21.445881 | Q33: =IFERROR($Q$5*O33,"-") -> 14.297254
I34: =EDATE(I33,1) -> 46784 | J34: =J33*H34 -> 0 | L34: - | M34: - | O34: =$O$4-J34 -> 35.743135 | P34: =IFERROR($P$5*O34,"-") -> 21.445881 | Q34: =IFERROR($Q$5*O34,"-") -> 14.297254
I35: =EDATE(I34,1) -> 46813 | J35: =J34*H35 -> 0 | L35: - | M35: - | O35: =$O$4-J35 -> 35.743135 | P35: =IFERROR($P$5*O35,"-") -> 21.445881 | Q35: =IFERROR($Q$5*O35,"-") -> 14.297254
C36: Saldo para Repagamento | E36: R$MM | I36: =EDATE(I35,1) -> 46844 | J36: =J35*H36 -> 0 | L36: - | M36: - | O36: =$O$4-J36 -> 35.743135 | P36: =IFERROR($P$5*O36,"-") -> 21.445881 | Q36: =IFERROR($Q$5*O36,"-") -> 14.297254
C37: Data | D37: Cenário A | E37: Cenário B | I37: =EDATE(I36,1) -> 46874 | J37: =J36*H37 -> 0 | L37: - | M37: - | O37: =$O$4-J37 -> 35.743135 | P37: =IFERROR($P$5*O37,"-") -> 21.445881 | Q37: =IFERROR($Q$5*O37,"-") -> 14.297254
C38: 45985 | D38: 40.273009 | E38: 20.418019 | I38: =EDATE(I37,1) -> 46905 | J38: =J37*H38 -> 0 | L38: - | M38: - | O38: =$O$4-J38 -> 35.743135 | P38: =IFERROR($P$5*O38,"-") -> 21.445881 | Q38: =IFERROR($Q$5*O38,"-") -> 14.297254
C39: =EDATE(C38,1) -> 46015 | D39: 41.208984 | E39: 20.690096 | I39: =EDATE(I38,1) -> 46935 | J39: =J38*H39 -> 0 | L39: - | M39: - | O39: =$O$4-J39 -> 35.743135 | P39: =IFERROR($P$5*O39,"-") -> 21.445881 | Q39: =IFERROR($Q$5*O39,"-") -> 14.297254
C40: 46357 | D40: 54.168808 | E40: 24.385179 | I40: =EDATE(I39,1) -> 46966 | J40: =J39*H40 -> 0 | L40: - | M40: - | O40: =$O$4-J40 -> 35.743135 | P40: =IFERROR($P$5*O40,"-") -> 21.445881 | Q40: =IFERROR($Q$5*O40,"-") -> 14.297254
C41: 46722 | D41: 72.859582 | E41: 29.459906 | I41: =EDATE(I40,1) -> 46997 | J41: =J40*H41 -> 0 | L41: - | M41: - | O41: =$O$4-J41 -> 35.743135 | P41: =IFERROR($P$5*O41,"-") -> 21.445881 | Q41: =IFERROR($Q$5*O41,"-") -> 14.297254
C42: 47088 | D42: 98.401372 | E42: 36.03285 | I42: =EDATE(I41,1) -> 47027 | J42: =J41*H42 -> 0 | L42: - | M42: - | O42: =$O$4-J42 -> 35.743135 | P42: =IFERROR($P$5*O42,"-") -> 21.445881 | Q42: =IFERROR($Q$5*O42,"-") -> 14.297254
C43: 47453 | D43: 133.48944 | E43: 44.536833 | I43: =EDATE(I42,1) -> 47058 | J43: =J42*H43 -> 0 | L43: - | M43: - | O43: =$O$4-J43 -> 35.743135 | P43: =IFERROR($P$5*O43,"-") -> 21.445881 | Q43: =IFERROR($Q$5*O43,"-") -> 14.297254
I44: =EDATE(I43,1) -> 47088 | J44: =J43*H44 -> 0 | L44: - | M44: - | O44: =$O$4-J44 -> 35.743135 | P44: =IFERROR($P$5*O44,"-") -> 21.445881 | Q44: =IFERROR($Q$5*O44,"-") -> 14.297254
I45: =EDATE(I44,1) -> 47119 | J45: =J44*H45 -> 0 | L45: - | M45: - | O45: =$O$4-J45 -> 35.743135 | P45: =IFERROR($P$5*O45,"-") -> 21.445881 | Q45: =IFERROR($Q$5*O45,"-") -> 14.297254
I46: =EDATE(I45,1) -> 47150 | J46: =J45*H46 -> 0 | L46: - | M46: - | O46: =$O$4-J46 -> 35.743135 | P46: =IFERROR($P$5*O46,"-") -> 21.445881 | Q46: =IFERROR($Q$5*O46,"-") -> 14.297254
I47: =EDATE(I46,1) -> 47178 | J47: =J46*H47 -> 0 | L47: - | M47: - | O47: =$O$4-J47 -> 35.743135 | P47: =IFERROR($P$5*O47,"-") -> 21.445881 | Q47: =IFERROR($Q$5*O47,"-") -> 14.297254
I48: =EDATE(I47,1) -> 47209 | J48: =J47*H48 -> 0 | L48: - | M48: - | O48: =$O$4-J48 -> 35.743135 | P48: =IFERROR($P$5*O48,"-") -> 21.445881 | Q48: =IFERROR($Q$5*O48,"-") -> 14.297254

Sheet Desembolsos
D2: =Contrato!$C$2 -> 45978
A3: CREDOR | B3: VALOR CESSÃO | C3: DATA PAGAMENTO | D3: HOJE | E3: VALOR ATT 30%
A4: AGAMENNON BRUNETTI JÚNIOR | B4: 26000 | C4: 43577 | D4: =$D$2 -> 45978 | E4: =B4*1.3^((D4-C4)/360) -> 149593.32
A5: DIONE DE SOUZA DA SILVA | B5: 2000 | C5: 43815 | D5: =$D$2 -> 45978 | E5: =B5*1.3^((D5-C5)/360) -> 9674.7475
A6: JOSE WILSON RODRIGUES NUNES | B6: 3733.37 | C6: 43812 | D6: =$D$2 -> 45978 | E6: =B6*1.3^((D6-C6)/360) -> 18099.234
A7: JUAREZ DELCIDES DOURADO | B7: 4405.26 | C7: 43812 | D7: =$D$2 -> 45978 | E7: =B7*1.3^((D7-C7)/360) -> 21356.531
A8: MARIANGELA CAIXETA GUIMARAES | B8: 23000 | C8: 43797 | D8: =$D$2 -> 45978 | E8: =B8*1.3^((D8-C8)/360) -> 112728.74
A9: RODRIGO SANTIAGO SANTO DE CARVALHO | B9: 4011.88 | C9: 43812 | D9: =$D$2 -> 45978 | E9: =B9*1.3^((D9-C9)/360) -> 19449.44
A10: ROMES LEMES | B10: 3887.38 | C10: 43812 | D10: =$D$2 -> 45978 | E10: =B10*1.3^((D10-C10)/360) -> 18845.869
A11: ARNALDO NOGUEIRA DOS SANTOS | B11: 3022.92 | C11: 43812 | D11: =$D$2 -> 45978 | E11: =B11*1.3^((D11-C11)/360) -> 14655
A12: CLEMENTE NUNES DA COSTA | B12: 2376.7 | C12: 43812 | D12: =$D$2 -> 45978 | E12: =B12*1.3^((D12-C12)/360) -> 11522.15
A13: GRIGORIO MANOEL DE SOUZA | B13: 3697.44 | C13: 43812 | D13: =$D$2 -> 45978 | E13: =B13*1.3^((D13-C13)/360) -> 17925.047
A14: JOAQUIM MAURÍCIO DE CARVALHO | B14: 11000 | C14: 43577 | D14: =$D$2 -> 45978 | E14: =B14*1.3^((D14-C14)/360) -> 63289.482
A15: JOSÉ CARLOS POLLONI | B15: 57760.6 | C15: 43812 | D15: =$D$2 -> 45978 | E15: =B15*1.3^((D15-C15)/360) -> 280021.17
... A26: Compra de creditos | B26: 1100000 | C26: 44796 | D26: =$D$2 -> 45978 | E26: =B26*1.3^((D26-C26)/360) -> 2603194.9
B27: =SUM(B4:B26) -> 2846895.5 | E27: =SUM(E4:E26) -> 11573900

Sheet Despesas(OLD)
A2: Tipo de baixa | B2: Pagamento | C2: Emissão | D2: Total Título | E2: Bruto | F2: Líquido | G2: Título | H2: Credor | I2: Cod. P.F. | J2: Descrição P.F | K2: Cod. C.C. | L2: Descrição C.C. | M2: Cod. A.N. | N2: Descrição A.N. | O2: Observação | P2: Cod. Banco | Q2: Nome Banco | R2: Descrição Doc. | S2: Número Doc. | T2: HOJE | U2: VALOR ATT inpc | V2: VALOR ATT
A3: *** Pagamento *** | B3: 43825 | C3: 43825 | D3: 1105423.3 | E3: 1105423.3 | F3: 1105423.3 | G3: 83573 | H3: MINISTERIO DA ECONOMIA | I3: 2.20.03.10 | J3: OUTRAS DESPESAS COM ATIVOS | K3: 10027 | L3: 0015292_COZAC_FALENCIA | M3: 44 | N3: FALENCIA E RJ_TOMBADO | O3: GUIA DE RECOLHIMENTO DE DEBITOS TRIBUTARIOS COZAC ENGENHARIA- PAGAMENTO PELO ADIANTAMENTO REALIZADO PELO FIDC | P3: 13013697-3 | Q3: SANTANDER - ENFORCE | R3: GUIA PARA RECOLHIMENTO DE IMPOSTOS | S3: 07.17.193570975753-0 | T3: 45978 | U3: {=[15]!CalculateINPC(B3,T3,-1)*F3} -> 1550553.2 | V3: =F3*1.3^((T3-B3)/360) -> 5308516.5
A4: *** Pagamento *** | B4: 44722 | C4: 44721 | D4: 4030.38 | E4: 4030.38 | F4: 4030.38 | G4: 151254 | H4: 1 TABELIAO DE PROTESTO DE LETRAS E TITULOS DA COMARCA DE RIBEIRÃO PRETO | I4: 2.20.03.15 | J4: IPTU - CUSTO REGULARIZACAO | K4: 10027 | L4: 0015292_COZAC_FALENCIA | M4: 44 | N4: FALENCIA E RJ_TOMBADO | O4: BOLETO REFERENTE AO PROTESTO DE IPTU REFERENTE AO CASO COZAC - 541108715 PIPEFY | P4: 13013697-3 | Q4: SANTANDER - ENFORCE | R4: BOLETO | S4: 321 | T4: 45978 | U4: {=[15]!CalculateINPC(B4,T4,-1)*F4} -> 4580.875 | V4: =F4*1.3^((T4-B4)/360) -> 10066.574
A5: *** Pagamento *** | B5: 44881 | C5: 44876 | D5: 2061.09 | E5: 2061.09 | F5: 2061.09 | G5: 161618 | H5: 1 TABELIAO DE PROTESTO DE LETRAS E TITULOS DA COMARCA DE RIBEIRÃO PRETO | I5: 2.20.03.02 | J5: IPTU E TAXA DE LIXO | K5: 10027 | L5: 0015292_COZAC_FALENCIA | M5: 44 | N5: FALENCIA E RJ_TOMBADO | O5: Pagamento protesto IPTU caso Cozac. http://app.pipefy.com/pipes/301656781#cards/600221268 | P5: 13013697-3 | Q5: SANTANDER - ENFORCE | R5: BOLETO | S5: 160 | T5: 45978 | U5: {=[15]!CalculateINPC(B5,T5,-1)*F5} -> 2346.0245 | V5: =F5*1.3^((T5-B5)/360) -> 4584.6657
A6: *** Pagamento *** | B6: 44876 | C6: 44869 | D6: 934.94 | E6: 934.94 | F6: 934.94 | G6: 161503 | H6: 1 TABELIAO DE PROTESTO DE LETRAS E TITULOS DA COMARCA DE RIBEIRÃO PRETO | I6: 2.20.03.10 | J6: OUTRAS DESPESAS COM ATIVOS | K6: 10027 | L6: 0015292_COZAC_FALENCIA | M6: 44 | N6: FALENCIA E RJ_TOMBADO | O6: Boleto protesto IPTU Cozac - 599771525 - Pipefy | P6: 13013697-3 | Q6: SANTANDER - ENFORCE | R6: BOLETO | S6: 658 | T6: 45978 | U6: {=[15]!CalculateINPC(B6,T6,-1)*F6} -> 1064.1904 | V6: =F6*1.3^((T6-B6)/360) -> 2087.2622
A7: *** Pagamento *** | B7: 45509 | C7: 45503 | D7: 250000 | E7: 250000 | F7: 250000 | G7: 203921 | H7: DANIEL CARNIO ADVOGADOS | I7: 2.20.04.01 | J7: HONORÁRIOS | K7: 18799 | L7: 0015292_COZAC_FALENCIA | M7: 243 | N7: FALENCIA E RJ_TOMBADO | O7: HONORARIOS ADVOCATICIOS REFERENTE A ELABORACAO DE PARECER JURIDICO E DESPACHO NO CASO COZAC. CONTRATO ASSINADO POR TODAS AS PARTES. (MARLENE TOCANDO O PGTO)APROVACAO DO CAMARA ANEXA AO CARD. | P7: DIRETAS | Q7: DIRETAS | R7: NOTA FISCAL DE SERVIÇOS | S7: 38 | T7: 45978 | U7: {=[15]!CalculateINPC(B7,T7,-1)*F7} -> 263711.02 | V7: =F7*1.3^((T7-B7)/360) -> 351870.51
A8: *** Pagamento *** | B8: 44722 | C8: 44719 | D8: 876.22 | E8: 876.22 | F8: 876.22 | G8: 151250 | H8: 1 TABELIAO DE PROTESTO DE LETRAS E TITULOS DA COMARCA DE RIBEIRÃO PRETO | I8: 2.20.03.15 | J8: IPTU - CUSTO REGULARIZACAO | K8: 10027 | L8: 0015292_COZAC_FALENCIA | M8: 44 | N8: FALENCIA E RJ_TOMBADO | O8: BOLETO REFERENTE AO PROTESTO DE IPTU REFERENTE AO CASO COZAC - 541108594 PIPEFY | P8: 13013697-3 | Q8: SANTANDER - ENFORCE | R8: BOLETO | S8: 343 | T8: 45978 | U8: {=[15]!CalculateINPC(B8,T8,-1)*F8} -> 995.89971 | V8: =F8*1.3^((T8-B8)/360) -> 2188.5116
A9: *** Pagamento *** | B9: 44757 | C9: 44754 | D9: 696.16 | E9: 696.16 | F9: 696.16 | G9: 153637 | H9: 1 TABELIAO DE PROTESTO DE LETRAS E TITULOS DA COMARCA DE RIBEIRÃO PRETO | I9: 2.20.03.15 | J9: IPTU - CUSTO REGULARIZACAO | K9: 10027 | L9: 0015292_COZAC_FALENCIA | M9: 44 | N9: FALENCIA E RJ_TOMBADO | O9: Pagamento protestos Cozac - 553542051 PIPEFY | P9: 13013697-3 | Q9: SANTANDER - ENFORCE | R9: BOLETO | S9: 25 | T9: 45978 | U9: {=[15]!CalculateINPC(B9,T9,-1)*F9} -> 786.3701 | V9: =F9*1.3^((T9-B9)/360) -> 1694.9892
A10: *** Pagamento *** | B10: 43825 | C10: 43825 | D10: 180480.79 | E10: 180480.79 | F10: 180480.79 | G10: 83575 | H10: MINISTERIO DA ECONOMIA | I10: 2.20.03.10 | J10: OUTRAS DESPESAS COM ATIVOS | K10: 10027 | L10: 0015292_COZAC_FALENCIA | M10: 44 | N10: FALENCIA E RJ_TOMBADO | O10: GUIA DE RECOLHIMENTO DE DEBITOS TRIBUTARIOS COZAC IMOVEIS -PAGAMENTO PELO ADIANTAMENTO REALIZADO PELO FIDC | P10: 32183-4 | Q10: BRADESCO - ENFORCE | R10: GUIA PARA RECOLHIMENTO DE IMPOSTOS | S10: 07.17.19357.0972899- | T10: 45978 | U10: {=[15]!CalculateINPC(B10,T10,-1)*F10} -> 253156.48 | V10: =F10*1.3^((T10-B10)/360) -> 866713.44
A11: *** Pagamento *** | B11: 44757 | C11: 44754 | D11: 696.16 | E11: 696.16 | F11: 696.16 | G11: 153631 | H11: 1 TABELIAO DE PROTESTO DE LETRAS E TITULOS DA COMARCA DE RIBEIRÃO PRETO | I11: 2.20.03.15 | J11: IPTU - CUSTO REGULARIZACAO | K11: 10027 | L11: 0015292_COZAC_FALENCIA | M11: 44 | N11: FALENCIA E RJ_TOMBADO | O11: Pagamento protestos Cozac - 553543837 PIPEFY | P11: 13013697-3 | Q11: SANTANDER - ENFORCE | R11: BOLETO | S11: 26 | T11: 45978 | U11: {=[15]!CalculateINPC(B11,T11,-1)*F11} -> 786.3701 | V11: =F11*1.3^((T11-B11)/360) -> 1694.9892
A12: *** Pagamento *** | B12: 43825 | C12: 43825 | D12: 154903.85 | E12: 154903.85 | F12: 154903.85 | G12: 83576 | H12: MINISTERIO DA ECONOMIA | I12: 2.20.03.10 | J12: OUTRAS DESPESAS COM ATIVOS | K12: 10027 | L12: 0015292_COZAC_FALENCIA | M12: 44 | N12: FALENCIA E RJ_TOMBADO | O12: GUIA DE RECOLHIMENTO DE DEBITOS TRIBUTARIOS COZAC ENGENHARIA -PAGAMENTO PELO ADIANTAMENTO REALIZADO PELO FIDC | P12: 32183-4 | Q12: BRADESCO - ENFORCE | R12: GUIA PARA RECOLHIMENTO DE IMPOSTOS | S12: 07.17.19357.0982752- | T12: 45978 | U12: {=[15]!CalculateINPC(B12,T12,-1)*F12} -> 217280.26 | V12: =F12*1.3^((T12-B12)/360) -> 743886.64
A13: *** Pagamento *** | B13: 44757 | C13: 44754 | D13: 696.16 | E13: 696.16 | F13: 696.16 | G13: 153621 | H13: 1 TABELIAO DE PROTESTO DE LETRAS E TITULOS DA COMARCA DE RIBEIRÃO PRETO | I13: 2.20.03.15 | J13: IPTU - CUSTO REGULARIZACAO | K13: 10027 | L13: 0015292_COZAC_FALENCIA | M13: 44 | N13: FALENCIA E RJ_TOMBADO | O13: Pagamento protestos Cozac - 553538611 PIPEFY | P13: 13013697-3 | Q13: SANTANDER - ENFORCE | R13: BOLETO | S13: 23 | T13: 45978 | U13: {=[15]!CalculateINPC(B13,T13,-1)*F13} -> 786.3701 | V13: =F13*1.3^((T13-B13)/360) -> 1694.9892
A14: *** Pagamento *** | B14: 44757 | C14: 44754 | D14: 696.16 | E14: 696.16 | F14: 696.16 | G14: 153646 | H14: 1 TABELIAO DE PROTESTO DE LETRAS E TITULOS DA COMARCA DE RIBEIRÃO PRETO | I14: 2.20.03.15 | J14: IPTU - CUSTO REGULARIZACAO | K14: 10027 | L14: 0015292_COZAC_FALENCIA | M14: 44 | N14: FALENCIA E RJ_TOMBADO | O14: Pagamento protestos Cozac - 553541810 PIPEFY | P14: 13013697-3 | Q14: SANTANDER - ENFORCE | R14: BOLETO | S14: 24 | T14: 45978 | U14: {=[15]!CalculateINPC(B14,T14,-1)*F14} -> 786.3701 | V14: =F14*1.3^((T14-B14)/360) -> 1694.9892
... A316: *** Pagamento *** | B316: 45806 | C316: 45789 | D316: 132145.8 | E316: 2 | F316: 2 | G316: 254289 | H316: 4MTI SOLUÇÕES LTDA ME | I316: 2.20.05.04 | J316: SISTEMAS DE BUSCA (SERASA, UPMINER, API, DIGESTO) | K316: 10027 | L316: 0015292_COZAC_FALENCIA | M316: 44 | N316: FALENCIA E RJ_TOMBADO | O316: ADM | REEMBOLSAVEIS - 28800 JESTORDesenvolvimento de sistema de coleta de dados online.Mensalidade de R$ 66.735,60 contratuais para manutencao e evolucao do projeto.Foram realizadas 199.642 consultas, que totalizam o montante de R$ 65.410,20.REF. 04/2025RETENCAO OK | P316: 13013697-3 | Q316: SANTANDER - ENFORCE | R316: NOTA FISCAL DE SERVIÇOS | S316: 73 | T316: 45978 | U316: {=[15]!CalculateINPC(B316,T316,-1)*F316} -> 2.022674 | V316: =F316*1.3^((T316-B316)/360) -> 2.2670944

Sheet Despesas(BI)
A1: Filtros aplicados: Caso é COZAC dt_pagamento é igual a ou está depois de 02/12/2016 e está antes de 21/10/2025
E2: =SUM(Table1[vl]) -> 5368354.3 | G2: 45978 | H2: =SUM(Table1[vl at inpc]) -> 6980384.2 | I2: =SUM(Table1[vl at 30]) -> 20897907
A3: Micro-Grupo | B3: Despesas | C3: Date - Ano | D3: Date - Mês | E3: vl | F3: Coluna2 | G3: Coluna3 | H3: vl at inpc | I3: vl at 30
A4: IPTU E TAXA DE LIXO | B4: 2012.3799 | C4: 2019 | D4: dezembro | E4: =Table1[[#This Row],[Despesas]]*1000 -> 2012379.9 | F4: 43800 | G4: =$G$2 -> 45978 | H4: {=[15]!CalculateINPC(Table1[[#This Row],[Coluna2]],Table1[[#This Row],[Coluna3]],-1)*Table1[[#This Row],[vl]]} -> 2822721.5 | I4: =1.3^((Table1[[#This Row],[Coluna3]]-Table1[[#This Row],[Coluna2]])/360)*Table1[[#This Row],[vl]] -> 9841635.1
A5: OUTRAS DESPESAS COM ATIVOS | B5: 1474.4893 | C5: 2019 | D5: dezembro | E5: =Table1[[#This Row],[Despesas]]*1000 -> 1474489.3 | F5: 43800 | G5: =$G$2 -> 45978 | H5: {=[15]!CalculateINPC(Table1[[#This Row],[Coluna2]],Table1[[#This Row],[Coluna3]],-1)*Table1[[#This Row],[vl]]} -> 2068234 | I5: =1.3^((Table1[[#This Row],[Coluna3]]-Table1[[#This Row],[Coluna2]])/360)*Table1[[#This Row],[vl]] -> 7211056.6
A6: HONORÁRIOS (OUTROS TIPOS) | B6: 917.57864 | C6: 2025 | D6: setembro | E6: =Table1[[#This Row],[Despesas]]*1000 -> 917578.64 | F6: 45901 | G6: =$G$2 -> 45978 | H6: {=[15]!CalculateINPC(Table1[[#This Row],[Coluna2]],Table1[[#This Row],[Coluna3]],-1)*Table1[[#This Row],[vl]]} -> 922626.54 | I6: =1.3^((Table1[[#This Row],[Coluna3]]-Table1[[#This Row],[Coluna2]])/360)*Table1[[#This Row],[vl]] -> 970542.4
A7: OUTRAS DESPESAS COM ATIVOS | B7: 313.51782 | C7: 2020 | D7: janeiro | E7: =Table1[[#This Row],[Despesas]]*1000 -> 313517.82 | F7: 43831 | G7: =$G$2 -> 45978 | H7: {=[15]!CalculateINPC(Table1[[#This Row],[Coluna2]],Table1[[#This Row],[Coluna3]],-1)*Table1[[#This Row],[vl]]} -> 434463.89 | I7: =1.3^((Table1[[#This Row],[Coluna3]]-Table1[[#This Row],[Coluna2]])/360)*Table1[[#This Row],[vl]] -> 1499021 | L7: janeiro | M7: 1
A8: HONORÁRIOS | B8: 250 | C8: 2024 | D8: agosto | E8: =Table1[[#This Row],[Despesas]]*1000 -> 250000 | F8: 45505 | G8: =$G$2 -> 45978 | H8: {=[15]!CalculateINPC(Table1[[#This Row],[Coluna2]],Table1[[#This Row],[Coluna3]],-1)*Table1[[#This Row],[vl]]} -> 263711.02 | I8: =1.3^((Table1[[#This Row],[Coluna3]]-Table1[[#This Row],[Coluna2]])/360)*Table1[[#This Row],[vl]] -> 352897.77 | L8: fevereiro | M8: 2
A9: PERICIAS E AVALIAÇÕES | B9: 78.001 | C9: 2023 | D9: agosto | E9: =Table1[[#This Row],[Despesas]]*1000 -> 78001 | F9: 45139 | G9: =$G$2 -> 45978 | H9: {=[15]!CalculateINPC(Table1[[#This Row],[Coluna2]],Table1[[#This Row],[Coluna3]],-1)*Table1[[#This Row],[vl]]} -> 85620.195 | I9: =1.3^((Table1[[#This Row],[Coluna3]]-Table1[[#This Row],[Coluna2]])/360)*Table1[[#This Row],[vl]] -> 143764.44 | L9: março | M9: 3
A10: IPTU E TAXA DE LIXO | B10: 48.60494 | C10: 2022 | D10: novembro | E10: =Table1[[#This Row],[Despesas]]*1000 -> 48604.94 | F10: 44866 | G10: =$G$2 -> 45978 | H10: {=[15]!CalculateINPC(Table1[[#This Row],[Coluna2]],Table1[[#This Row],[Coluna3]],-1)*Table1[[#This Row],[vl]]} -> 55324.31 | I10: =1.3^((Table1[[#This Row],[Coluna3]]-Table1[[#This Row],[Coluna2]])/360)*Table1[[#This Row],[vl]] -> 109304.68 | L10: abril | M10: 4
A11: HONORÁRIOS | B11: 42.863 | C11: 2020 | D11: junho | E11: =Table1[[#This Row],[Despesas]]*1000 -> 42863 | F11: 43983 | G11: =$G$2 -> 45978 | H11: {=[15]!CalculateINPC(Table1[[#This Row],[Coluna2]],Table1[[#This Row],[Coluna3]],-1)*Table1[[#This Row],[vl]]} -> 59363.335 | I11: =1.3^((Table1[[#This Row],[Coluna3]]-Table1[[#This Row],[Coluna2]])/360)*Table1[[#This Row],[vl]] -> 183450.39 | L11: maio | M11: 5
A12: OUTRAS DESPESAS LEGAIS | B12: 20.00894 | C12: 2020 | D12: maio | E12: =Table1[[#This Row],[Despesas]]*1000 -> 20008.94 | F12: 43952 | G12: =$G$2 -> 45978 | H12: {=[15]!CalculateINPC(Table1[[#This Row],[Coluna2]],Table1[[#This Row],[Coluna3]],-1)*Table1[[#This Row],[vl]]} -> 27642.191 | I12: =1.3^((Table1[[#This Row],[Coluna3]]-Table1[[#This Row],[Coluna2]])/360)*Table1[[#This Row],[vl]] -> 87593.514 | L12: junho | M12: 6
A13: DESPACHANTES E DILIGENTES | B13: 15 | C13: 2019 | D13: novembro | E13: =Table1[[#This Row],[Despesas]]*1000 -> 15000 | F13: 43770 | G13: =$G$2 -> 45978 | H13: {=[15]!CalculateINPC(Table1[[#This Row],[Coluna2]],Table1[[#This Row],[Coluna3]],-1)*Table1[[#This Row],[vl]]} -> 21153.797 | I13: =1.3^((Table1[[#This Row],[Coluna3]]-Table1[[#This Row],[Coluna2]])/360)*Table1[[#This Row],[vl]] -> 74979.721 | L13: julho | M13: 7
A14: IPTU - CUSTO REGULARIZACAO | B14: 10.84773 | C14: 2022 | D14: junho | E14: =Table1[[#This Row],[Despesas]]*1000 -> 10847.73 | F14: 44713 | G14: =$G$2 -> 45978 | H14: {=[15]!CalculateINPC(Table1[[#This Row],[Coluna2]],Table1[[#This Row],[Coluna3]],-1)*Table1[[#This Row],[vl]]} -> 12329.382 | I14: =1.3^((Table1[[#This Row],[Coluna3]]-Table1[[#This Row],[Coluna2]])/360)*Table1[[#This Row],[vl]] -> 27272.387 | L14: agosto | M14: 8
A15: HONORÁRIOS | B15: 10 | C15: 2019 | D15: dezembro | E15: =Table1[[#This Row],[Despesas]]*1000 -> 10000 | F15: 43800 | G15: =$G$2 -> 45978 | H15: {=[15]!CalculateINPC(Table1[[#This Row],[Coluna2]],Table1[[#This Row],[Coluna3]],-1)*Table1[[#This Row],[vl]]} -> 14026.782 | I15: =1.3^((Table1[[#This Row],[Coluna3]]-Table1[[#This Row],[Coluna2]])/360)*Table1[[#This Row],[vl]] -> 48905.452 | L15: setembro | M15: 9
A16: PROCURAÇÕES E ESCRITURAS | B16: 5.66385 | C16: 2022 | D16: agosto | E16: =Table1[[#This Row],[Despesas]]*1000 -> 5663.85 | F16: 44774 | G16: =$G$2 -> 45978 | H16: {=[15]!CalculateINPC(Table1[[#This Row],[Coluna2]],Table1[[#This Row],[Coluna3]],-1)*Table1[[#This Row],[vl]]} -> 6436.4085 | I16: =1.3^((Table1[[#This Row],[Coluna3]]-Table1[[#This Row],[Coluna2]])/360)*Table1[[#This Row],[vl]] -> 13620.372 | L16: outubro | M16: 10
A17: PROCURAÇÕES E ESCRITURAS | B17: 5.66385 | C17: 2022 | D17: setembro | E17: =Table1[[#This Row],[Despesas]]*1000 -> 5663.85 | F17: 44805 | G17: =$G$2 -> 45978 | H17: {=[15]!CalculateINPC(Table1[[#This Row],[Coluna2]],Table1[[#This Row],[Coluna3]],-1)*Table1[[#This Row],[vl]]} -> 6456.4218 | I17: =1.3^((Table1[[#This Row],[Coluna3]]-Table1[[#This Row],[Coluna2]])/360)*Table1[[#This Row],[vl]] -> 13316.104 | L17: novembro | M17: 11
A18: IPTU - CUSTO REGULARIZACAO | B18: 5.6326 | C18: 2022 | D18: julho | E18: =Table1[[#This Row],[Despesas]]*1000 -> 5632.6 | F18: 44743 | G18: =$G$2 -> 45978 | H18: {=[15]!CalculateINPC(Table1[[#This Row],[Coluna2]],Table1[[#This Row],[Coluna3]],-1)*Table1[[#This Row],[vl]]} -> 6362.486 | I18: =1.3^((Table1[[#This Row],[Coluna3]]-Table1[[#This Row],[Coluna2]])/360)*Table1[[#This Row],[vl]] -> 13854.725 | L18: dezembro | M18: 12
A19: MATRÍCULAS E CERTIDÕES | B19: 5.41947 | C19: 2025 | D19: abril | E19: =Table1[[#This Row],[Despesas]]*1000 -> 5419.47 | F19: 45748 | G19: =$G$2 -> 45978 | H19: {=[15]!CalculateINPC(Table1[[#This Row],[Coluna2]],Table1[[#This Row],[Coluna3]],-1)*Table1[[#This Row],[vl]]} -> 5507.2167 | I19: =1.3^((Table1[[#This Row],[Coluna3]]-Table1[[#This Row],[Coluna2]])/360)*Table1[[#This Row],[vl]] -> 6408.4641
A20: ANALISE URBANISTICA E AMBIENTAL (REGULATORIO) | B20: 5.28 | C20: 2022 | D20: outubro | E20: =Table1[[#This Row],[Despesas]]*1000 -> 5280 | F20: 44835 | G20: =$G$2 -> 45978 | H20: {=[15]!CalculateINPC(Table1[[#This Row],[Coluna2]],Table1[[#This Row],[Coluna3]],-1)*Table1[[#This Row],[vl]]} -> 6038.1794 | I20: =1.3^((Table1[[#This Row],[Coluna3]]-Table1[[#This Row],[Coluna2]])/360)*Table1[[#This Row],[vl]] -> 12145.183
A21: ANALISE URBANISTICA E AMBIENTAL (REGULATORIO) | B21: 5.1 | C21: 2023 | D21: janeiro | E21: =Table1[[#This Row],[Despesas]]*1000 -> 5100 | F21: 44927 | G21: =$G$2 -> 45978 | H21: {=[15]!CalculateINPC(Table1[[#This Row],[Coluna2]],Table1[[#This Row],[Coluna3]],-1)*Table1[[#This Row],[vl]]} -> 5743.4404 | I21: =1.3^((Table1[[#This Row],[Coluna3]]-Table1[[#This Row],[Coluna2]])/360)*Table1[[#This Row],[vl]] -> 10970.375
A22: DESPACHANTES E DILIGENTE (REGULATORIO) | B22: 5.1 | C22: 2022 | D22: julho | E22: =Table1[[#This Row],[Despesas]]*1000 -> 5100 | F22: 44743 | G22: =$G$2 -> 45978 | H22: {=[15]!CalculateINPC(Table1[[#This Row],[Coluna2]],Table1[[#This Row],[Coluna3]],-1)*Table1[[#This Row],[vl]]} -> 5760.8704 | I22: =1.3^((Table1[[#This Row],[Coluna3]]-Table1[[#This Row],[Coluna2]])/360)*Table1[[#This Row],[vl]] -> 12544.668
A23: REEMBOLSOS DE ADVOGADOS | B23: 4.66534 | C23: 2025 | D23: março | E23: =Table1[[#This Row],[Despesas]]*1000 -> 4665.34 | F23: 45717 | G23: =$G$2 -> 45978 | H23: {=[15]!CalculateINPC(Table1[[#This Row],[Coluna2]],Table1[[#This Row],[Coluna3]],-1)*Table1[[#This Row],[vl]]} -> 4765.0548 | I23: =1.3^((Table1[[#This Row],[Coluna3]]-Table1[[#This Row],[Coluna2]])/360)*Table1[[#This Row],[vl]] -> 5642.7685
A24: MATRÍCULAS E CERTIDÕES | B24: 4.53523 | C24: 2023 | D24: novembro | E24: =Table1[[#This Row],[Despesas]]*1000 -> 4535.23 | F24: 45231 | G24: =$G$2 -> 45978 | H24: {=[15]!CalculateINPC(Table1[[#This Row],[Coluna2]],Table1[[#This Row],[Coluna3]],-1)*Table1[[#This Row],[vl]]} -> 4956.8945 | I24: =1.3^((Table1[[#This Row],[Coluna3]]-Table1[[#This Row],[Coluna2]])/360)*Table1[[#This Row],[vl]] -> 7816.8499
A25: PERICIAS E AVALIAÇÕES | B25: 4.11 | C25: 2023 | D25: maio | E25: =Table1[[#This Row],[Despesas]]*1000 -> 4110 | F25: 45047 | G25: =$G$2 -> 45978 | H25: {=[15]!CalculateINPC(Table1[[#This Row],[Coluna2]],Table1[[#This Row],[Coluna3]],-1)*Table1[[#This Row],[vl]]} -> 4519.1133 | I25: =1.3^((Table1[[#This Row],[Coluna3]]-Table1[[#This Row],[Coluna2]])/360)*Table1[[#This Row],[vl]] -> 8100.5031
A26: REEMBOLSOS DE ADVOGADOS | B26: 3.9517 | C26: 2022 | D26: setembro | E26: =Table1[[#This Row],[Despesas]]*1000 -> 3951.7 | F26: 44805 | G26: =$G$2 -> 45978 | H26: {=[15]!CalculateINPC(Table1[[#This Row],[Coluna2]],Table1[[#This Row],[Coluna3]],-1)*Table1[[#This Row],[vl]]} -> 4504.6818 | I26: =1.3^((Table1[[#This Row],[Coluna3]]-Table1[[#This Row],[Coluna2]])/360)*Table1[[#This Row],[vl]] -> 9290.7204
A27: REEMBOLSOS DE ADVOGADOS | B27: 3.8893 | C27: 2025 | D27: janeiro | E27: =Table1[[#This Row],[Despesas]]*1000 -> 3889.3 | F27: 45658 | G27: =$G$2 -> 45978 | H27: {=[15]!CalculateINPC(Table1[[#This Row],[Coluna2]],Table1[[#This Row],[Coluna3]],-1)*Table1[[#This Row],[vl]]} -> 4031.2211 | I27: =1.3^((Table1[[#This Row],[Coluna3]]-Table1[[#This Row],[Coluna2]])/360)*Table1[[#This Row],[vl]] -> 4910.8246
A28: MATRÍCULAS E CERTIDÕES | B28: 3.85697 | C28: 2025 | D28: janeiro | E28: =Table1[[#This Row],[Despesas]]*1000 -> 3856.97 | F28: 45658 | G28: =$G$2 -> 45978 | H28: {=[15]!CalculateINPC(Table1[[#This Row],[Coluna2]],Table1[[#This Row],[Coluna3]],-1)*Table1[[#This Row],[vl]]} -> 3997.7114 | I28: =1.3^((Table1[[#This Row],[Coluna3]]-Table1[[#This Row],[Coluna2]])/360)*Table1[[#This Row],[vl]] -> 4870.0031
A29: PERICIAS E AVALIAÇÕES | B29: 3.82498 | C29: 2023 | D29: novembro | E29: =Table1[[#This Row],[Despesas]]*1000 -> 3824.98 | F29: 45231 | G29: =$G$2 -> 45978 | H29: {=[15]!CalculateINPC(Table1[[#This Row],[Coluna2]],Table1[[#This Row],[Coluna3]],-1)*Table1[[#This Row],[vl]]} -> 4180.6088 | I29: =1.3^((Table1[[#This Row],[Coluna3]]-Table1[[#This Row],[Coluna2]])/360)*Table1[[#This Row],[vl]] -> 6592.6744
A30: PERICIAS E AVALIAÇÕES | B30: 3.42 | C30: 2022 | D30: julho | E30: =Table1[[#This Row],[Despesas]]*1000 -> 3420 | F30: 44743 | G30: =$G$2 -> 45978 | H30: {=[15]!CalculateINPC(Table1[[#This Row],[Coluna2]],Table1[[#This Row],[Coluna3]],-1)*Table1[[#This Row],[vl]]} -> 3863.1719 | I30: =1.3^((Table1[[#This Row],[Coluna3]]-Table1[[#This Row],[Coluna2]])/360)*Table1[[#This Row],[vl]] -> 8412.3069
... A185: SISTEMAS DE BUSCA (SERASA, UPMINER, API, DIGESTO) | B185: 0.002 | C185: 2025 | D185: maio | E185: =Table1[[#This Row],[Despesas]]*1000 -> 2 | F185: 45778 | G185: =$G$2 -> 45978 | H185: {=[15]!CalculateINPC(Table1[[#This Row],[Coluna2]],Table1[[#This Row],[Coluna3]],-1)*Table1[[#This Row],[vl]]} -> 2.022674 | I185: =1.3^((Table1[[#This Row],[Coluna3]]-Table1[[#This Row],[Coluna2]])/360)*Table1[[#This Row],[vl]] -> 2.3138322

Sheet Planilha1
A2: NPL | G2: SPE
A3: Soma de Líquido | B3: Rótulos de Coluna | G3: Rótulos de Linha | H3: Soma de Líquido
A4: Rótulos de Linha | B4: Despesa | C4: Investimento | D4: Total Geral | G4: IPTU - CUSTO REGULARIZACAO | H4: 1485369.9
A5: IPTU E TAXA DE LIXO | B5: 50259.31 | C5: 2012379.9 | D5: 2062639.2 | G5: ITBI | H5: 516131.47
A6: OUTRAS DESPESAS COM ATIVOS | B6: 934.94 | C6: 1474221.8 | D6: 1475156.7 | G6: REGISTROS E AVERBAÇÕES | H6: 90251.78
A7: HONORÁRIOS (OUTROS TIPOS) | B7: 917578.64 | D7: 917578.64 | G7: IPTU E TAXA DE LIXO | H7: 81021.24
A8: HONORÁRIOS | B8: 303653.64 | D8: 303653.64 | G8: DESPACHANTES E DILIGENTES | H8: 12028.47
A9: PERICIAS E AVALIAÇÕES | B9: 89553.666 | D9: 89553.666 | G9: ANALISE URBANISTICA E AMBIENTAL (REGULATORIO) | H9: 11460
A10: OUTRAS DESPESAS LEGAIS | B10: 3484.4 | C10: 24758 | D10: 28242.4 | G10: HONORÁRIOS | H10: 10000
A11: REEMBOLSOS DE ADVOGADOS | B11: 27569.22 | D11: 27569.22 | G11: LAUDOS DE AVALIAÇÃO | H11: 9210
A12: MATRÍCULAS E CERTIDÕES | B12: 21550.57 | D12: 21550.57 | G12: MANUTENÇÕES, DEMOLIÇÕES E REFORMAS | H12: 3139.68
A13: DESPACHANTES E DILIGENTES | B13: 19225.005 | D13: 19225.005 | G13: REGISTROS E AVERBAÇÕES CUSTO INTERNALIZAÇÃO | H13: 2328.38
A14: IPTU - CUSTO REGULARIZACAO | B14: 16480.33 | D14: 16480.33 | G14: CONTAS CONSUMO (ÁGUA, ENERGIA, GAS, TEL, INTERNET) | H14: 1976.12
A15: DESPACHANTES E DILIGENTE (REGULATORIO) | B15: 15937.8 | D15: 15937.8 | G15: CUSTAS JUDICIAIS | H15: 1554.84
A16: ANALISE URBANISTICA E AMBIENTAL (REGULATORIO) | B16: 14790 | D16: 14790 | G16: QUILOMETRAGEM | H16: 800.67
A17: PROCURAÇÕES E ESCRITURAS | B17: 11327.7 | D17: 11327.7 | G17: MATRÍCULAS E CERTIDÕES | H17: 643.37
A18: MATRÍCULAS E CERTIDÕES REGULATORIAS | B18: 9142.02 | D18: 9142.02 | G18: HONORARIOS CONTABILIDADE | H18: 432.69323
A19: QUILOMETRAGEM | B19: 7294.46 | D19: 7294.46 | G19: HOSPEDAGEM | H19: 311.21
A20: LOCALIZAÇÃO DE IMOVEIS | B20: 6791.04 | D20: 6791.04 | G20: ESTUDOS TÉCNICOS E RELATÓRIOS | H20: 182.24
A21: CUSTAS JUDICIAIS | B21: 6544.43 | D21: 6544.43 | G21: PEDAGIO | H21: 147.8
A22: OUTRAS DESPESAS COM VIAGENS | B22: 2880 | D22: 2880 | G22: CSRF - GUIA DE PAGAMENTO | H22: 94.35
... A26: ISS RETIDO - GUIA DE PAGAMENTO | B26: 2189.58 | D26: 2189.58 | G26: Total Geral | H26: 2227253.4
A27: LAUDOS DE AVALIAÇÃO | B27: 2060 | D27: 2060
A28: PERICIA / LAUDO JUDICIAL / ASSISTÊNCIA TECNICA | B28: 1845 | D28: 1845
A29: SISTEMAS DE BUSCA (SERASA, UPMINER, API, DIGESTO) | B29: 1641.0638 | D29: 1641.0638
A30: REEMBOLSO DE ADVOGADOS | B30: 1581.1 | D30: 1581.1
A31: TAXI / UBER | B31: 1353.11 | D31: 1353.11
A32: REGISTROS E AVERBAÇÕES | B32: 1008.12 | D32: 1008.12
A33: INSS - GUIA DE PAGAMENTO | B33: 955.83 | D33: 955.83
A34: IR FONTE - GUIA DE PAGAMENTO | B34: 910.62402 | D34: 910.62402
A35: HOSPEDAGEM | B35: 804.13 | D35: 804.13
A36: OBTENÇÃO DE CÓPIAS DE PROCESSOS | B36: 700 | D36: 700
A37: PEDAGIO | B37: 631.4 | D37: 631.4
A38: OUTRAS DESPESAS COM PESQUISA DE BENS | B38: 461.99 | D38: 461.99
... A44: ESTACIONAMENTO | B44: 89 | D44: 89
A45: Total Geral | B45: 1550332.6 | C45: 3511359.7 | D45: 5061692.3

Sheet Despesas - NPL
C1: Despesa | H1: =SUMIF($C$6:$C$335,$C$1,$H$6:$H$335) -> 1550332.6 | J1: =SUMIF($C$6:$C$335,$C$1,$J$6:$J$335) -> 1629995.1 | K1: =SUMIF($C$6:$C$335,$C$1,$K$6:$K$335) -> 2473973 | L1: =SUMIF($C$6:$C$335,$C$1,$L$6:$L$335) -> 1773514.3
C2: Investimento | H2: =SUMIF($C$6:$C$335,$C$2,$H$6:$H$335) -> 3511359.7 | J2: =SUMIF($C$6:$C$335,$C$2,$J$6:$J$335) -> 4924783.3 | K2: =SUMIF($C$6:$C$335,$C$2,$K$6:$K$335) -> 23729063 | L2: =SUMIF($C$6:$C$335,$C$2,$L$6:$L$335) -> 5972086.1
B4: =Contrato!$C$2 -> 45978 | H4: =SUM(H6:H335) -> 5061692.3 | J4: =SUM(J6:J335) -> 6554778.4 | K4: =SUM(K6:K335) -> 26203036 | L4: =SUM(L6:L335) -> 7745600.4
B5: Tipo de baixa | C5: Tipo | D5: Pagamento | E5: Emissão | F5: Total Título | G5: Bruto | H5: Líquido | I5: Data atual | J5: Vl At. INPC | K5: Vl At. 30% | L5: Vl At. CDI% | M5: Título | N5: Credor | O5: Cod. P.F. | P5: Descrição P.F | Q5: Cod. C.C. | R5: Descrição C.C. | S5: Cod. A.N. | T5: Descrição A.N. | U5: Observação | V5: Cod. Banco | W5: Nome Banco | X5: Descrição Doc. | Y5: Número Doc.
B6: *** Pagamento *** | C6: Despesa | D6: 45078 | E6: 45071 | F6: 800 | G6: 800 | H6: 800 | I6: =$B$4 -> 45978 | J6: {=[15]!CalculateINPC(D6,I6,-1)*H6} -> 876.47702 | K6: =J6*1.3^((I6-D6)/360) -> 1688.8805 | L6: {=[15]!CalculateDICetip(D6,I6,1)*H6} -> 1069.455 | M6: 174426 | N6: FELSBERG E PEDRETTI ADVOGADOS E CONSULTORES LEGAIS | O6: 2.20.04.02 | P6: REEMBOLSOS DE ADVOGADOS | Q6: 10027 | R6: 0015292_COZAC_FALENCIA | S6: 44 | T6: FALENCIA E RJ_TOMBADO | U6: REEMBOLSO DE DESPESA APROVADAS NO PIPEFY CARD 4185 REF. AO CASO: COZAC_FALENCIA | V6: 13013697-3 | W6: SANTANDER - ENFORCE | X6: NOTA DE DEBITO | Y6: 169312
B7: *** Pagamento *** | C7: Despesa | D7: 45078 | E7: 45057 | F7: 100 | G7: 100 | H7: 100 | I7: =$B$4 -> 45978 | J7: {=[15]!CalculateINPC(D7,I7,-1)*H7} -> 109.55963 | K7: =J7*1.3^((I7-D7)/360) -> 211.11006 | L7: {=[15]!CalculateDICetip(D7,I7,1)*H7} -> 133.68188 | M7: 174392 | N7: FELSBERG E PEDRETTI ADVOGADOS E CONSULTORES LEGAIS | O7: 2.20.04.02 | P7: REEMBOLSOS DE ADVOGADOS | Q7: 10027 | R7: 0015292_COZAC_FALENCIA | S7: 44 | T7: FALENCIA E RJ_TOMBADO | U7: REEMBOLSO DE DESPESAS APROVADAS NO PIPEFY CARD 4060 REF. AO CASO COZAC_FALENCIA | V7: 13013697-3 | W7: SANTANDER - ENFORCE | X7: NOTA DE DEBITO | Y7: 170497
B8: *** Pagamento *** | C8: Despesa | D8: 44743 | E8: 44743 | F8: 1297.47 | G8: 1297.47 | H8: 1297.47 | I8: =$B$4 -> 45978 | J8: {=[15]!CalculateINPC(D8,I8,-1)*H8} -> 1465.5993 | K8: =J8*1.3^((I8-D8)/360) -> 3604.9916 | L8: {=[15]!CalculateDICetip(D8,I8,1)*H8} -> 1948.523 | M8: 152297 | N8: GOVERNO DO ESTADO DE SÃO PAULO - SECRETARIA DA FAZENDA | O8: 2.20.04.04 | P8: CUSTAS JUDICIAIS | Q8: 10027 | R8: 0015292_COZAC_FALENCIA | S8: 44 | T8: FALENCIA E RJ_TOMBADO | U8: CUSTAS DE PREPARO DE APELACAO QUE SERA INTERPOSTA CONTRA A SENTENCA PROFERIDA NOS AUTOS DO INCIDENTE DE HABILIDACAO DE CREDITO ENVOLVENDO O SINDICO E A MASSA FALIDA DA COZAC N. 0006293-25.2020.8.26.0506 - 548663201 PIPEFY | V8: 13013697-3 | W8: SANTANDER - ENFORCE | X8: GUIA PARA RECOLHIMENTO DE IMPOSTOS | Y8: 220590074051094
B9: *** Pagamento *** | C9: Despesa | D9: 44805 | E9: 44799 | F9: 66.65 | G9: 66.65 | H9: 66.65 | I9: =$B$4 -> 45978 | J9: {=[15]!CalculateINPC(D9,I9,-1)*H9} -> 75.976678 | K9: =J9*1.3^((I9-D9)/360) -> 178.62643 | L9: {=[15]!CalculateDICetip(D9,I9,1)*H9} -> 97.923786 | M9: 156817 | N9: OPERADOR NACIONAL DO SISTEMA DE REGISTRO ELETRONICO DE IMOVEIS ( ONR ) | O9: 2.20.02.03 | P9: REGISTROS E AVERBAÇÕES | Q9: 10027 | R9: 0015292_COZAC_FALENCIA | S9: 44 | T9: FALENCIA E RJ_TOMBADO | U9: Averbacao da cessao de credito do BB para Travessia VIII do caso Cozac - Mat 72157 - 571667779 - Pipefy | V9: 13013697-3 | W9: SANTANDER - ENFORCE | X9: BOLETO | Y9: 61351049
B10: *** Pagamento *** | C10: Despesa | D10: 45901 | E10: 45883 | F10: 3000 | G10: 73.18 | H10: 73.18 | I10: =$B$4 -> 45978 | J10: {=[15]!CalculateINPC(D10,I10,-1)*H10} -> 73.582587 | K10: =J10*1.3^((I10-D10)/360) -> 77.829864 | L10: {=[15]!CalculateDICetip(D10,I10,1)*H10} -> 75.432322 | M10: 268132 | N10: R.P.D. - DOCUMENTOS, APOIO EMPRESARIAL E NEGOCIOS LTDA | O10: 2.20.02.11 | P10: MATRÍCULAS E CERTIDÕES REGULATORIAS | Q10: 10027 | R10: 0015292_COZAC_FALENCIA | S10: 44 | T10: FALENCIA E RJ_TOMBADO | U10: REEMBOLSAVEIS: 30877 JESTOR Trata-se do pagamento referente a licenca da plataforma docket do mes de julho, utilizada para analise e gestao de documento, referente aos casos em anexo.RETENCAO OK | V10: 13013697-3 | W10: SANTANDER - ENFORCE | X10: NOTA FISCAL DE SERVIÇOS | Y10: 33435
B11: *** Pagamento *** | C11: Despesa | D11: 43923 | E11: 43902 | F11: 5500 | G11: 180 | H11: 180 | I11: =$B$4 -> 45978 | J11: {=[15]!CalculateINPC(D11,I11,-1)*H11} -> 248.09673 | K11: =J11*1.3^((I11-D11)/360) -> 1109.2966 | L11: {=[15]!CalculateDICetip(D11,I11,1)*H11} -> 302.6689 | M11: 87902 | N11: NELSON HENRIQUE SANTANA ALEXANDRE 40012558800 | O11: 2.20.02.10 | P11: OUTRAS DESPESAS REGULATORIAS | Q11: 10027 | R11: 0015292_COZAC_FALENCIA | S11: 44 | T11: FALENCIA E RJ_TOMBADO | U11: REFERENTE SERVICO DE MOTO BOY - REF: A JAN / FEV -2020 | V11: 13013697-3 | W11: SANTANDER - ENFORCE | X11: NOTA FISCAL DE SERVIÇOS | Y11: 57
B12: *** Pagamento *** | C12: Despesa | D12: 44806 | E12: 44803 | F12: 5663.85 | G12: 5663.85 | H12: 5663.85 | I12: =$B$4 -> 45978 | J12: {=[15]!CalculateINPC(D12,I12,-1)*H12} -> 6456.4218 | K12: =J12*1.3^((I12-D12)/360) -> 15168.436 | L12: {=[15]!CalculateDICetip(D12,I12,1)*H12} -> 8317.2407 | M12: 156908 | N12: SEXTO TABELIAO DE NOTAS DA COMARCA DE CAMPINAS-SP | O12: 2.20.05.02 | P12: PROCURAÇÕES E ESCRITURAS | Q12: 10027 | R12: 0015292_COZAC_FALENCIA | S12: 44 | T12: FALENCIA E RJ_TOMBADO | U12: Lavratura Escritura da Cessao de Credito do caso COZAC - 571693725 PIPEFY | V12: 13013697-3 | W12: SANTANDER - ENFORCE | X12: RECIBO | Y12: 23558
B13: *** Pagamento *** | C13: Despesa | D13: 44806 | E13: 44799 | F13: 66.65 | G13: 66.65 | H13: 66.65 | I13: =$B$4 -> 45978 | J13: {=[15]!CalculateINPC(D13,I13,-1)*H13} -> 75.976678 | K13: =J13*1.3^((I13-D13)/360) -> 178.4963 | L13: {=[15]!CalculateDICetip(D13,I13,1)*H13} -> 97.874077 | M13: 156899 | N13: OPERADOR NACIONAL DO SISTEMA DE REGISTRO ELETRONICO DE IMOVEIS ( ONR ) | O13: 2.20.02.03 | P13: REGISTROS E AVERBAÇÕES | Q13: 10027 | R13: 0015292_COZAC_FALENCIA | S13: 44 | T13: FALENCIA E RJ_TOMBADO | U13: Averbacao da cessao de credito do BB para Travessia VIII do caso Cozac - Mat 5103 - 572358901 PIPEFY | V13: 13013697-3 | W13: SANTANDER - ENFORCE | X13: BOLETO | Y13: 61351053
B14: *** Pagamento *** | C14: Despesa | D14: 45902 | E14: 45883 | F14: 50695.2 | G14: 568.7 | H14: 568.7 | I14: =$B$4 -> 45978 | J14: {=[15]!CalculateINPC(D14,I14,-1)*H14} -> 571.82861 | K14: =J14*1.3^((I14-D14)/360) -> 604.39461 | L14: {=[15]!CalculateDICetip(D14,I14,1)*H14} -> 585.88035 | M14: 268144 | N14: R.P.D. - DOCUMENTOS, APOIO EMPRESARIAL E NEGOCIOS LTDA | O14: 2.20.02.11 | P14: MATRÍCULAS E CERTIDÕES REGULATORIAS | Q14: 10027 | R14: 0015292_COZAC_FALENCIA | S14: 44 | T14: FALENCIA E RJ_TOMBADO | U14: REEMBOLSAVEIS: 30876 JESTORTrata-se do pagamento referente a licenca da plataforma docket do mes de julho, utilizada para analise e gestao de documento, referente aos casos em anexo.RETENCAO OK | V14: 13013697-3 | W14: SANTANDER - ENFORCE | X14: NOTA FISCAL DE SERVIÇOS | Y14: 33432
B15: *** Pagamento *** | C15: Despesa | D15: 45811 | E15: 45793 | F15: 18582 | G15: 1176 | H15: 1176 | I15: =$B$4 -> 45978 | J15: {=[15]!CalculateINPC(D15,I15,-1)*H15} -> 1185.1836 | K15: =J15*1.3^((I15-D15)/360) -> 1338.575 | L15: {=[15]!CalculateDICetip(D15,I15,1)*H15} -> 1254.8948 | M15: 254480 | N15: DINIZ E FRAIHA SOCIEDADE DE ADVOGADOS | O15: 2.20.05.11 | P15: ANALISE DE DOCUMENTOS (ELIOT) | Q15: 10027 | R15: 0015292_COZAC_FALENCIA | S15: 44 | T15: FALENCIA E RJ_TOMBADO | U15: REMBOLSAVEIS - 28638 JESTORNF referente a servicos de analise registral.REF. 04/2025RETENCAO OK | V15: 13013697-3 | W15: SANTANDER - ENFORCE | X15: NOTA FISCAL DE SERVIÇOS | Y15: 1015
B16: *** Pagamento *** | C16: Despesa | D16: 45811 | E16: 45778 | F16: 7330.27 | G16: 75.29 | H16: 75.29 | I16: =$B$4 -> 45978 | J16: {=[15]!CalculateINPC(D16,I16,-1)*H16} -> 75.877956 | K16: =J16*1.3^((I16-D16)/360) -> 85.698393 | L16: {=[15]!CalculateDICetip(D16,I16,1)*H16} -> 80.341013 | M16: 255141 | N16: UBER DO BRASIL TECNOLOGIA LTDA. | O16: 2.20.01.09 | P16: TAXI / UBER | Q16: 10027 | R16: 0015292_COZAC_FALENCIA | S16: 44 | T16: FALENCIA E RJ_TOMBADO | U16: ADM | REEMBOLSAVEIS - 28432 JESTORFatura mensal da Uber - Abril25 | V16: 13013697-3 | W16: SANTANDER - ENFORCE | X16: FATURA | Y16: D32522
B17: *** Pagamento *** | C17: Despesa | D17: 45110 | E17: 45082 | F17: 86989.25 | G17: 130.19 | H17: 130.19 | I17: =$B$4 -> 45978 | J17: {=[15]!CalculateINPC(D17,I17,-1)*H17} -> 142.77839 | K17: =J17*1.3^((I17-D17)/360) -> 268.77729 | L17: {=[15]!CalculateDICetip(D17,I17,1)*H17} -> 172.19454 | M17: 176020 | N17: 4MTI SOLUÇÕES LTDA ME | O17: 2.20.05.04 | P17: SISTEMAS DE BUSCA (SERASA, UPMINER, API, DIGESTO) | Q17: 10027 | R17: 0015292_COZAC_FALENCIA | S17: 44 | T17: FALENCIA E RJ_TOMBADO | U17: Maio/23 - 63.000,00 (mensalidade) + 23.989,25 (48.865 consultas) = 86.989,25 - 730600837 PIPEFY - RETENCAO OK | V17: 13013697-3 | W17: SANTANDER - ENFORCE | X17: NOTA FISCAL DE SERVIÇOS | Y17: 2023/122
... B335: *** Pagamento *** | C335: Despesa | D335: 45905 | E335: 45890 | F335: 917578.64 | G335: 917578.64 | H335: 917578.64 | I335: =$B$4 -> 45978 | J335: {=[15]!CalculateINPC(D335,I335,-1)*H335} -> 922626.54 | K335: =J335*1.3^((I335-D335)/360) -> 973040.96 | L335: {=[15]!CalculateDICetip(D335,I335,1)*H335} -> 943736.83 | M335: 267952 | N335: FELSBERG E PEDRETTI ADVOGADOS E CONSULTORES LEGAIS | O335: 2.20.04.14 | P335: HONORÁRIOS (OUTROS TIPOS) | Q335: 18799 | R335: 0015292_COZAC_FALENCIA | S335: 243 | T335: FALENCIA E RJ_TOMBADO | U335: Pagamento devido a titulo de honorarios de Exito para o Escritorio FELSBERG conforme aprovado em comite com OC (ATA anexo), com base nos 17MM da avaliacao interna (Enforce) dos imoveis, descontando eventuais debitos (contrato anexo).Pagamento Submetido. Numero de Solicitacao CAPG_299913 | V335: DIRETAS | W335: DIRETAS | X335: NOTA FISCAL DE SERVIÇOS | Y335: 47231

Sheet Despesas - SPE
A2: =Contrato!$C$2 -> 45978 | G2: =SUM(G4:G545) -> 2227253.4 | I2: =SUM(I4:I545) -> 2230145 | J2: =SUM(J4:J545) -> 2291142 | K2: =SUM(K4:K545) -> 2260325.1
A3: Tipo de baixa | B3: Tipo | C3: Pagamento | D3: Emissão | E3: Total Título | F3: Bruto | G3: Líquido | H3: Data atual | I3: Vl At. INPC | J3: Vl At. 30% | K3: Vl At. CDI | L3: Título | M3: Credor | N3: Cod. P.F. | O3: Descrição P.F | P3: Cod. C.C. | Q3: Descrição C.C. | R3: Cod. A.N. | S3: Descrição A.N. | T3: Observação | U3: Cod. Banco | V3: Nome Banco | W3: Descrição Doc. | X3: Número Doc.
A4: *** Pagamento *** | B4: Despesa | C4: 45901 | D4: 45870 | E4: 192.3 | F4: 77.2 | G4: 77.2 | H4: =$A$2 -> 45978 | I4: {=G4*[15]!CalculateINPC(C4,H4,-1)} -> 77.624703 | J4: =G4*1.3^((H4-C4)/360) -> 81.656078 | K4: {=[15]!CalculateDICetip(C4,H4,1)*G4} -> 79.576048 | L4: 273258 | M4: OPERADOR NACIONAL DO SISTEMA DE REGISTRO ELETRONICO DE IMOVEIS ( ONR ) | N4: 2.20.05.01 | O4: MATRÍCULAS E CERTIDÕES | P4: 27143 | Q4: 818247_COZAC_MAT_23299 - Ribeirão Preto, SP | R4: 4 | S4: COZAC - SPE COMERCIAL | T4: PRESTACAO DE CONTAS ARISP - TIME REGULATORIOBAIXAR SOMENTE COM DATA DE SETEMBROTITULO REPLICADO PAGO PELO TITULO 268183 | U4: CAIXA | V4: CAIXA | W4: PRESTAÇÃO DE CONTAS | X4: ARISP - SPE.02
A5: *** Pagamento *** | B5: Despesa | C5: 45901 | D5: 45870 | E5: 192.3 | F5: 77.2 | G5: 77.2 | H5: =$A$2 -> 45978 | I5: {=G5*[15]!CalculateINPC(C5,H5,-1)} -> 77.624703 | J5: =G5*1.3^((H5-C5)/360) -> 81.656078 | K5: {=[15]!CalculateDICetip(C5,H5,1)*G5} -> 79.576048 | L5: 273258 | M5: OPERADOR NACIONAL DO SISTEMA DE REGISTRO ELETRONICO DE IMOVEIS ( ONR ) | N5: 2.20.05.01 | O5: MATRÍCULAS E CERTIDÕES | P5: 27159 | Q5: 790175_COZAC_MAT_76858 - Ribeirão Preto, SP | R5: 4 | S5: COZAC - SPE COMERCIAL | T5: PRESTACAO DE CONTAS ARISP - TIME REGULATORIOBAIXAR SOMENTE COM DATA DE SETEMBROTITULO REPLICADO PAGO PELO TITULO 268183 | U5: CAIXA | V5: CAIXA | W5: PRESTAÇÃO DE CONTAS | X5: ARISP - SPE.02
A6: *** Pagamento *** | B6: Despesa | C6: 45903 | D6: 45896 | E6: 20261.52 | F6: 18.235368 | G6: 18.235368 | H6: =$A$2 -> 45978 | I6: {=G6*[15]!CalculateINPC(C6,H6,-1)} -> 18.335687 | J6: =G6*1.3^((H6-C6)/360) -> 19.259842 | K6: {=[15]!CalculateDICetip(C6,H6,1)*G6} -> 18.775905 | L6: 268023 | M6: CONTACTUS SERVIÇOS CONTABEIS LTDA | N6: 2.20.03.19 | O6: HONORARIOS CONTABILIDADE | P6: 29661 | Q6: GENÉRICO_COZAC | R6: 4 | S6: COZAC - SPE COMERCIAL | T6: HONORARIO REFERENTE 08/2025 - BASE DE CALCULO ESTOQUE 31/07/2025 - 428 UNIDADES | U6: 13016842-2 | V6: SANTANDER - SPE COMERCIAL | W6: NOTA FISCAL DE SERVIÇOS | X6: 10230
A7: *** Pagamento *** | B7: Despesa | C7: 45903 | D7: 45897 | E7: 6191.74 | F7: 5.572566 | G7: 5.572566 | H7: =$A$2 -> 45978 | I7: {=G7*[15]!CalculateINPC(C7,H7,-1)} -> 5.6032225 | J7: =G7*1.3^((H7-C7)/360) -> 5.8856363 | K7: {=[15]!CalculateDICetip(C7,H7,1)*G7} -> 5.7377492 | L7: 267044 | M7: CONTACTUS ACESSORIA CONTÁBIL LTDA | N7: 2.20.03.19 | O7: HONORARIOS CONTABILIDADE | P7: 29661 | Q7: GENÉRICO_COZAC | R7: 4 | S7: COZAC - SPE COMERCIAL | T7: HONORARIO MENSAL 08/2025 | U7: 13016842-2 | V7: SANTANDER - SPE COMERCIAL | W7: NOTA FISCAL DE SERVIÇOS | X7: 11463
A8: *** Pagamento *** | B8: Despesa | C8: 45933 | D8: 45922 | E8: 19598.76 | F8: 84.274668 | G8: 84.274668 | H8: =$A$2 -> 45978 | I8: {=G8*[15]!CalculateINPC(C8,H8,-1)} -> 84.299895 | J8: =G8*1.3^((H8-C8)/360) -> 87.084321 | K8: {=[15]!CalculateDICetip(C8,H8,1)*G8} -> 85.726948 | L8: 272962 | M8: CONTACTUS SERVIÇOS CONTABEIS LTDA | N8: 2.20.03.19 | O8: HONORARIOS CONTABILIDADE | P8: 29661 | Q8: GENÉRICO_COZAC | R8: 4 | S8: COZAC - SPE COMERCIAL | T8: HONORARIO REFERENTE 09/2025 - BASE DE CALCULO ESTOQUE 31/08/2025 - 414 UNIDADES | U8: 13016842-2 | V8: SANTANDER - SPE COMERCIAL | W8: NOTA FISCAL DE SERVIÇOS | X8: 10328
A9: *** Pagamento *** | B9: Despesa | C9: 45933 | D9: 45925 | E9: 6191.74 | F9: 26.624482 | G9: 26.624482 | H9: =$A$2 -> 45978 | I9: {=G9*[15]!CalculateINPC(C9,H9,-1)} -> 26.632452 | J9: =G9*1.3^((H9-C9)/360) -> 27.512122 | K9: {=[15]!CalculateDICetip(C9,H9,1)*G9} -> 27.083294 | L9: 272990 | M9: CONTACTUS ACESSORIA CONTÁBIL LTDA | N9: 2.20.03.19 | O9: HONORARIOS CONTABILIDADE | P9: 29661 | Q9: GENÉRICO_COZAC | R9: 4 | S9: COZAC - SPE COMERCIAL | T9: HONORARIO MENSAL 09/2025 | U9: 13016842-2 | V9: SANTANDER - SPE COMERCIAL | W9: NOTA FISCAL DE SERVIÇOS | X9: 11516
A10: *** Pagamento *** | B10: Despesa | C10: 45966 | D10: 45954 | E10: 6191.74 | F10: 27.86283 | G10: 27.86283 | H10: =$A$2 -> 45978 | I10: {=G10*[15]!CalculateINPC(C10,H10,-1)} -> 27.86283 | J10: =G10*1.3^((H10-C10)/360) -> 28.107572 | K10: {=[15]!CalculateDICetip(C10,H10,1)*G10} -> 27.985956 | L10: 276951 | M10: CONTACTUS ACESSORIA CONTÁBIL LTDA | N10: 2.20.03.19 | O10: HONORARIOS CONTABILIDADE | P10: 29661 | Q10: GENÉRICO_COZAC | R10: 4 | S10: COZAC - SPE COMERCIAL | T10: HONORARIO MENSAL 10/2025 | U10: 13016842-2 | V10: SANTANDER - SPE COMERCIAL | W10: NOTA FISCAL DE SERVIÇOS | X10: 11645
A11: *** Pagamento *** | B11: Despesa | C11: 45966 | D11: 45925 | E11: 273.4 | F11: 20.88 | G11: 20.88 | H11: =$A$2 -> 45978 | I11: {=G11*[15]!CalculateINPC(C11,H11,-1)} -> 20.88 | J11: =G11*1.3^((H11-C11)/360) -> 21.063406 | K11: {=[15]!CalculateDICetip(C11,H11,1)*G11} -> 20.972269 | L11: 272410 | M11: PREFEITURA MUNICIPAL DE RIBEIRÃO PRETO | N11: 2.20.03.02 | O11: IPTU E TAXA DE LIXO | P11: 27162 | Q11: 790201_COZAC_MAT_96158 - Ribeirão Preto, SP | R11: 4 | S11: COZAC - SPE COMERCIAL | T11: IPTU 2025 - 790201_COZAC_MAT_96158 - Ribeirao Preto, SP | U11: 13016842-2 | V11: SANTANDER - SPE COMERCIAL | W11: GUIA PARA RECOLHIMENTO DE IMPOSTOS | X11: 79839_2025
A12: *** Pagamento *** | B12: Despesa | C12: 45966 | D12: 45954 | E12: 19958.16 | F12: 89.81172 | G12: 89.81172 | H12: =$A$2 -> 45978 | I12: {=G12*[15]!CalculateINPC(C12,H12,-1)} -> 89.81172 | J12: =G12*1.3^((H12-C12)/360) -> 90.600611 | K12: {=[15]!CalculateDICetip(C12,H12,1)*G12} -> 90.208598 | L12: 276989 | M12: CONTACTUS SERVIÇOS CONTABEIS LTDA | N12: 2.20.03.19 | O12: HONORARIOS CONTABILIDADE | P12: 29661 | Q12: GENÉRICO_COZAC | R12: 4 | S12: COZAC - SPE COMERCIAL | T12: HONORARIO REFERENTE 10/2025 - BASE DE CALCULO ESTOQUE 30/09/2025 - 411 UNIDADES | U12: 13016842-2 | V12: SANTANDER - SPE COMERCIAL | W12: NOTA FISCAL DE SERVIÇOS | X12: 10579
A13: *** Pagamento *** | B13: Despesa | C13: 45967 | D13: 45967 | E13: 35684.88 | F13: 30403.82 | G13: 30403.82 | H13: =$A$2 -> 45978 | I13: {=G13*[15]!CalculateINPC(C13,H13,-1)} -> 30403.82 | J13: =G13*1.3^((H13-C13)/360) -> 30648.537 | K13: {=[15]!CalculateDICetip(C13,H13,1)*G13} -> 30521.348 | L13: 278941 | M13: PREFEITURA MUNICIPAL DE RIBEIRÃO PRETO | N13: 2.20.03.02 | O13: IPTU E TAXA DE LIXO | P13: 27143 | Q13: 818247_COZAC_MAT_23299 - Ribeirão Preto, SP | R13: 4 | S13: COZAC - SPE COMERCIAL | T13: IPTU 2025 - 818247_COZAC_MAT_23299 - Ribeirao Preto, SP | U13: 13016842-2 | V13: SANTANDER - SPE COMERCIAL | W13: GUIA PARA RECOLHIMENTO DE IMPOSTOS | X13: 109077_2025
A14: *** Pagamento *** | B14: Despesa | C14: 45967 | D14: 45967 | E14: 3330.33 | F14: 3330.33 | G14: 3330.33 | H14: =$A$2 -> 45978 | I14: {=G14*[15]!CalculateINPC(C14,H14,-1)} -> 3330.33 | J14: =G14*1.3^((H14-C14)/360) -> 3357.1355 | K14: {=[15]!CalculateDICetip(C14,H14,1)*G14} -> 3343.2036 | L14: 278997 | M14: OPERADOR NACIONAL DO SISTEMA DE REGISTRO ELETRONICO DE IMOVEIS ( ONR ) | N14: 2.20.02.03 | O14: REGISTROS E AVERBAÇÕES | P14: 27156 | Q14: 818257_COZAC_MAT_83398 - Ribeirão Preto, SP | R14: 4 | S14: COZAC - SPE COMERCIAL | T14: PAGAMENTO REF. A CUSTAS PARA REGISTRO DA CARTE DE ADJUDICACAO - 818257_COZAC_MAT_83398 - Ribeirao Preto, SP - CARTEIRA COZAC - JESTOR 33083 | U14: 13016842-2 | V14: SANTANDER - SPE COMERCIAL | W14: BOLETO | X14: Mat. 83398
A15: *** Pagamento *** | B15: Despesa | C15: 45967 | D15: 45967 | E15: 3863.26 | F15: 3863.26 | G15: 3863.26 | H15: =$A$2 -> 45978 | I15: {=G15*[15]!CalculateINPC(C15,H15,-1)} -> 3863.26 | J15: =G15*1.3^((H15-C15)/360) -> 3894.355 | K15: {=[15]!CalculateDICetip(C15,H15,1)*G15} -> 3878.1937 | L15: 278990 | M15: OPERADOR NACIONAL DO SISTEMA DE REGISTRO ELETRONICO DE IMOVEIS ( ONR ) | N15: 2.20.02.03 | O15: REGISTROS E AVERBAÇÕES | P15: 27154 | Q15: 790204_COZAC_MAT_5104 - Ribeirão Preto, SP | R15: 4 | S15: COZAC - SPE COMERCIAL | T15: PAGAMENTO REF. A CUSTAS PARA REGISTRO DA CARTE DE ADJUDICACAO - 790204_COZAC_MAT_5104 - Ribeirao Preto, SP - CARTEIRA COZAC - JESTOR 33175 | U15: 13016842-2 | V15: SANTANDER - SPE COMERCIAL | W15: RECIBO | X15: mat. 5104
... A545: *** Pagamento *** | B545: Despesa | C545: 45961 | D545: 45960 | E545: 4507.64 | F545: 3280.06 | G545: 3280.06 | H545: =$A$2 -> 45978 | I545: {=G545*[15]!CalculateINPC(C545,H545,-1)} -> 3281.0419 | J545: =G545*1.3^((H545-C545)/360) -> 3320.9508 | K545: {=[15]!CalculateDICetip(C545,H545,1)*G545} -> 3300.0065 | L545: 277830 | M545: PREFEITURA MUNICIPAL DE RIBEIRÃO PRETO | N545: 2.20.03.15 | O545: IPTU - CUSTO REGULARIZACAO | P545: 27198 | Q545: 822568_COZAC_MAT_59250 - Ribeirão Preto, SP | R545: 4 | S545: COZAC | T545: PAGAMENTO REF. A REFIS IPTU - 822568_COZAC_MAT_59250 - Ribeirao Preto, SP - JESTOR 32990 | U545: 13017348-8 | V545: SANTANDER - ENF SPE RESIDENCIAL | W545: GUIA PARA RECOLHIMENTO DE IMPOSTOS | X545: 176875

Sheet Receitas
A1: CodigoDaEmpresa | B1: NomeDaEmpresa | C1: CodigoDoCentroDeCusto | D1: NomeDoCentroDeCusto | E1: CodigoDoCliente | F1: NomeDoCliente | G1: CodigoDoDocumento | H1: NumeroDoDocumento | I1: NomeDoDocumento | J1: NumeroDoTitulo | K1: NumeroDaParcela | L1: CodigoDoTipoDeCondicao | M1: NomeDoTipoDeCondicao | N1: NumeroDaUnidade | O1: CodigoDoPortador | P1: NomeDoPortador | Q1: CodigoDaOperacaoDeCobranca | R1: CodigoDoPlanoFinanceiroComMascara | S1: CodigoDoPlanoFinanceiro | T1: NomeDoPlanoFinanceiro | U1: NumeroDaContaCorrente | V1: NomeDaContaCorrente | W1: CodigoDaAreaDeNegocio | X1: NomeDaAreaDeNegocio | Y1: CodigoDaObra | Z1: NomeDaObra | AA1: CodigoDoProjeto | AB1: NomeDoProjeto | AC1: CodigoDoTipoDeNegocio | AD1: NomeDoTipoDeNegocio | AE1: CodigoDoMunicipio | AF1: NomeDoMunicipio | AG1: CodigoDoIndexador | AH1: NomeDoIndexador | AI1: DataDaBaixa | AJ1: DataDeVencimento | AK1: DataDeEmissao | AL1: BaixaTotalOuParcial | AM1: BaixaOuMovimentacao | AN1: CodigoDoTipoDeBaixa | AO1: NomeDoTipoDeBaixa | AP1: ObservacaoDoTitulo | AQ1: ObservacaoDaBaixa | AR1: ValorDaBaixa
A2: 55 | B2: ENF SPE COMERCIAL LTDA | C2: 27149 | D2: 818232_COZAC_MAT_72157 - Ribeirão Preto, SP | E2: 8137 | F2: ALFREDO PINTO DE LIMA ME (8137) | G2: CT | H2: JNX_22341 | I2: CONTRATO | J2: 18070 | K2: 1 | L2: AT | M2: Ato | N2: COZAC MAT 72157 Ribeirao Preto SP | O2: 1 | P2: CARTEIRA A | Q2: 0 | S2: 12002 | T2: RECEITA BRUTA - BNDU | U2: 291607-5 | V2: BTG 0030 BAAS - SPE COMERCIAL | AE2: 101 | AF2: RIBEIRÃO PRETO | AG2: 0 | AH2: REAL | AI2: 45945 | AJ2: 45945 | AK2: 45938 | AL2: T | AM2: B | AN2: 2 | AO2: Recebimento | AR2: 241607.9
A3: 55 | B3: ENF SPE COMERCIAL LTDA | C3: 27158 | D3: 818255_COZAC_MAT_62872 - Ribeirão Preto, SP | E3: 8137 | F3: ALFREDO PINTO DE LIMA ME (8137) | G3: CT | H3: JNX_22340 | I3: CONTRATO | J3: 18102 | K3: 1 | L3: AT | M3: Ato | N3: COZAC MAT62872 Ribeirao Preto SP | O3: 1 | P3: CARTEIRA A | Q3: 0 | S3: 12002 | T3: RECEITA BRUTA - BNDU | U3: 291607-5 | V3: BTG 0030 BAAS - SPE COMERCIAL | AE3: 101 | AF3: RIBEIRÃO PRETO | AG3: 0 | AH3: REAL | AI3: 45968 | AJ3: 45967 | AK3: 45960 | AL3: T | AM3: B | AN3: 2 | AO3: Recebimento | AR3: 68392.09
